Workbook
Name a: #REF!
Name AAA: #REF!
Name ATICA_DATA: #REF!
Name CAPE_DATA: #REF!
Name DicoRefFOTibco: #REF!
Name Field_Data_Types: #REF!
Name ListeMsg: #REF!
Name ListeMsg: #REF!
Name ListeMsg: #REF!
Name ListeTypeEntite: #REF!
Name Name: #REF!
Name TOTO: #REF!
Name ZoneDicoRefFO: #REF!
Name ZoneDicoRefFO: #REF!
Name ZoneDicoRefFO: #REF!

Sheet ChangeLog
A1: Version | B1: Auteur | C1: Date | D1: Domaine | E1: Description | F1: Origine
A2: 21.17 | B2: G.HARAGHI | C2: 46180 | D2: Acquisition | E2: Pour la donnée (250827114300): changement du libellé :"These messages are file action instructions (0360)." ==> "Number of messages in the file - File action instructions - 360" + Changement du mapping + Changement de type de "Max6NumericText" devient "Max10NumericText" Pour la donnée (250827114500): Changement du libellé "The number of messages that the file sender" ==> "Number of messages that the file sender can transmit without waiting for an acknowledgement message (0370)" + changement du mapping Pour la donnée (250827113500): Changement du mapping Pour la donnée (250827114100): Changement du mapping La donnée(250604103001) a été rendue obsolète La donnée (260605091000) qui est en doublon a été supprimée
A3: 21.17 | B3: B. Porcher | C3: 46181 | D3: Acquisition | E3: Creation de la donnée reservedUseData : 260608100200 // Transaction // transactionDetails // reservedUseData // ReservedUseDataType // DNS // // Data and structure usable for reserved field | F3: BK-9845
A4: 21.17 | B4: B. Porcher | C4: 46181 | D4: Acquisition | E4: Creation de la structure ReservedUseDataType: ReservedUseDataType // complement // Max255Text // Information on the reserved use data ReservedUseDataType // typeData // Max50Text // Name of the reserved use data ReservedUseDataType // value // Max3000Text // Value of the reserved use data | F4: BK-9845
A5: 21.16 | B5: G.HARAGHI | C5: 46178 | D5: Acquisition | E5: Modification d'attribut: 260310134700 \\ Header \\ headerFunctionalInfo \\ V \\ UUIDType \\ DNS \\ Id created for each transaction to associate nativ and Estreem format data. ==> 260310134700 \\ Header \\ headerFunctionalInfo \\ transactionCorrelationId \\ UUIDType \\ DNS \\ Id created for each transaction to associate native and Processor format data. | F5: Message de Luc
A6: 21.16 | B6: G.HARAGHI | C6: 46178 | D6: Acquisition | E6: Création d'attributs: fileData \\ captureFileReceivedDateTime \\ ISODateTime \\ DNS \\ File reception date calculated by capture fileData \\ captureErrorSequenceNumberOfMessage \\ Max10NumericText \\ DNS \\ Sequence number of the relevant message in the file fileData \\ fileNumberOfMessages \\ Max10NumericText \\ DNS \\ Number of message in the file Modification du codeset CardholderPresenceCodeset: Remplacer le valeur VADS par SERT = Secure Remote Transaction Modification d'attributs: 260310134700 \\ Header \\ headerFunctionalInfo \\ transactionDataCorrelationId \\ UUIDType \\ DNS \\ Id created for each transaction to associate nativ and Estreem format data. ==> 260310134700 \\ Header \\ headerFunctionalInfo \\ transactionCorrelationId \\ UUIDType \\ DNS \\ Id created for each transaction to associate nativ and Estreem format data. | F6: BK-9975
A7: 21.16 | B7: G.HARAGHI | C7: 46177 | D7: Acquisition | E7: Modification du codeset: IcsSettlementServiceCodeset Ajout des valeurs: IcsSettlementServiceCodeset \\ Exact4Text \\ WSAL \\ Mastercard Wholesale Settlement Service IcsSettlementServiceCodeset \\ Exact4Text \\ TRGT \\ Cartes bancaires TARGET2 Settlement Service | F7: BK-9970
A8: 21.16 | B8: G.HARAGHI | C8: 46176 | D8: Acquisition | E8: Modification de l'attribut: 250528140503 \\ Context \\ transactionContext \\ princingEngineDesignation \\ Max200Text \\ DNS \\ Textual description of transaction nature with country, region, network, .. ==> 250528140503 \\ Context \\ transactionContext \\ qualificationDesignation \\ Max200Text \\ DNS \\ Textual description of transaction nature with country, region, network, .. | F8: BK-9968
A9: 21.15 | C9: 45806 | D9: Emission | E9: Modification d'attribut: 260424190700 // Environment // cardTariff // calculationMethod // CardFeeCalculationMethodCodeset // DNS // Method used to calculate the card fee ==> 260424190700 // Environment // cardFee // calculationMethod // CardFeeCalculationMethodCodeset // DNS // Method used to calculate the card fee Création d'attribut: 260529115100 // Environment // cardTariff // calculationMethod // CardFeeCalculationMethodCodeset // DNS // Method used to calculate the card fee | F9: Coquille(BK-9903)
A10: 21.15 | B10: G.HARAGHI | C10: 45806 | D10: Emission | E10: Modification d'arttribut: 260518102400 \\ Environment \\ cardTariff \\ negociatedTariffStartDate \\ ISODate \\ DNS \\ Start date of the period of a negotiated tariff ==> 260518102400 \\ Environment \\ cardTariff \\ negotiatedTariffStartDate \\ ISODate \\ DNS \\ Start date of the period of a negotiated tariff 260518102600 \\ Environment \\ cardTariff \\ negociatedTariffEndDate \\ ISODate \\ DNS \\ End date of the period of a negotiated tariff ==> 260518102600 \\ Environment \\ cardTariff \\ negotiatedTariffEndDate \\ ISODate \\ DNS \\ End date of the period of a negotiated tariff | F10: Message de Luc
A11: 21.15 | B11: G.HARAGHI | C11: 46171 | D11: Emission | E11: Modification d'attribut: 260518105700 \\ Environment \\ cardTariff \\ discountRate \\ FeeAmountType \\ DNS \\ Discount applied on the standard tariff ==> 260518105700 \\ Environment \\ cardTariff \\ discountRate \\ PercentageRate \\ DNS \\ Discount applied on the standard tariff | F11: Coquille(BK-9903)
A12: 21.15 | B12: G.HARAGHI | C12: 46170 | D12: Contestation | E12: Modification des valeurs prises par le codeset RefundNatureCodeset : Retirer BCFI et ESTR Ajouter PROC : Processor Ajouter ESFI : Establishment financing Modification d'attribut: 260526111400 \\ AuditTrail \\ auditTrail \\ walletEnrolmentAuthenticationMean \\ AuthenticationMethodCodeset \\ DNS \\ Indicates the technical method of strong authentication used during the card enrolment into the digital wallet ==> 260526111400 \\ AuditTrail \\ auditTrail \\ walletEnrolmentAuthenticationMethod \\ AuthenticationMethodCodeset \\ DNS \\ Indicates the technical method of strong authentication used during the card enrolment into the digital wallet
A13: 21.15 | B13: G.HARAGHI | C13: 46170 | D13: Contestation | E13: Modification d'attribut: 260526131700 \\ Edition \\ editionParameters \\ mailVariant \\ Max2Text \\ DNS \\ Defines the letter variant to be generated and allows adapting the layout and document subject ==> 260526131700 \\ Edition \\ editionParameters \\ variant \\ Max2Text \\ DNS \\ Defines the letter variant to be generated and allows adapting the layout and document subject 260422142700 \\ Edition \\ editionParameters \\ mailRequestDateTime \\ ISODateTime \\ DNS \\ Letter request date time ==> 260422142700 \\ Edition \\ editionParameters \\ requestDateTime \\ ISODateTime \\ DNS \\ Letter request date time | F13: BK-9955
A14: 21.15 | B14: G.HARAGHI | C14: 46170 | D14: Contestation | E14: Création d'attributs: 260528140500 \\ Edition \\ editionParameters \\ annexTableName \\ Max50Text \\ DNS \\ Name of the table annex 260528140700 \\ Edition \\ editionParameters \\ annexTableColumn \\ Max50Text \\ DNS \\ Column of the table annex 260528140800 \\ Edition \\ editionParameters \\ annexTableData \\ Max50Text \\ DNS \\ Data of the table annex 260528142000 \\ Transaction threeDs threeDSAuthenticationDateTime \\ ISODateTime \\ DNS \\ Date and time of the authentication Modification des valeurs prises par le codeset DisputeQualificationCodeset : LITC : Dispute - Commercial -> DCOM : Dispute - Commercial Suppression des champs: 260526110400 \\ Context \\ transactionContext \\ processorCode \\ NetworkCodeset \\ DNS \\Code identifying the transaction processing channel (internal or external network), derived from INTRA/ON-US indicator, card network, and operation type. 260526112000 \\ AuditTrail \\ auditTrail \\ acsAuthenticationDateTime \\ ISODateTime \\ DNS \\ Date and time of the transaction authentication | F14: BK-9954
A15: 21.15 | B15: G.HARAGHI | C15: 46168 | D15: Contestation | E15: Creation de codeset: WalletEnrolmentChannelCodeset WalletEnrolmentChannelCodeset \\ Exact4Text \\ APBA \\ enrolment from the banking application WalletEnrolmentChannelCodeset \\ Exact4Text \\ APWA \\ enrolment from the wallet application Création du codeset: AuthenticationEnrolmentChannelCodeset AuthenticationEnrolmentChannelCodeset \\ Exact4Text \\ INAP \\ In-App Banking AuthenticationEnrolmentChannelCodeset \\ Exact4Text \\ WEBB \\ Web Banking AuthenticationEnrolmentChannelCodeset \\ Exact4Text \\ CALL \\ Call Center AuthenticationEnrolmentChannelCodeset \\ Exact4Text \\ MAIL \\ Postal Mail AuthenticationEnrolmentChannelCodeset \\ Exact4Text \\ OTHR \\ Other | F15: BK-9914
A16: 21.15 | B16: G.HARAGHI | C16: 46168 | D16: Contestation | E16: Modification Codeset: RefundNatureCodeset Retirer NTXS : Natixis Ajouter ESTR : ESTREEM Modification Codeset: DisputeQualificationCodeset Modification des valeurs prises par le codeset DisputeQualificationCodeset : OPME : Operation wrongly executed. -> OPWE : Operation wrongly executed. Modification Codeset: DisputeConditionCodeset Modification des valeurs prises par le codeset DisputeConditionCodeset : CAEC : Expired card -> CAEX : Expired card CCLO : Closed Account -> ACLO : Closed Account CEAM : Card extorted with threats -> CEWT : Card extorted with threats CNPA : Card not delivered to the cardholder -> CNDL : Card not delivered to the cardholder COPP : Suspended card -> CSUS : Suspended card CPER : Lost Card -> CLST : Lost Card CVSV : Stolen card without violence -> SCWV : Stolen card without violence DEMA : Defect in merchandise/service -> DEMS : Defect in merchandise/service DETC : Account jacking -> AJAC : Account jacking DOUB : Duplicate processing -> DUPL : Duplicate processing FCTC : Disputed invoice -> DINV : Disputed invoice FRDF : Differed fee -> DIFF : Differed fee MOER : Incorrect amount -> INAM : Incorrect amount PRIN : Non-existant cardholder -> NEXC : Non-existant cardholder RFPM : DDJ MC -> RFPM : Request for proof MC RFPV : DDJ VISA -> RFPV : Request for proof VISA RNDI : Undistributed withdrawal -> UNWD : Undistributed withdrawal RPAR : issuer ATM regulation before claim -> ARBC : issuer ATM regulation before claim RPDI : Partially distributed withdrawal -> PDWD : Partially distributed withdrawal Modification Codeset: WalletProviderCodeset Ajout des valeurs prises par le codeset WalletProviderCodeset : WPAY : Wero Pay OPAY : Open Payment | F16: BK-9914
A17: 21.15 | B17: G.HARAGHI | C17: 46168 | D17: Contestation | E17: Modification d'attributs: 250617101500 \\ Transaction \\ chargebackData \\ additionalData \\ AdditionalDataType \\ DNS \\ Additionnal data ==> 250617101500 \\ Transaction \\ chargebackData \\ additionalData \\ AdditionalDataType \\ DNS \\ Additional data 251027112335 \\ Context \\ crcCase \\ additionnalData \\ AdditionalDataType \\ DNS \\ Additionnal Data ==> 251027112335 \\ Context \\ crcCase \\ additionalData \\ AdditionalDataType \\ DNS \\ Additional Data 260422141000 \\ Transaction claimData \\ additionnalData \\ AdditionalDataType \\ DNS \\ Additionnal Data ==> 260422141000 \\ Transaction \\ claimData \\ additionalData \\ AdditionalDataType \\ DNS \\ Additional Data 250324131105 \\ Transaction \\ disputeData \\ additionnalData \\ TrueFalseIndicator \\ DNS \\ Additionnal data ==> 250324131105 \\ Transaction \\ disputeData \\ additionalData \\ TrueFalseIndicator \\ DNS \\ Additional data 250528104039 \\ AuditTrail \\ auditTrail \\ deviceTechnicalName \\ Max255Text \\ DNS \\ Enrolment terminal ==> 250528104039 \\ AuditTrail \\ auditTrail \\ deviceTechnicalName \\ Max255Text \\ DNS Technical name of the device 250717102632 \\ Environment \\ terminal \\ enrolmentCity \\ Max70Text \\ DNS \\ City of enrolment ==> 250717102632 \\ Environment \\ terminal \\ city \\ Max70Text \\ DNS \\ City associated with the device | F17: BK-9914
A18: 21.15 | B18: G.HARAGHI | C18: 46168 | D18: Contestation | E18: Création d'attributs: 260526110000 \\ Edition editionParameters \\ requestDateTime \\ ISODateTime \\ DNS \\ Edition request date time 260526110400 \\ Context \\ transactionContex t\\ processorCode \\ NetworkCodeset \\ DNS \\ Code identifying the transaction processing channel (internal or external network), derived from INTRA/ON-US indicator, card network, and operation type. 260526110800 \\ AuditTrail \\ auditTrail\\ walletEnrolmentChannel \\ WalletEnrolmentChannelCodeset \\ DNS \\ Indicates the channel through which the card was enrolled into the digital wallet. 260526111000 \\ AuditTrail \\ auditTrail\\ walletEnrolmentAuthenticationMean \\ AuthenticationMeanCodeset \\ DNS \\ Strong authentication method used for the enrolment of the card into a digital wallet 260526111200 \\ AuditTrail \\ auditTrail\\ walletEnrolmentDateTime \\ ISODateTime \\ DNS \\ Date and time when the card was enrolled into the digital wallet 260526111400 \\ AuditTrail \\ auditTrail\\ walletEnrolmentAuthenticationMean \\ AuthenticationMethodCodeset \\ DNS \\ Indicates the technical method of strong authentication used during the card enrolment into the digital wallet 260526111600 \\ AuditTrail \\ auditTrail\\ walletEnrolmentAuthenticationSuccessfulIndicator \\ TrueFalseIndicator \\ DNS \\ Indicates whether the strong authentication process for the card enrollment into the digital wallet was completed successfully 260526111800 \\ AuditTrail \\ auditTrail\\ walletEnrolmentValidationMessage \\ Max255Text \\ DNS \\ Message associated with the validation of the card enrollment into a digital wallet 260526112000 \\ AuditTrail \\ auditTrail\\ acsAuthenticationDateTime \\ ISODateTime \\ DNS \\ Date and time of the transaction authentication 260526112200 \\ AuditTrail \\ auditTrail\\ deviceTechnicalName \\ Max255Text \\ DNS \\ Technical name of the device 260526120800 \\ Transaction \\ sinisterData\\ mobileDeviceStolen \\ TrueFalseIndicator \\ DNS \\ Client indicated that their mobile phone was stolen 260526121000 \\ Transaction \\ sinisterData\\ simSwapIndicator \\ TrueFalseIndicator \\ DNS \\ Indicates whether a recent SIM swap has been detected or reported as part of the incident 260526121200 \\ Transaction \\ sinisterData\\ recentPortabilityIndicator \\ TrueFalseIndicator \\ DNS \\ Indicates whether a recent mobile number portability has been detected or reported as part of the incident 260526121400 \\ Transaction \\ sinisterData\\ eSimIndicator \\ TrueFalseIndicator \\ DNS \\ Indicates whether the customer’s device uses an eSIM at the time of the incident 260526130000 \\ AuditTrail \\ auditTrail \\ authenticationEnrolmentChannel \\ AuthenticationEnrolmentChannelCodeset \\ DNS \\ Indicates the channel through which the customer’s authentication device enrollment was performed 260526130500 \\ Environment \\ terminal \\ deviceUniqueIdentifier \\ Max64AlphaNumericText \\ DNS \\ Technical identifier of the device, enabling its unique identification within the system 260526131600 \\ AuditTrail \\ auditTrail \\ isPaymentWallet \\ TrueFalseIndicator \\ DNS \\ Indicates whether this wallet corresponds to the one used for the payment associated with the transaction 260526131700 \\ Edition \\ editionParameters \\ mailVariant \\ Max2Text \\ DNS \\ Defines the letter variant to be generated and allows adapting the layout and document subject 260422171100 \\ Transaction \\ originalTransactionData \\ initialThreeDsProtocolVersion \\ Max2NumericText \\ DNS \\ 3DS protocol major version \\ RSB119_0046_ p1 \\ 119-0046-p1 \\ 059-0046-p1 \\ 056-0046-p1 | F18: BK-9914
A19: 21.14 | B19: G.HARAGHI | C19: 46162 | D19: MOPasserel | E19: Modification des attributs: 260304141000 \\ Transaction \\ transactionDetails \\ extendedAuthorisationIndicator \\ Exact4NumericText \\ DNS \\ Indicator “Extended Authorization” ==> 260304141000 \\ Transaction \\ transactionDetails \\ extendedAuthorisationIndicator \\ Exact1AlphaNumericText \\ DNS \\ Indicator “Extended Authorization” 260304141700 \\ Transaction \\ transactionDetails \\ maximumClearingDate \\ Exact1AlphaNumericText \\ DNS \\ Clearing deadline \\ 112_0083 ==> 260304141700 \\ Transaction \\ transactionDetails \\ maximumClearingDate \\ Exact4NumericText \\ DNS \\ Clearing deadline \\ 112_0083 | F19: BK-9907
A20: 21.14 | B20: G.HARAGHI | C20: 46162 | D20: Emission | E20: Modification des attributs: 260518101800 // Environment // cardFee // standardTariffCode // Max70Text // DNS // Code defining a standard tariff ==> 260518101800 // Environment // cardTariff // standardTariffCode // Max70Text // DNS // Code defining a standard tariff 260518102200 // Environment // cardFee // negotiatedTariffCode // Max70Text // DNS // Code defining a negotiated tariff ==> 260518102200 // Environment // cardTariff // negotiatedTariffCode // Max70Text // DNS // Code defining a negotiated tariff 260518102400 // Environment // cardFee // negociatedTariffStartDate // ISODate // DNS // Start date of the period of a negotiated tariff ==> 260518102400 // Environment // cardTariff // negociatedTariffStartDate // ISODate // DNS // Start date of the period of a negotiated tariff 260518102600 // Environment // cardFee // negociatedTariffEndDate // ISODate // DNS // End date of the period of a negotiated tariff ==> 260518102600 // Environment // cardTariff // negociatedTariffEndDate // ISODate // DNS // End date of the period of a negotiated tariff 260518103000 // Environment // cardFee // minimumFee // FeeAmountType // DNS // Minimum fee applied for the calculation of a card fee ==> 260518103000 // Environment // cardTariff // minimumFee // FeeAmountType // DNS // Minimum fee applied for the calculation of a card fee 260518103200 // Environment // cardFee // maximumFee // FeeAmountType // DNS // Maximum fee applied for the calculation of a card fee ==> 260518103200 // Environment // cardTariff // maximumFee // FeeAmountType // DNS // Maximum fee applied for the calculation of a card fee 260518103400 // Environment // cardFee // tariffRate // PercentageRate // DNS // Rate applied on the base amount ==> 260518103400 // Environment // cardTariff // tariffRate // PercentageRate // DNS // Rate applied on the base amount 260518103600 // Environment // cardFee // tariffFixedAmount // FeeAmountType // DNS // Fixed amount applied for the calculation of a card fee ==> 260518103600 // Environment // cardTariff // tariffFixedAmount // FeeAmountType // DNS // Fixed amount applied for the calculation of a card fee 260518105700 // Environment // cardFee // discountRate // FeeAmountType // DNS // Discount applied on the standard tariff ==> 260518105700 // Environment // cardTariff // discountRate // FeeAmountType // DNS // Discount applied on the standard tariff 260424190700 // Environment // cardFee // calculationMethod // CardFeeCalculationMethodCodeset // DNS // Method used to calculate the card fee ==> 260424190700 // Environment // cardTariff // calculationMethod // CardFeeCalculationMethodCodeset // DNS // Method used to calculate the card fee | F20: BK-9903(Commentaire Enguerran)
A21: 21.14 | B21: G.HARAGHI | C21: 46161 | D21: Acquisition | E21: Modification des attributs: 250528104004 \\ Transaction \\ transactionDetails \\ clearingDate \\ ISODate \\ DNS \\ Expected Date of Clearing ==> 250528104004 \\ Transaction \\ transactionDetails \\ clearingDateTime \\ ISODateTime \\ DNS \\ Expected Date of Clearing 260423174500 \\ Transaction \\ transactionDetails \\ clearingSettlementDate \\ ISODate \\ DNS \\ Clearing Settlement Date calculated by the Pre-Clearing Service. ==> 260423174500 \\ Transaction \\ transactionDetails \\ clearingSettlementDateTime \\ ISODateTime \\ DNS \\ Clearing Settlement Date calculated by the Pre-Clearing Service. | F21: BK-9902
A22: 21.14 | B22: G.HARAGHI | C22: 46161 | D22: Transverse | E22: Modification des attributs: 260324180000 // Transaction // transactionDetails // msgReceivedDateTime // ISODateTime // DNS // // Date Time EO solution has received a question ==> 260324180000 // Transaction // transactionDetails // msgReceivedDateTime // ISODateTime // DNS // // Date Time the processor has received a question 260324180100 // Transaction // transactionDetails // msgSentDateTime // ISODateTime // DNS // // Date Time EO solution has sent a response ==> 260324180100 // Transaction // transactionDetails // msgSentDateTime // ISODateTime // DNS // // Date Time the processor has sent a response 260324180300 // Transaction // transactionDetails // msgReceivedFromIssuerDateTime // ISODateTime // DNS // // Date Time EO solution has received a response from Issuer ==> 260324180300 // Transaction // transactionDetails // msgReceivedFromIssuerDateTime // ISODateTime // DNS // // Date Time the processor has received a response from Issuer 260324180400 // Transaction // transactionDetails // msgSentToIssuerDateTime // ISODateTime // DNS // // Date Time EO solution has sent a question to Issuer ==> 260324180400 // Transaction // transactionDetails // msgSentToIssuerDateTime // ISODateTime // DNS // // Date Time the processor has sent a question to Issuer | F22: Message de Luc
A23: 21.14 | B23: G.HARAGHI | C23: 46161 | D23: Acquisition | E23: Création de l'attribut: 260519101000 \\ Context \\ transactionContext \\ clearingRoute \\ ClearingRouteCodeset \\ DNS \\ Identify the transaction clearing route (INTRA or SCHEME). Création du codeSet ClearingRouteCodeset: ClearingRouteCodeset \\ Exact4Text \\ INTR \\ INTRA ClearingRouteCodeset \\ Exact4Text \\ SCHE \\ SCHEME | F23: BK-9858
A24: 21.14 | B24: G.HARAGHI | C24: 46161 | D24: Acquisition | E24: Création de l'attribut: 260519100200 // Context // transactionContext // qualifScheme // QualifSchemeCodeset // DNS // Scheme identification done by qualification. Création du codeSet QualifSchemeCodeset: QualifSchemeCodeset \\ Exact4Text \\ CBFR \\ CB QualifSchemeCodeset \\ Exact4Text \\ MACD \\ MasterCard QualifSchemeCodeset \\ Exact4Text \\ VISA \\ VISA | F24: BK-9858
... A48: 21.13 | B48: B. Porcher | C48: 46141 | D48: Contestation | E48: Modification de l'attribut "distributedAmount" devient "disputedAmount" 260422142800 / Transaction / disputeData / disputedAmount / AmountType / DNS / / Amount of the transaction related to the dispute | F48: BK-9877
A49: 21.12 | B49: B. Porcher | C49: 46140 | D49: Acquisition | E49: Création du codeset QualificationBrandCodeset / Exact4Text / CBFR / CB QualificationBrandCodeset / Exact4Text / VISA / VISA QualificationBrandCodeset / Exact4Text / VPAY / VISA VPAY QualificationBrandCodeset / Exact4Text / VELC / VISA ELECTRON QualificationBrandCodeset / Exact4Text / MACD / MASTERCARD QualificationBrandCodeset / Exact4Text / MAES / MAESTRO QualificationBrandCodeset / Exact4Text / DISC / DISCOVER QualificationBrandCodeset / Exact4Text / UPIC / UPI CHINA QualificationBrandCodeset / Exact4Text / JCB0 / JCB QualificationBrandCodeset / Exact4Text / AMEX / AMEX QualificationBrandCodeset / Exact4Text / UNKN / Unknown
A50: 21.12 | B50: B. Porcher | C50: 46140 | D50: Acquisition | E50: Création de 2 attributs 260428104900 / Transaction / transactionDetails / qualifCardBrand / QualificationBrandCodeset / DNS / / Brand defined by qualification. 260428105000 / Transaction / transactionDetails / clearingNetwork / NetworkCodeset / DNS / / Network for clearing - Scheme
A51: 21.12 | B51: B. Porcher | C51: 46140 | D51: Emission | E51: Modification d'attribut 250528140504 / Transaction / transactionDetails / feesAmountPayable / AmountType / DNS / / Fees Amount Payable devient 250528140504 / Transaction / transactionDetails / payableFeeAmount / FeeAmountType / DNS / / Payable Fee Amount
A52: 21.12 | B52: B. Porcher | C52: 46136 | D52: Emission | E52: Création des codeset pour les attributs de cardFee CardFeeNegotiationNatureCodeset // Exact4Text // DISC // Negotiated price with a discount CardFeeNegotiationNatureCodeset // Exact4Text // EXPT // Negotiated price with an explicit tariff CardFeeNegotiationNatureCodeset // Exact4Text // STRD // Standard price (no negotiation) CardFeeExemptionReasonCodeset // Exact4Text // PERD // Fee exemption for the period CardFeeExemptionReasonCodeset // Exact4Text // PRCG // Pricing fee exemption CardFeeCalculationMethodCodeset // Exact4Text // EXTL // External price CardFeeCalculationMethodCodeset // Exact4Text // FIXD // Fixed amount CardFeeCalculationMethodCodeset // Exact4Text // FREE // Free price CardFeeCalculationMethodCodeset // Exact4Text // UNIT // Unitary price CardFeeCalculationMethodCodeset // Exact4Text // PROP // Proportional price CardFeeCalculationMethodCodeset // Exact4Text // UNPR // Unitary and proportional price CardFeePartialPeriodCodeset // Exact4Text // FULL // The period is fully charged CardFeePartialPeriodCodeset // Exact4Text // FREE // The period is free CardFeePartialPeriodCodeset // Exact4Text // PRTP // Pro rata temporis over the period applied on the fee | F52: BK-9873
A53: 21.12 | B53: B. Porcher | C53: 46136 | D53: Emission | E53: Création d'un objet cardFee et d'une série d'attributs dans le cadre du nouveau contrat Iss-CMS26_001 "Billing card events" 260424190000 / Environment / cardFee / cardFeeId / Max36IdentifierText / DNS / / Unique identifier of the card fee 260424190100 / Environment / cardFee / creationDateTime / ISODateTime / DNS / / Creation date and time of the card fee 260424190200 / Environment / cardFee / referenceDate / ISODate / DNS / / Reference date of the card fee 260424190300 / Environment / cardFee / payableAmount / FeeAmountType / DNS / / Payable card fee amount 260424190400 / Environment / cardFee / negotiationNature / CardFeeNegotiationNatureCodeset / DNS / / Card fee negotiation conditions 260424190500 / Environment / cardFee / exemptionReason / CardFeeExemptionReasonCodeset / DNS / / Reason for a card fee exemption (zero amount) 260424190600 / Environment / cardFee / settlementDate / ISODate / DNS / / Settlement date of the card fee 260424190700 / Environment / cardFee / calculationMethod / CardFeeCalculationMethodCodeset / DNS / / Method used to calculate the card fee 260424190800 / Environment / cardFee / standardAmount / FeeAmountType / DNS / / Standard amount to apply for a card fee 260424190900 / Environment / cardFee / baseAmount / AmountType / DNS / / Base amount used for the calculation of a card fee 260424191000 / Environment / cardFee / standardRate / PercentageRate / DNS / / Standard rate to apply for a card fee 260424191100 / Environment / cardFee / periodStartDate / ISODate / DNS / / Start date of the period of a recurring card fee 260424191200 / Environment / cardFee / periodEndDate / ISODate / DNS / / End date of the period of a recurring card fee 260424191300 / Environment / cardFee / firstPeriodCalculationCode / CardFeePartialPeriodCodeset / DNS / / Code indicating the calculation mode of the first period of a recurring card fee 260424191400 / Environment / cardFee / lastPeriodCalculationCode / CardFeePartialPeriodCodeset / DNS / / Code indicating the calculation mode of the last period of a recurring card fee | F53: BK-9873
A54: 21.12 | B54: B. Porcher | C54: 46135 | D54: Acquisition | E54: Création d'un attribut clearingSettlementDate 260423174500 / Transaction / transactionDetails / clearingSettlementDate / ISODate / DNS / / Clearing Settlement Date calculated by P2SPen | F54: BK-9837
A55: 21.12 | B55: B. Porcher | C55: 46135 | D55: Acquisition | E55: Ajout des valeurs suivantes au codest CardholderPresenceCodeset CardholderPresenceCodeset / Exact4Text / VADS / Vad Sale | F55: BK-9863
A56: 21.12 | B56: B. Porcher | C56: 46135 | D56: Acquisition | E56: Ajout des valeurs suivantes au codest DigitalWalletNameCodeset DigitalWalletNameCodeset / Exact4Text / PAYL / 04 PAYL (CB2AF 1.6.4 & 1.6.5 et plus après) DigitalWalletNameCodeset / Exact4Text / VPME / 02 V.ME (CB2AF 1.5.0 et plus à partir de 1.6.0) DigitalWalletNameCodeset / Exact4Text / MPAS / 03 Masterpass (ex PPOL, jusqu'à 1.6.3 et plus après) | F56: BK-9825
A57: 21.12 | B57: B. Porcher | C57: 46135 | D57: Contestation | E57: Création des attributs suivants : 260423103400 / Context / claimData / receiptsNumber / Max6NumericText / DNS / / Number of receipts covered by the claim. 260423103500 / Transaction / claimData / saleDate / ISODate / DNS / / Sale Date 260423103600 / Edition / editionParameters / recourseRequestNature / MainServiceCodeset / DNS / / amicable recourse request nature 260423103700 / Transaction / claimData / caseAdvancementCode / CaseAdvancementCodeset / DNS / / Case Advancement Code | F57: BK-9867
A58: 21.12 | B58: B. Porcher | C58: 46135 | D58: Contestation | E58: Modification de Codeset Ajout de la valeur UNKN au codeset CardholderAuthenticationMethodCodeset | F58: BK-9805
A59: 21.12 | B59: B. Porcher | C59: 46134 | D59: Acquisition | E59: Création de l'attribut suivant : 260422150000 / Transaction / remittanceData / mostRecentTransactionDateTime / ISODateTime / DNS / / Most recent transaction of a remittance | F59: BK-9862
A60: 21.12 | B60: B. Porcher | C60: 46134 | D60: Contestation | E60: Ajout de 2 nouvelles valeurs à CaseAdvancementCodeset TRTD : Treated CONS : Constituted | F60: BK-9861
A61: 21.12 | B61: B. Porcher | C61: 46134 | D61: Contestation | E61: Modification du libelle quie devient Reopenning date Time (perd le Last) 251027112302 / Transaction / disputeData / reopeningDateTime / ISODateTime / DNS / / Reopening date time | F61: BK-9857
A62: 21.12 | B62: B. Porcher | C62: 46134 | D62: Contestation | E62: Modification de l'attribut de claimDataId devient claimCaseId 250528103500 / Transaction / claimData / claimCaseId / Exact16AlphaNumericText / DNS / / Claim case reference | F62: BK-9857
A63: 21.12 | B63: B. Porcher | C63: 46134 | D63: Contestation | E63: Création des attributs suivants : 260422141600 / Edition / editionParameters / previousLetterDate / ISODate / DNS / / Claim date 260422141700 / Context / claimData / additionnalData / AdditionalDataType / DNS / / Number of debit receipts 260422141800 / Edition / editionParameters / emailLetterhead / EmailAddressType / DNS / / Number of credit receipts 260422141900 / Edition / editionParameters / letterObject / Max200Text / DNS / / Amount to reverse 260422142000 / Edition / editionParameters / chargebackReasonTitleFieldName / Max50Text / DNS / / Amount to reprocess 260422142100 / Edition / editionParameters / conclusionContent / Max500Text / DNS / / starting date for statement 260422142200 / Edition / editionParameters / finalDateReceipt / ISODate / DNS / / ending date for statement 260422142300 / Transaction / claimData / caseAdvancementLevel / Max2NumericText / DNS / / Case Advancement level 260422142400 / Transaction / claimData / statusUpdateDateTime / ISODateTime / DNS / / Update date time of the status 260422142500 / Transaction / claimData / taskAdvancement / Max255Text / DNS / / Task Advancement 260422142600 / Transaction / claimData / totalAmount / AmountType / DNS / / Total amount of transactions in the claim file 260422142700 / Edition / editionParameters / mailRequestDateTime / ISODateTime / DNS / / Letter request date time 260422142800 / Transaction / disputeData / distributedAmount / AmountType / DNS / / Amount of the transaction related to the dispute 260422142900 / Context / executionContractFinancialParameters / contractRetrievalMethod / Max1Text / DNS / / Contract Retrieval Method 260422143000 / Transaction / transactionDetails / vrolBundleCaseReference / Max35AlphaNumericText / DNS / / VISA Resolve Bundle case reference | F63: BK-9857
... A69: 21.12 | B69: B. Porcher | C69: 46128 | D69: Autorisation | E69: Modification des libellés : 250203172500/Transaction/additionalResponseData/addServiceReportData/AddServiceReportDataCodeset/DNS//Additional service report sent to the acquirer by the network - Data 250203170300/Transaction/additionalResponseData/addServiceReportId/AddServiceReportIDCodeset/DNS//Additional service report sent to the acquirer by the network - ID | F69: BK-8909
A70: 21.12 | B70: G.HARAGHI | C70: 46121 | E70: Modification: 250331125901 \\ Environment \\ terminal \\ cardholderPickUpCapabilities \\ CardholderPickUpCapabilitiesCodeset \\ DNS \\ Cardholder pick-up capability \\ 021-p3 ==> 250331125901 \\ Environment \\ terminal \\ cardCaptureCapabilities \\ cardCaptureCapabilitiesCodeset \\ DNS \\ Cardholder pick-up capability \\ 021-p3 Création: Création du Codeset: cardCaptureCapabilitiesCodeset: cardCaptureCapabilitiesCodeset \\ Exact4Text \\ UNKN \\ Unknown or not specified cardCaptureCapabilitiesCodeset \\ Exact4Text \\ NONE \\ Terminal has no card capture capabilities cardCaptureCapabilitiesCodeset \\ Exact4Text \\ CAPT \\ Terminal has card capture capabilities | F70: BK-9763
A71: 21.12 | B71: G.HARAGHI | C71: 46119 | D71: Transverse | E71: Modification: 241112000204 \\ Context\\ transactionContext \\ ecommerceIndicator \\ Exact2AlphaNumericText \\ DNS \\ Electronic commerce indicator (VISA) \\ RSB59_416 \\ 059-0416 \\ 058-416 \\ 059-0416 \\ [60.8] \\ DE48 SE42 SF1 ==>Retirer DE 48 SE 42 SF 1 de la colonne MCD 241112000041 \\ Context \\ transactionContext \\ electronicCommerceAuthenticationNature \\ ElectronicCommerceAuthenticationNatureCodeset \\ DNS \\ Electronic commerce transaction authentication type \\ RSB59_407 \\ 059-0407 \\ 058-FF47 059-0407 \\ DE 48 SE 42 SF 1 ==>Retirer DE 48 SE 42 SF 1 de la colonne MCD 241112000111 \\ Environment \\ merchantAgreement \\ companyRegistrationNumber \\ Max25AlphaNumericText \\ DNS \\ Company Registration Number \\ SIREN en France RSB47_96 \\ 047-96 \\ 046-DF5D \\ 047-96 \\ 104 Usage 2 Dataset ID 63 Tag 05, Field 34 Dataset ID 02 Tag CB \\ DE 112 SE 020 ==>Retirer DE 48 SE 42 SF 1 de la colonne MCD | F71: BK-9797
A72: 21.12 | B72: G.HARAGHI | C72: 46119 | D72: Transverse | E72: Modification: 260304150700 \\ Environment \\ paymentToken \\ digitalAthenticationData \\ Max250AlphaNumericText \\ DNS \\ Digital Authentication Data \\ 108_0400 ==> 260304150700 \\ Environment \\ paymentToken \\ digitalAuthenticationData \\ Max250AlphaNumericText \\ DNS \\ Digital Authentication Data \\ 108_0400 | F72: Mail de Stephane COUTANT
A73: 21.12 | B73: G.HARAGHI | C73: 46119 | D73: Contestation | E73: Modification: 251024104002 \\ Transaction \\ claimData \\ handlingIndicator \\ TrueFalseIndicator \\ DNS \\ Acceptance indicator of claim ==> 251024104002 \\ Transaction \\ claimData \\ handlingIndicator \\ TrueFalseIndicator \\ DNS \\ Claim handling indicator | F73: BK-9156
A74: 21.12 | B74: G.HARAGHI | C74: 46119 | D74: Acquisition | E74: Modification: 250617141800 \\ Environment \\ executionContract \\ processingName \\ Max70Text \\ DNS \\ Trade name or commercial brand of the merchant (at SIREN level). Used by all acquisition services. \\ 043-p1-1 \\ 043-p1-1 \\ 043-p1-1 ==> 250617141800 \\ Environment \\ executionContract \\ processingName \\ Max70Text \\ DNS \\ Merchant Name used by all acquisition services. \\ 043-p1-1 \\ 043-p1-1 \\ 043-p1-1 | F74: Suite à la discussion dans le canal teams
A75: 21.12 | B75: G.HARAGHI | C75: 46114 | D75: MOPasserel | E75: Modification: Modification du Codeset MessageFunctionCodeset: Ajout des deux valeurs: MessageFunctionCodeset \\ Exact4Text \\ REVQ \\ Reversal Request MessageFunctionCodeset \\ Exact4Text \\ REVR \\ Reversal Response | F75: BK-9768
A76: 21.12 | B76: G.HARAGHI | C76: 46114 | D76: Emission | E76: Création: 260402171900 \\ Environment \\ paymentToken \\ cardReferenceId \\ Max64AlphaNumericText \\ DNS \\ Card reference identifier from the TSP | F76: BK-9743
A77: 21.12 | B77: B.Porcher | C77: 46113 | D77: Transverse | E77: ANNULATION de l'obsolescence de transactionIdentification.transactionReference 241112000229 // transaction // transactionIdentification // transactionReference // Max35Text
A78: 21.12 | B78: G.HARAGHI | C78: 46111 | D78: Acquisition | E78: Modification: 251021103703 \\ Transaction \\ remittanceData \\ preclearinRejectedTransactionsCounter \\ Max10NumericText \\ DNS \\ Counter of rejected transaction in a remittance by Preclearing ==> 251021103703 \\ Transaction \\ remittanceData \\ preclearingRejectedTransactionsCounter \\ Max10NumericText \\ DNS \\ Counter of rejected transaction in a remittance by Preclearing | F78: BK-9751
A79: 21.11 | B79: B.Porcher | C79: 46107 | D79: Acquisition | E79: SUPPRESSION des 4 valeurs de codesets ci-dessous pour "BrandCodeset": BrandCodeset \\ Exact4Text \\ VCOR \\ Visa Corporate BrandCodeset \\ Exact4Text \\ VELC \\ Visa Electron BrandCodeset \\ Exact4Text \\ VPAY \\ Visa Vpay BrandCodeset \\ Exact4Text \\ MAES \\ Maestro de mastercard | F79: Contrôle CI
A80: 21.11 | B80: B.Porcher | C80: 46107 | D80: Acquisition | E80: Modification de l'attribut - captureRejected… à la place de capturedRejected….. (retrait du d de captured) 260306100300 // Transaction // remittanceData // captureRejectedTransactionsCounter // Max10NumericText | F80: Contrôle CI
A81: 21.11 | B81: B.Porcher | C81: 46107 | D81: Telepar | E81: Modification de l'attribut - automaticCallLocalTime à la place de localTimeAutomaticCall 250425201024 // Context // pointOfServiceContext // automaticCallLocalTime // Exact4NumericText // DNS // // Local time , automatic call | F81: Contrôle du CI Acquisition UA07
A82: 21.11 | B82: B.Porcher | C82: 46107 | D82: Acquisition | E82: Modification de l'attribut - nonCompletedDebitsNumber à la place de debitsNonCompletedNumber. 50703153900 // Transaction // remittanceData // nonCompletedDebitsNumber // Max6NumericText | F82: Contrôle du CI Acquisition TC04-2
A83: 21.11 | B83: B.Porcher | C83: 46107 | D83: Acquisition | E83: Modification des 4 attribtus - debitsWith à la place de debitwith 250425151002 // Transaction // remittanceData // debitsWithDonationAmount // AmountType 250425151001 // Transaction // remittanceData // debitsWithDonationNumber // Max6NumericText 250425150901 // Transaction // remittanceData // debitsWithTipAmount // AmountType 250425150900 // Transaction // remittanceData // debitsWithTipNumber // Max6NumericText | F83: Contrôle du CI Acquisition TC04-2
A84: 21.11 | B84: B.Porcher | C84: 46107 | D84: Acquisition | E84: 6 attributs obsolètes - Une seul référence dictionnaire conservée dans remittanceData et qui sera utilisée de 2 façons différentes à travers la simplification syntaxique. 250707160804 // Context // transactionContext // creditsAmount // AmountType // DNS // Obsolète // Credits,amount (terminal) 250707160802 // Context // transactionContext // creditsNumber // Max6NumericText // DNS // Obsolète // Credits, number (terminal) 250707160805 // Context // transactionContext // debitsAmount // AmountType // DNS // Obsolète // Debits,amount (terminal) 250707160803 // Context // transactionContext // debitsNumber // Max6NumericText // DNS // Obsolète // Debits, number (terminal) 250703154900 // Context // transactionContext // debitsReversalAmount // AmountType // DNS // Obsolète // Debits, reversal amount (terminal) 250707160800 // Context // transactionContext // debitsReversalNumber // Max6NumericText // DNS // Obsolète // Debits, reversal number (terminal) 250707160801 // Context // transactionContext // numberOfNonCompletedTransactions // Max6NumericText // DNS // Obsolète // Debits,non completed number (terminal) | F84: Echanges BPO, LVA et MDE
A85: 21.11 | B85: G.HARAGHI | C85: 46106 | D85: Emission | E85: Création: 260325093000 \\ Reference \\ virtualCard \\ enrolmentStatus CardStatusCodeset \\ DNS \\ Virtual card agreement enrolment status 260325093200 \\ Reference \\ virtualCard \\ enrolmentClosureDateTime \\ ISODateTime DNS \\ Virtual card agreement enrolment closure date and time 260325093700 \\ Reference \\ virtualCard \\ enrolmentCreationDateTime \\ ISODateTime \\ DNS \\ Virtual card agreement enrolment creation date and time | F85: BK-9734
A86: 21.11 | B86: B.Porcher | C86: 46105 | D86: Transverse | E86: Attribut headerFunctionalInfo.recipientPartyResponseCode devient obsolète 241112000156 // Header // headerFunctionalInfo // recipientPartyResponseCode // Exact5NumericText // DNS // Obsolète // Estreem internal response code
A87: 21.11 | B87: B.Porcher | C87: 46104 | D87: Transverse | E87: Attribut response.responseDateTime devient obsolète 241114154800 // Transaction // response // responseDateTime // ISODateTime // DNS // Obsolète // Response Date Time
A88: 21.11 | B88: B.Porcher | C88: 46104 | D88: Transverse | E88: Création de 4 attributs pour stocker les dates et heures des messages entrants et sortant msgReceivedDateTime : Demande reçue d'un Scheme pour le SAE ou reçu pour le SAA msgSentDateTime : Réponse renvoyé à un Scheme par le SAE ou par le SAA msgSentToIssuerDateTime : Demande envoyée par la passerelle suivant le SAA vers un Issuer msgReceivedFromIssuerDateTime : Réponse reçu d'un issuer par la passerelle utilisée par le SAA 260324180000 // Transaction // transactionDetails // msgReceivedDateTime // ISODateTime // DNS // // Date Time EO solution has received a question 260324180100 // Transaction // transactionDetails // msgSentDateTime // ISODateTime // DNS // // Date Time EO solution has sent a response 260324180300 // Transaction // transactionDetails // msgReceivedFromIssuerDateTime // ISODateTime // DNS // // Date Time EO solution has received a response from Issuer 260324180400 // Transaction // transactionDetails // msgSentToIssuerDateTime // ISODateTime // DNS // // Date Time EO solution has sent a question to Issuer
A89: 21.11 | B89: B.Porcher | C89: 46104 | D89: Passerelle | E89: Modification du type du montant dans le type structuré FeesType (CBAE 119-010 et VISA 46) amount devient FeesAmount le type passe de ImpliedCurrencyAndAmount à ImpliedFeeCurrencyAndAmount ==> FeesType // feesAmount // ImpliedFeeCurrencyAndAmount | F89: BK-9729
A90: 21.11 | B90: B.Porcher | C90: 46104 | D90: Acquisition | E90: Ajout d'une valeur de Codeset à BrandCodeset BrandCodeset // Exact4Text // VCOR // VISA Corporate | F90: BK-9727
A91: 21.11 | B91: B.Porcher | C91: 46104 | D91: Acquisition | E91: Modification de la structure SchemeFeesType amount // AmountType devient fixedOrCalculatedAmountInfo // FeeAmountType schemeFeesAmount // AmountType devient schemeFeesAmountInfo // FeeAmountType | F91: BK-9722
A92: 21.11 | B92: B.Porcher | C92: 46104 | D92: Acquisition | E92: Création du Type FeeAmountType pour intégrer les montants de type Fee FeeAmountType // feeAmount // ImpliedFeeCurrencyAndAmount // FeeAmountType // amountDescription // Max35Text // Short description of amount FeeAmountType // conversionDateTime // ISODateTime // FeeAmountType // currency // ISO3NumericCurrencyCode // FeeAmountType // exchangeRate // Base25OneRate // FeeAmountType // originalFeeAmount // ImpliedFeeCurrencyAndAmount // FeeAmountType // originalCurrency // ISO3NumericCurrencyCode // | F92: BK-9722
A93: 21.11 | B93: B.Porcher | C93: 46104 | D93: Acquisition | E93: Modification dans interchange : amount par interchangeAmount et AmountType par FeeAmountType 250317120008 // Transaction // interchange // interchangeAmount // FeeAmountType | F93: BK-9722
A94: 21.11 | B94: B.Porcher | C94: 46104 | D94: Acquisition | E94: Création d'un type, ImpliedFeeCurrencyAndAmount, de montant particulier pour les montants de Fees et d'interchange ImpliedFeeCurrencyAndAmount // Number of monetary units FOR FEE specified in a currency where the unit of currency is implied by the context and compliant with ISO 4217. The decimal separator is a dot. Less interger number of digit and until 10 digit for decimal number. // string // \-?[0-9]{1,5}(\.?[0-9]{0,10})? Examples : 1.1234567891 or 0.0987654321 or 0.12345 etc … // Taille max = 15 | F94: BK-9722
A95: 21.11 | B95: B.Porcher | C95: 46104 | D95: Acquisition | E95: Modification : Renseignement des références CB2AF pour les attributs xxxxNumber et xxxxAmount dans transactionContext & remittanceData - Dans Context / transactionContext, la référence est celle du protocole, par exemple 086. - Dans Transaction / remittanceData, la référence est identifiée par xxx calculated, par exemple 086 - Calculated | F95: BK-9726
A96: 21.11 | B96: B.Porcher | C96: 46104 | D96: Acquisition | E96: Modification : Remplacement de l'attribut creditCounter par creditsNumber et modification du type de Max10NumericText à Max6NumericText 250624103900 // Context // clearingContext // creditsNumber // Max6NumericText // DNS // Total number of credit invoices contained in the remittance | F96: BK-9726
A97: 21.11 | B97: B.Porcher | C97: 46104 | D97: Acquisition | E97: Modification : Remplacement de l'attribut totalNumberOfDebitTransactionsWithDeferredClearing par debitsWithDeferredClearingNumber et modification du type de Max10NumericText à Max6NumericText 250422120103 // Transaction // remittanceData // debitsWithDeferredClearingNumber // Max6NumericText // DNS // Total number of debit transactions with deferred clearing | F97: BK-9726
A98: 21.11 | B98: B.Porcher | C98: 46104 | D98: Acquisition | E98: Modification : Remplacement de l'attribut totalAmountOfDebitTransactionsWithDeferredClearing par debitsWithDeferredClearingAmount 250422120104 // Transaction // remittanceData // debitsWithDeferredClearingAmount // AmountType // DNS // Total amount of debit transactions with deferred clearing | F98: BK-9726
A99: 21.11 | B99: B.Porcher | C99: 46104 | D99: Acquisition | E99: Modification : Remplacement de debitReversalAmount par debitsReversalAmount 250425153909 // Transaction // remittanceData // debitsReversalAmount // AmountType // DNS // Debits, reversal amount (server) | F99: BK-9726
A100: 21.11 | B100: B.Porcher | C100: 46104 | D100: Acquisition | E100: Modification : Remplacement de debitNonCompletedTotalNumber par debitsNonCompletedNumber et modification du type de Max10NumericText à Max6NumericText 250703153900 // Transaction // remittanceData // debitsNonCompletedNumber // Max6NumericText // DNS // Debits, non completed total number (server) | F100: BK-9726
... A135: 21.10 | B135: B.Porcher | C135: 46087 | D135: PRECOMP | E135: Création: 260306100300 // Transaction // remittanceData // capturedRejectedTransactionsCounter // Max10NumericText // DNS // // Counter of rejected transaction in a remittance by Capture | F135: BK-9694
A136: 21.10 | B136: B.Porcher | C136: 46087 | D136: PRECOMP | E136: Correction coquille : remitanceData au lieu de remittanceData 260217141500 // Transaction // remittanceData // includedPreClearingDateTime // ISODateTime // DNS // // Date and time the remittance was included in the PreClearing process.
A137: 21.10 | B137: G.HARAGHI | C137: 46085 | D137: MOPasserel | E137: Création: 260304143000 \\ Transaction \\ transactionDetails \\ cardholderVerificationMethodePos \\ Max4HexBinaryText \\ DNS \\ Transaction CVM indicator \\ 119_1022 260304147000 \\ Environment \\ paymentToken \\tokenAuthenticationAmount \\ Exact3HexBinaryText \\ DNS \\ Token Authentication Amount \\ 108_0154 260304150000 \\ Environment \\ paymentToken \\ tokenAuthenticationFactorB \\ Exact1HexBinaryText \\ DNS \\ Token Authentication Factor B \\ 108_0155 260304150700 \\ Environment \\ paymentToken \\ digitalAthenticationData \\ Max250AlphaNumericText \\ DNS \\ Digital Authentication Data \\ 108_0400 260304151200 \\ Environment paymentToken \\ digitalServiceProviderId \\ Max25AlphaNumericText \\ DNS \\ Digital Service Provider Id \\ 108_0401 260304152200 \\ Transaction \\ additionalResponseData \\ appliedProductPlatform \\ Exact2AlphaNumericText \\ DNS \\ Applied Product Platform \\ 112_1001_p5 260304152700 \\ Transaction \\ additionalResponseData \\ appliedCardholderIdMethod \\ Exact1AlphaNumericText \\ DNS \\ Applied Cardholder ID Method \\ 112_1001_p6 260304154500 \\ Transaction \\ additionalResponseData \\ appliedAccountTypeFrom \\ Exact1AlphaNumericText \\ DNS \\ Applied Account Type From \\ 112_1001_p7 Création du type simple: Exact30AlphaNumericText | F137: BK-9535
A138: 21.10 | B138: G.HARAGHI | C138: 46085 | D138: MOPasserel | E138: Création: 260304135100 \\ Transaction \\ transactionDetails \\ downgradeReason \\ Exact1NumericText \\ DNS \\Transaction declassification reason \\ 57_21 260304135700 \\ Context \\ transactionContext \\ tokenUpdateFirstUseIndicator \\ Exact1AlphaNumericText \\ DNS \\ VDCU token initial‑use status \\ 112_0033 260304140300 \\ Context \\transactionContext \\ authenticationDataQualityIndicator \\ Exact1AlphaNumericText \\ DNS \\ Authentication data quality level \\ 112_0040 260304141000 \\ Transaction \\ transactionDetails \\ extendedAuthorisationIndicator \\ Exact4NumericText \\ DNS \\ Indicator “Extended Authorization” \\ 112_0082 260304141700 \\ Transaction \\ transactionDetails \\ maximumClearingDate \\ Exact1AlphaNumericText \\ DNS \\ Clearing deadline \\ 112_0083 260304142000 \\ Context \\ transactionContext merchantPaymentGatewayId Exact11NumericText DNS \\ Merchant payment gateway identifier \\ 112_0204 260304142300 \\ Context \\ transactionContext \\ almServiceData \\ Exact30AlphaNumericText \\ DNS \\ Alm date service \\ 114_61 260304142700 \\ Context \\ transactionContext \\ merchantCountryOrigin \\ Exact3NumericText \\ DNS \\ Merchant country code \\ 119_0374 | F138: BK-9535
A139: 21.9 | B139: G.HARAGHI | C139: 46078 | D139: Emission | E139: Modification: Pour l'attribut: 250401135100 \\ Environment \\ acquirer \\ acquirerName \\ Max40Text \\ DNS \\ Acquirer Name \\ 112-0022 \\ field 34 Dataset ID 02 Tag C1 \\ N/A ==> Précision dans les références protocolaire CBAE: 112-0022 VISA: field 34 Dataset ID 02 Tag C1 MCD : N\A. Pour l'attribut: 250418220112 \\ Environment \\ acquirer \\ postalAddress \\ PostalAddressType \\ DNS \\ Acquiring institution postal address \\ ISO19 \\ 019 \\ prm-asc ==>Modification du libéllé et Précision dans les références protocolaire CB2A: prm-asc CBAE: 019 CIFO: ISO19 | F139: BK-9662
A140: 21.9 | B140: G.HARAGHI | C140: 46079 | D140: Emission | E140: Création: 260226092800 \\ Environment \\ accountOwner \\ birthCountryCode \\ ISO3NumericCountryCode \\ DNS \\ Account owner birth country code \\ 118-4013 \\ 56.05.90 2602260942 \\ Environment \\ acquirer \\ fullPostalAddress \\ PostalAddressType \\ DNS \\ Acquirer postal address \\ 112-002x \\ field 34 Dataset ID 02 Tag C6 2602260934 \\ Environment \\ accountOwner \\ birthDate \\ ISODate \\ DSP \\ Date of birth of account owner \\ 118-4015 \\ 56.05.92 | F140: BK-9662
A141: 21.9 | B141: G.HARAGHI | C141: 46078 | D141: Emission | E141: Création d'attributs: 260225201700 \\ Environment\\ paymentToken \\ applicationId \\ Max36Text \\ DNS \\ Application unique identifier 260225201900 \\ Environment \\ paymentToken \\ enrolmentDeviceType \\ Max100Text \\DNS \\ Device type in the VISA token enrolment context | F141: BK-9663
A142: 21.9 | B142: G.HARAGHI | C142: 46078 | D142: Emission | E142: Création: 260225153200 \\ Reference \\ virtualCard \\ enrolmentId \\ Max32Text \\ DNS \\ Virtual card enrolment identifier Modification du Data Comment du codeset EligibilityCheckStepCodeset Exact4Text BEEN Before enrollment => Before enrolment EligibilityCheckStepCodeset Exact4Text DUEN During enrollment => During enrolment Modification du libellé de l'attribut: Attribut: 250717102632 \\ Environment \\ terminal \\ enrolmentCity \\ Max70Text DNS \\ City of enrollment City of enrollment ==> City of enrolment Attribut: 251125100015 \\ Context \\ cardContext\\ cardRiskLevel \\ Max10AlphaNumericText \\ DNS \\ Represent the level of risk linked to the card Modification Represent the level of risk linked to the card Modification ==>Represents the level of risk linked to the card | F142: BK-9635
A143: 21.9 | B143: B. Porcher | C143: 46078 | D143: Transverse | E143: Modification de la référence 250418220114 250418220114 // Reference // cardRepository // accountFundingSource // AccountFundingSourceCodeset // DNS // // Account Funding Source // SICB - VI21 250418220114 // Reference // cardRepository // visaAccountFundingSource // Exact1Text // DNS // // Visa Account Funding Source // SICB - VI21
A144: 21.9 | B144: B. Porcher | C144: 46078 | D144: Transverse | E144: Création du type NoTimezoneDateTime : Ce type permet de gérer les attribut DateTime qui ne peuvent pas déterminer leur Timezone. Si le Timezone est identifié, il faut utiliser le type ISODateTime Format : AAAA-MM-DDTHH:MM:SS (SS facultatif) Pattern de controle associé. | F144: BK-9375 à l'origne de l'étude
A145: 21.9 | B145: G.HARAGHI | C145: 46077 | D145: Contestation | E145: Creation des codeset: TransfertStatusCodeset LoadingErrorCodeCodeset Modification codeset Rajouter une valeur "AWCD" au codeset CaseStatusCodeset Modification du type de l'attribut 250324131113 \\ Transaction \\ transactionDetails \\ settlementStatusCode \\ SettlementStatusCodeCodeset | F145: BK-9623
A146: 21.9 | B146: G.HARAGHI | C146: 46077 | D146: Contestation | E146: Modification du nom et du libellé de l'attribut: settlementStatus -> settlementStatusCode libellé: Settlement Status code Création des attributs: 260224143800 \\ Edition \\ documentDetails \\ fileSize\\ Max19NumericText 260224145000 \\ Edition \\ documentDetails \\ documentUuid \\ UUIDType \\ Processor Document uuid 260224145500 \\ Context \\ loadingDetails \\ statusCode \\ TransfertStatusCodeset \\ Loading status 260224155013 \\ Context \\ loadingDetails \\errorCode \\ LoadingErrorCodeCodeset 260224150900 \\ Context \\ loadingDetails \\ errorComment \\ Max70Text 260224151200 \\ Context \\ loadingDetails \\ presignedUrl \\Max8000Text | F146: BK-9623
A147: 21.9 | B147: G.HARAGHI | C147: 46077 | D147: Contestation | E147: Modifications des libellés: 260107110002 \\ AuditTrail \\ auditTrail \\ enrolmentPhoneNumber \\ PhoneNumberText Phone used for enrolment 260107110003 \\ AuditTrail \\ auditTrail \\ enrolmentEmail \\ EmailAddressType \\ Email used in case of OTP mail enrollment. 260107110006 \\ Context transactionContext \\ disputeLink \\ DisputeLinkCodeset \\ Link between payment and dispute 260107110007 \\ Context \\ transactionContext \\ paymentAuthenticationDateTime \\ ISODateTime \\ Date time on which the payment was authenticated. 260107110015 \\ Context \\ auditTrail \\ consistencyScore \\ Max1NumericText \\ Authentication method usage consistency score. 260107110016 \\ Context auditTrail \\ strengthScore \\ Max1NumericText \\ Authentication method robustness score. 250324131114 \\ Transaction transactionDetails settlementStatusLabel Max255Text Label of the settlement status 251027112333 \\ Context crcCase taskStatus TaskStatusCodeset Task statut status code Renommer le nom du codeset CaseStatusCodeset en CaseAdvancementCodeset Création d'un CodeSet: ConsistencyScoreCodeset Modification du type de l'attribut: 260107110015 \\ AuditTrail \\ auditTrail \\ consistencyScore \\ ConsistencyScoreCodeset Création d'un codeSet: StrengthScoreCode Modification du type de l'attribut: 260107110016 \\ AuditTrail \\ auditTrail \\ strengthScore \\ StrengthScoreCodeset Modification du codeset: SettlementStatusCodeset==> SettlementStatusCodeCodeset | F147: BK-9623
A148: 21.9 | B148: B.Porcher | C148: 46070 | D148: ACQ-AUTO CAPTURE PRECOMP | E148: Attribut devenant Obsolète transactionDetails // issuerAuthorisationTransactionReference // Max50Text // DNS // Obsolète // Unique Transaction Reference Utiliser dorénavant les 2 attributs ci-dessous additionalResponseData // uniqueTransactionIdNetwork // NetworkCodeset // DNS // // Transaction Id network // // RSB47_95_p1 // 047-95-p1 // 047-95-p1 // 047-95-p1 additionalResponseData // uniqueTransactionIdValue // Max49Text // DNS // // Unique transaction Id value // // RSB47_95_p2 // 047-95-p2 // 047-95-p2 // 047-95-p2 | F148: Etude croisée Capture / Precomp sur les transferts d'informations.
A149: 21.9 | B149: M.Marghad | C149: 46077 | D149: Acquisition | E149: Création des attributs : Context//executionContractFinancialParameters//merchantSettlementIban//IBANIdentifier Context//executionContractFinancialParameters//merchantFeesIban//IBANIdentifier
A150: 21.9 | B150: G.HARAGHI | C150: 46076 | D150: Emission | E150: Créations : transaction//transactionDetails//exchangeRateInformation // ExchangeRateInformationType Création de la structure du type ExchangeRateInformationType ExchangeRateInformationType // network // NetworkCodeset ExchangeRateInformationType // exchangeRateOrigin // ExchangeRateOriginCodeset ExchangeRateInformationType // exchangeRateProvider // Max70Text ExchangeRateInformationType // exchangeRate // Base25OneRate ExchangeRateInformationType // rateTableId // Max5AlphaNumericText ExchangeRateInformationType // persistentFxEligibleIndicator // TrueFalseIndicator ExchangeRateInformationType // rateDiffSign // DebitCreditCodeset ExchangeRateInformationType // rateDiffPercent // Exact6NumericText Création du codeset ExchangeRateOrigin Attributs Obsolétes : Transaction // TrasactionDetails // currencyConversionRateNomenclature Transaction // TrasactionDetails // mastercardCurrencyConversionRateData Transaction // TrasactionDetails // visaCurrencyConversionRateData | F150: BK-9538
A151: 21.9 | B151: B.Porcher | C151: 46070 | D151: PRECOMP | E151: Creation de l'attribut : includedPreClearingDateTim dans remittanceData 260217141500 // Transaction // remittanceData // includedPreClearingDateTime // ISODateTime // DNS // // Date and time the remittance was included in the PreClearing process. | F151: BK9610 Loic Jean
A152: 21.9 | B152: B.Porcher | C152: 46066 | D152: TLC | E152: Complément pour le code set : ElectronicCommerceAuthenticationNatureCodeset Ajout des valeurs du CB2A dans le libellé du Codeset. | F152: Loic et Lamine
A153: 21.9 | B153: A.Vounki | C153: 46066 | D153: SMHSM | E153: Suppression des valeurs ISO5 et NPIN de PinBlockFormatCodeset | F153: BK-8902
A154: 21.9 | B154: B.Porcher | C154: 46065 | D154: PRECOMP | E154: Creation de l'attribut : includedPreClearingDateTime dans ClearingData 260212175400 // Transaction // clearingData // includedPreClearingDateTime // ISODateTime // DNS // // Date and time the transaction was included in the PreClearing process. | F154: BK9610 Loic Jean
A155: 21.9 | B155: B.Porcher | C155: 46065 | D155: PRECOMP | E155: Modification de l'attribut : includedDataTime devient includedClearingDateTime 251112091000 // Transaction // clearingData // includedClearingDateTime // ISODateTime // DNS // // Date and time the transaction was included in the clearing process. | F155: BK9610 Loic Jean
A156: 21.9 | B156: B. Porcher | C156: 46065 | D156: PRECOMP | E156: Ajout d'une valeur de Codeset : ProcessingStageCodeset // Exact4Text // NCRE // Clearing – Non completed // ajusted Remittance | F156: BK9610 Loic Jean
A157: 21.8 | B157: B.Porcher | C157: 46065 | D157: TLC | E157: Création de captureFileId 260212084000 // Transaction // fileData // captureFileId // UUIDType // DNS // // File identification defined by capture process - Double information with stampingReference | F157: Bruno Porcher - Symétrie avec CaptureRemittanceId et captureTransId
A158: 21.8 | B158: B.Porcher | C158: 46064 | D158: TLC | E158: Modification du nom des attributs pour intégrer Error : 250915172700 // Transaction // remittanceData // captureErrorNumberOfRelevantField // Exact3AlphaNumericText // DNS // // Capture Error Number Of Relevant Field // // // // 047-0047-p2 250915172702 // Transaction // remittanceData // captureErrorTypeOfRelevantField // Exact4AlphaNumericText // DNS // // Capture Error Type Of Relevant Field // // // // 047-0047-p3* | F158: Lamine Seck & Luc Vanel BK-9585
A159: 21.8 | B159: B.Porcher | C159: 46064 | D159: TLC | E159: Attribut lengthOfDataElementToFollow est obsolète L'attribut est finalement inutile. 250425201612 // Context // pointOfServiceContext // lengthOfDataElementToFollow // Max3NumericText // DNS // OBSOLETE // Length of data element to follow // // // // 031-p2 | F159: Lamine Seck & Luc Vanel BK-9585
A160: 21.8 | B160: B.Porcher | C160: 46064 | D160: TLC | E160: Modification de l'attribut dataCategory qui devient printDisplayDataCategory de type PrintDisplayDataCategoryCodeset 250425201611 // Context // pointOfServiceContext // printDisplayDataCategory // PrintDisplayDataCategoryCodeset // DNS // // Data type to print or display on acceptor device// // // // 031-p1 | F160: Lamine Seck & Luc Vanel BK-9585
A161: 21.8 | B161: B.Porcher | C161: 46064 | D161: TLC | E161: Modification de l'attribut printDispalyData qui devient printDisplayDataValue 260205110200 // Context // pointOfServiceContext // printDisplayDataValue // Max250AlphaNumericText // DNS // // Data to print or display on acceptor device - Sensible data not accepted// // // 031-p3 | F161: Lamine Seck & Luc Vanel BK-9585
... A172: 21.8 | B172: B.Porcher | C172: 46058 | D172: TLC | E172: Remplacement de l'objet transactionDetails par remittanceData (attributs pas encore utilisé dans des Contrats) 250915172600 // Transaction // remittanceData // captureErrorCode // CaptureErrorCodeCodeset // DNS // // Capture Error code 250915172700 // Transaction // remittanceData // captureNumberOfRelevantField // Exact3AlphaNumericText // DNS // // Capture Number Of Relevant Field 250915172702 // Transaction // remittanceData // captureTypeOfRelevantField // Exact4AlphaNumericText // DNS // // Capture Type Of Relevant Field | F172: Lamine Seck BK-9585
...

Sheet MON_MSG
A1: Référence | B1: Segment | C1: Object | D1: Attribute | E1: Type | F1: Libellé | G1: Description | H1: Obligatoire | I1: Répétable | J1: Liste de valeurs du codeset | K1: Ancien Flux | L1: Ancien Nom | M1: Ancien Format | N1: TLP | O1: Autor | P1: Capture | Q1: Precomp | R1: Compens | S1: Litiges | T1: MàJ | U1: Obsolete
A2: 241112000000 | U2: =IF(VLOOKUP($A2,DICO_Complet!A:R,9,FALSE)<>0,VLOOKUP($A2,DICO_Complet!A:R,9,FALSE),"")
A3: 241112000001 | U3: =IF(VLOOKUP($A3,DICO_Complet!A:R,9,FALSE)<>0,VLOOKUP($A3,DICO_Complet!A:R,9,FALSE),"")
A4: 241112000003 | U4: =IF(VLOOKUP($A4,DICO_Complet!A:R,9,FALSE)<>0,VLOOKUP($A4,DICO_Complet!A:R,9,FALSE),"")
A5: 241112000004 | U5: =IF(VLOOKUP($A5,DICO_Complet!A:R,9,FALSE)<>0,VLOOKUP($A5,DICO_Complet!A:R,9,FALSE),"")
A6: 241112000002 | U6: =IF(VLOOKUP($A6,DICO_Complet!A:R,9,FALSE)<>0,VLOOKUP($A6,DICO_Complet!A:R,9,FALSE),"")
A7: 250331114316 | U7: =IF(VLOOKUP($A7,DICO_Complet!A:R,9,FALSE)<>0,VLOOKUP($A7,DICO_Complet!A:R,9,FALSE),"")
A8: 250528104041 | U8: =IF(VLOOKUP($A8,DICO_Complet!A:R,9,FALSE)<>0,VLOOKUP($A8,DICO_Complet!A:R,9,FALSE),"")
A9: 250717102622 | U9: =IF(VLOOKUP($A9,DICO_Complet!A:R,9,FALSE)<>0,VLOOKUP($A9,DICO_Complet!A:R,9,FALSE),"")
A10: 250717102624 | U10: =IF(VLOOKUP($A10,DICO_Complet!A:R,9,FALSE)<>0,VLOOKUP($A10,DICO_Complet!A:R,9,FALSE),"")
A11: 250717102623 | U11: =IF(VLOOKUP($A11,DICO_Complet!A:R,9,FALSE)<>0,VLOOKUP($A11,DICO_Complet!A:R,9,FALSE),"")
A12: 250723172700 | U12: =IF(VLOOKUP($A12,DICO_Complet!A:R,9,FALSE)<>0,VLOOKUP($A12,DICO_Complet!A:R,9,FALSE),"")
A13: 250717102602 | U13: =IF(VLOOKUP($A13,DICO_Complet!A:R,9,FALSE)<>0,VLOOKUP($A13,DICO_Complet!A:R,9,FALSE),"")
... A1833: 260608100200 | U1833: =IF(VLOOKUP($A1833,DICO_Complet!A:R,9,FALSE)<>0,VLOOKUP($A1833,DICO_Complet!A:R,9,FALSE),"")

Sheet MSG_Export
B1: De MON_MSG | C1: Champs reportés de DICO_COMPLET | K1: Champs reportés de MON_MSG | N1: Champs reportés de DICO_COMPLET
A2: Référence | B2: O/N | C2: Segment Message | D2: Object | E2: Attribute | F2: Type | G2: Sensitivty | H2: Colonne2 | I2: Obsolete | J2: Libellé | K2: Description fonctionnelle | L2: Obligatoire | M2: Repetable | N2: CIFO | O2: CBAE | P2: CB2AF | Q2: CB2A | R2: VISA | S2: MCD | T2: Mainframe | U2: .
A3: 241112000000 | B3: =IF(ISNA(VLOOKUP(Tableau161920[[#This Row],[Référence]],MON_MSG!A:B,2,FALSE)),"N",IF($I3="Obsolete","N","O")) -> O | C3: =VLOOKUP($A3,DICO_Complet!A:R,3,FALSE) -> ApiResponse | D3: =VLOOKUP($A3,DICO_Complet!A:R,4,FALSE) -> error | E3: =VLOOKUP($A3,DICO_Complet!A:R,5,FALSE) -> code | F3: =VLOOKUP($A3,DICO_Complet!A:R,6,FALSE) -> Max20Text | G3: =VLOOKUP($A3,DICO_Complet!A:R,7,FALSE) -> DNS | H3: =VLOOKUP($A3,DICO_Complet!A:R,8,FALSE) -> 0 | I3: =IF(VLOOKUP($A3,DICO_Complet!A:R,9,FALSE)<>0,VLOOKUP($A3,DICO_Complet!A:R,9,FALSE),"") | J3: =VLOOKUP($A3,DICO_Complet!A:R,10,FALSE) -> Error code | K3: =IF(OR(ISNA(VLOOKUP(Tableau161920[[#This Row],[Référence]],MON_MSG!A:H,7,FALSE)),ISBLANK(VLOOKUP(Tableau161920[[#This Row],[Référence]],MON_MSG!A:H,7,FALSE))),"",VLOOKUP(Tableau161920[[#This Row],[Référence]],MON_MSG!A:H,7,FALSE)) | L3: =IF(OR(ISNA(VLOOKUP(Tableau161920[[#This Row],[Référence]],MON_MSG!A:I,8,FALSE)),ISBLANK(VLOOKUP(Tableau161920[[#This Row],[Référence]],MON_MSG!A:I,8,FALSE))),"",VLOOKUP(Tableau161920[[#This Row],[Référence]],MON_MSG!A:I,8,FALSE)) | M3: =IF(OR(ISNA(VLOOKUP(Tableau161920[[#This Row],[Référence]],MON_MSG!A:J,9,FALSE)),ISBLANK(VLOOKUP(Tableau161920[[#This Row],[Référence]],MON_MSG!A:J,9,FALSE))),"",VLOOKUP(Tableau161920[[#This Row],[Référence]],MON_MSG!A:J,9,FALSE)) | N3: =IF(VLOOKUP($A3,DICO_Complet!A:R,12,FALSE)=0,"",VLOOKUP($A3,DICO_Complet!A:R,12,FALSE)) | O3: =IF(VLOOKUP($A3,DICO_Complet!A:R,13,FALSE)=0,"",VLOOKUP($A3,DICO_Complet!A:R,13,FALSE)) | P3: =IF(VLOOKUP($A3,DICO_Complet!A:R,14,FALSE)=0,"",VLOOKUP($A3,DICO_Complet!A:R,14,FALSE)) | Q3: =IF(VLOOKUP($A3,DICO_Complet!A:R,15,FALSE)=0,"",VLOOKUP($A3,DICO_Complet!A:R,15,FALSE)) | R3: =IF(VLOOKUP($A3,DICO_Complet!A:R,16,FALSE)=0,"",VLOOKUP($A3,DICO_Complet!A:R,16,FALSE)) | S3: =IF(VLOOKUP($A3,DICO_Complet!A:R,17,FALSE)=0,"",VLOOKUP($A3,DICO_Complet!A:R,17,FALSE)) | T3: =IF(VLOOKUP($A3,DICO_Complet!A:R,18,FALSE)=0,"",VLOOKUP($A3,DICO_Complet!A:R,18,FALSE))
A4: 241112000001 | B4: =IF(ISNA(VLOOKUP(Tableau161920[[#This Row],[Référence]],MON_MSG!A:B,2,FALSE)),"N",IF($I4="Obsolete","N","O")) -> O | C4: =VLOOKUP($A4,DICO_Complet!A:R,3,FALSE) -> ApiResponse | D4: =VLOOKUP($A4,DICO_Complet!A:R,4,FALSE) -> error | E4: =VLOOKUP($A4,DICO_Complet!A:R,5,FALSE) -> developerText | F4: =VLOOKUP($A4,DICO_Complet!A:R,6,FALSE) -> Max70Text | G4: =VLOOKUP($A4,DICO_Complet!A:R,7,FALSE) -> DNS | H4: =VLOOKUP($A4,DICO_Complet!A:R,8,FALSE) -> 0 | I4: =IF(VLOOKUP($A4,DICO_Complet!A:R,9,FALSE)<>0,VLOOKUP($A4,DICO_Complet!A:R,9,FALSE),"") | J4: =VLOOKUP($A4,DICO_Complet!A:R,10,FALSE) -> Explains possible reason(s) of the error, and possible corrections | K4: =IF(OR(ISNA(VLOOKUP(Tableau161920[[#This Row],[Référence]],MON_MSG!A:H,7,FALSE)),ISBLANK(VLOOKUP(Tableau161920[[#This Row],[Référence]],MON_MSG!A:H,7,FALSE))),"",VLOOKUP(Tableau161920[[#This Row],[Référence]],MON_MSG!A:H,7,FALSE)) | L4: =IF(OR(ISNA(VLOOKUP(Tableau161920[[#This Row],[Référence]],MON_MSG!A:I,8,FALSE)),ISBLANK(VLOOKUP(Tableau161920[[#This Row],[Référence]],MON_MSG!A:I,8,FALSE))),"",VLOOKUP(Tableau161920[[#This Row],[Référence]],MON_MSG!A:I,8,FALSE)) | M4: =IF(OR(ISNA(VLOOKUP(Tableau161920[[#This Row],[Référence]],MON_MSG!A:J,9,FALSE)),ISBLANK(VLOOKUP(Tableau161920[[#This Row],[Référence]],MON_MSG!A:J,9,FALSE))),"",VLOOKUP(Tableau161920[[#This Row],[Référence]],MON_MSG!A:J,9,FALSE)) | N4: =IF(VLOOKUP($A4,DICO_Complet!A:R,12,FALSE)=0,"",VLOOKUP($A4,DICO_Complet!A:R,12,FALSE)) | O4: =IF(VLOOKUP($A4,DICO_Complet!A:R,13,FALSE)=0,"",VLOOKUP($A4,DICO_Complet!A:R,13,FALSE)) | P4: =IF(VLOOKUP($A4,DICO_Complet!A:R,14,FALSE)=0,"",VLOOKUP($A4,DICO_Complet!A:R,14,FALSE)) | Q4: =IF(VLOOKUP($A4,DICO_Complet!A:R,15,FALSE)=0,"",VLOOKUP($A4,DICO_Complet!A:R,15,FALSE)) | R4: =IF(VLOOKUP($A4,DICO_Complet!A:R,16,FALSE)=0,"",VLOOKUP($A4,DICO_Complet!A:R,16,FALSE)) | S4: =IF(VLOOKUP($A4,DICO_Complet!A:R,17,FALSE)=0,"",VLOOKUP($A4,DICO_Complet!A:R,17,FALSE)) | T4: =IF(VLOOKUP($A4,DICO_Complet!A:R,18,FALSE)=0,"",VLOOKUP($A4,DICO_Complet!A:R,18,FALSE))
A5: 241112000003 | B5: =IF(ISNA(VLOOKUP(Tableau161920[[#This Row],[Référence]],MON_MSG!A:B,2,FALSE)),"N",IF($I5="Obsolete","N","O")) -> O | C5: =VLOOKUP($A5,DICO_Complet!A:R,3,FALSE) -> ApiResponse | D5: =VLOOKUP($A5,DICO_Complet!A:R,4,FALSE) -> error | E5: =VLOOKUP($A5,DICO_Complet!A:R,5,FALSE) -> moreInfo | F5: =VLOOKUP($A5,DICO_Complet!A:R,6,FALSE) -> Max256Text | G5: =VLOOKUP($A5,DICO_Complet!A:R,7,FALSE) -> DNS | H5: =VLOOKUP($A5,DICO_Complet!A:R,8,FALSE) -> 0 | I5: =IF(VLOOKUP($A5,DICO_Complet!A:R,9,FALSE)<>0,VLOOKUP($A5,DICO_Complet!A:R,9,FALSE),"") | J5: =VLOOKUP($A5,DICO_Complet!A:R,10,FALSE) -> URI to documents | K5: =IF(OR(ISNA(VLOOKUP(Tableau161920[[#This Row],[Référence]],MON_MSG!A:H,7,FALSE)),ISBLANK(VLOOKUP(Tableau161920[[#This Row],[Référence]],MON_MSG!A:H,7,FALSE))),"",VLOOKUP(Tableau161920[[#This Row],[Référence]],MON_MSG!A:H,7,FALSE)) | L5: =IF(OR(ISNA(VLOOKUP(Tableau161920[[#This Row],[Référence]],MON_MSG!A:I,8,FALSE)),ISBLANK(VLOOKUP(Tableau161920[[#This Row],[Référence]],MON_MSG!A:I,8,FALSE))),"",VLOOKUP(Tableau161920[[#This Row],[Référence]],MON_MSG!A:I,8,FALSE)) | M5: =IF(OR(ISNA(VLOOKUP(Tableau161920[[#This Row],[Référence]],MON_MSG!A:J,9,FALSE)),ISBLANK(VLOOKUP(Tableau161920[[#This Row],[Référence]],MON_MSG!A:J,9,FALSE))),"",VLOOKUP(Tableau161920[[#This Row],[Référence]],MON_MSG!A:J,9,FALSE)) | N5: =IF(VLOOKUP($A5,DICO_Complet!A:R,12,FALSE)=0,"",VLOOKUP($A5,DICO_Complet!A:R,12,FALSE)) | O5: =IF(VLOOKUP($A5,DICO_Complet!A:R,13,FALSE)=0,"",VLOOKUP($A5,DICO_Complet!A:R,13,FALSE)) | P5: =IF(VLOOKUP($A5,DICO_Complet!A:R,14,FALSE)=0,"",VLOOKUP($A5,DICO_Complet!A:R,14,FALSE)) | Q5: =IF(VLOOKUP($A5,DICO_Complet!A:R,15,FALSE)=0,"",VLOOKUP($A5,DICO_Complet!A:R,15,FALSE)) | R5: =IF(VLOOKUP($A5,DICO_Complet!A:R,16,FALSE)=0,"",VLOOKUP($A5,DICO_Complet!A:R,16,FALSE)) | S5: =IF(VLOOKUP($A5,DICO_Complet!A:R,17,FALSE)=0,"",VLOOKUP($A5,DICO_Complet!A:R,17,FALSE)) | T5: =IF(VLOOKUP($A5,DICO_Complet!A:R,18,FALSE)=0,"",VLOOKUP($A5,DICO_Complet!A:R,18,FALSE))
A6: 241112000004 | B6: =IF(ISNA(VLOOKUP(Tableau161920[[#This Row],[Référence]],MON_MSG!A:B,2,FALSE)),"N",IF($I6="Obsolete","N","O")) -> O | C6: =VLOOKUP($A6,DICO_Complet!A:R,3,FALSE) -> ApiResponse | D6: =VLOOKUP($A6,DICO_Complet!A:R,4,FALSE) -> error | E6: =VLOOKUP($A6,DICO_Complet!A:R,5,FALSE) -> text | F6: =VLOOKUP($A6,DICO_Complet!A:R,6,FALSE) -> Max40Text | G6: =VLOOKUP($A6,DICO_Complet!A:R,7,FALSE) -> DNS | H6: =VLOOKUP($A6,DICO_Complet!A:R,8,FALSE) -> 0 | I6: =IF(VLOOKUP($A6,DICO_Complet!A:R,9,FALSE)<>0,VLOOKUP($A6,DICO_Complet!A:R,9,FALSE),"") | J6: =VLOOKUP($A6,DICO_Complet!A:R,10,FALSE) -> short text that explains the error in a language that is useful for the end-user of the service | K6: =IF(OR(ISNA(VLOOKUP(Tableau161920[[#This Row],[Référence]],MON_MSG!A:H,7,FALSE)),ISBLANK(VLOOKUP(Tableau161920[[#This Row],[Référence]],MON_MSG!A:H,7,FALSE))),"",VLOOKUP(Tableau161920[[#This Row],[Référence]],MON_MSG!A:H,7,FALSE)) | L6: =IF(OR(ISNA(VLOOKUP(Tableau161920[[#This Row],[Référence]],MON_MSG!A:I,8,FALSE)),ISBLANK(VLOOKUP(Tableau161920[[#This Row],[Référence]],MON_MSG!A:I,8,FALSE))),"",VLOOKUP(Tableau161920[[#This Row],[Référence]],MON_MSG!A:I,8,FALSE)) | M6: =IF(OR(ISNA(VLOOKUP(Tableau161920[[#This Row],[Référence]],MON_MSG!A:J,9,FALSE)),ISBLANK(VLOOKUP(Tableau161920[[#This Row],[Référence]],MON_MSG!A:J,9,FALSE))),"",VLOOKUP(Tableau161920[[#This Row],[Référence]],MON_MSG!A:J,9,FALSE)) | N6: =IF(VLOOKUP($A6,DICO_Complet!A:R,12,FALSE)=0,"",VLOOKUP($A6,DICO_Complet!A:R,12,FALSE)) | O6: =IF(VLOOKUP($A6,DICO_Complet!A:R,13,FALSE)=0,"",VLOOKUP($A6,DICO_Complet!A:R,13,FALSE)) | P6: =IF(VLOOKUP($A6,DICO_Complet!A:R,14,FALSE)=0,"",VLOOKUP($A6,DICO_Complet!A:R,14,FALSE)) | Q6: =IF(VLOOKUP($A6,DICO_Complet!A:R,15,FALSE)=0,"",VLOOKUP($A6,DICO_Complet!A:R,15,FALSE)) | R6: =IF(VLOOKUP($A6,DICO_Complet!A:R,16,FALSE)=0,"",VLOOKUP($A6,DICO_Complet!A:R,16,FALSE)) | S6: =IF(VLOOKUP($A6,DICO_Complet!A:R,17,FALSE)=0,"",VLOOKUP($A6,DICO_Complet!A:R,17,FALSE)) | T6: =IF(VLOOKUP($A6,DICO_Complet!A:R,18,FALSE)=0,"",VLOOKUP($A6,DICO_Complet!A:R,18,FALSE))
A7: 241112000002 | B7: =IF(ISNA(VLOOKUP(Tableau161920[[#This Row],[Référence]],MON_MSG!A:B,2,FALSE)),"N",IF($I7="Obsolete","N","O")) -> O | C7: =VLOOKUP($A7,DICO_Complet!A:R,3,FALSE) -> ApiResponse | D7: =VLOOKUP($A7,DICO_Complet!A:R,4,FALSE) -> httpStatus | E7: =VLOOKUP($A7,DICO_Complet!A:R,5,FALSE) -> httpCode | F7: =VLOOKUP($A7,DICO_Complet!A:R,6,FALSE) -> Exact3NumericText | G7: =VLOOKUP($A7,DICO_Complet!A:R,7,FALSE) -> DNS | H7: =VLOOKUP($A7,DICO_Complet!A:R,8,FALSE) -> 0 | I7: =IF(VLOOKUP($A7,DICO_Complet!A:R,9,FALSE)<>0,VLOOKUP($A7,DICO_Complet!A:R,9,FALSE),"") | J7: =VLOOKUP($A7,DICO_Complet!A:R,10,FALSE) -> Status code http | K7: =IF(OR(ISNA(VLOOKUP(Tableau161920[[#This Row],[Référence]],MON_MSG!A:H,7,FALSE)),ISBLANK(VLOOKUP(Tableau161920[[#This Row],[Référence]],MON_MSG!A:H,7,FALSE))),"",VLOOKUP(Tableau161920[[#This Row],[Référence]],MON_MSG!A:H,7,FALSE)) | L7: =IF(OR(ISNA(VLOOKUP(Tableau161920[[#This Row],[Référence]],MON_MSG!A:I,8,FALSE)),ISBLANK(VLOOKUP(Tableau161920[[#This Row],[Référence]],MON_MSG!A:I,8,FALSE))),"",VLOOKUP(Tableau161920[[#This Row],[Référence]],MON_MSG!A:I,8,FALSE)) | M7: =IF(OR(ISNA(VLOOKUP(Tableau161920[[#This Row],[Référence]],MON_MSG!A:J,9,FALSE)),ISBLANK(VLOOKUP(Tableau161920[[#This Row],[Référence]],MON_MSG!A:J,9,FALSE))),"",VLOOKUP(Tableau161920[[#This Row],[Référence]],MON_MSG!A:J,9,FALSE)) | N7: =IF(VLOOKUP($A7,DICO_Complet!A:R,12,FALSE)=0,"",VLOOKUP($A7,DICO_Complet!A:R,12,FALSE)) | O7: =IF(VLOOKUP($A7,DICO_Complet!A:R,13,FALSE)=0,"",VLOOKUP($A7,DICO_Complet!A:R,13,FALSE)) | P7: =IF(VLOOKUP($A7,DICO_Complet!A:R,14,FALSE)=0,"",VLOOKUP($A7,DICO_Complet!A:R,14,FALSE)) | Q7: =IF(VLOOKUP($A7,DICO_Complet!A:R,15,FALSE)=0,"",VLOOKUP($A7,DICO_Complet!A:R,15,FALSE)) | R7: =IF(VLOOKUP($A7,DICO_Complet!A:R,16,FALSE)=0,"",VLOOKUP($A7,DICO_Complet!A:R,16,FALSE)) | S7: =IF(VLOOKUP($A7,DICO_Complet!A:R,17,FALSE)=0,"",VLOOKUP($A7,DICO_Complet!A:R,17,FALSE)) | T7: =IF(VLOOKUP($A7,DICO_Complet!A:R,18,FALSE)=0,"",VLOOKUP($A7,DICO_Complet!A:R,18,FALSE))
A8: 250331114316 | B8: =IF(ISNA(VLOOKUP(Tableau161920[[#This Row],[Référence]],MON_MSG!A:B,2,FALSE)),"N",IF($I8="Obsolete","N","O")) -> O | C8: =VLOOKUP($A8,DICO_Complet!A:R,3,FALSE) -> ApiResponse | D8: =VLOOKUP($A8,DICO_Complet!A:R,4,FALSE) -> httpStatus | E8: =VLOOKUP($A8,DICO_Complet!A:R,5,FALSE) -> requestId | F8: =VLOOKUP($A8,DICO_Complet!A:R,6,FALSE) -> Max36NumericText | G8: =VLOOKUP($A8,DICO_Complet!A:R,7,FALSE) -> DNS | H8: =VLOOKUP($A8,DICO_Complet!A:R,8,FALSE) -> 0 | I8: =IF(VLOOKUP($A8,DICO_Complet!A:R,9,FALSE)<>0,VLOOKUP($A8,DICO_Complet!A:R,9,FALSE),"") | J8: =VLOOKUP($A8,DICO_Complet!A:R,10,FALSE) -> Unique ID of API response | K8: =IF(OR(ISNA(VLOOKUP(Tableau161920[[#This Row],[Référence]],MON_MSG!A:H,7,FALSE)),ISBLANK(VLOOKUP(Tableau161920[[#This Row],[Référence]],MON_MSG!A:H,7,FALSE))),"",VLOOKUP(Tableau161920[[#This Row],[Référence]],MON_MSG!A:H,7,FALSE)) | L8: =IF(OR(ISNA(VLOOKUP(Tableau161920[[#This Row],[Référence]],MON_MSG!A:I,8,FALSE)),ISBLANK(VLOOKUP(Tableau161920[[#This Row],[Référence]],MON_MSG!A:I,8,FALSE))),"",VLOOKUP(Tableau161920[[#This Row],[Référence]],MON_MSG!A:I,8,FALSE)) | M8: =IF(OR(ISNA(VLOOKUP(Tableau161920[[#This Row],[Référence]],MON_MSG!A:J,9,FALSE)),ISBLANK(VLOOKUP(Tableau161920[[#This Row],[Référence]],MON_MSG!A:J,9,FALSE))),"",VLOOKUP(Tableau161920[[#This Row],[Référence]],MON_MSG!A:J,9,FALSE)) | N8: =IF(VLOOKUP($A8,DICO_Complet!A:R,12,FALSE)=0,"",VLOOKUP($A8,DICO_Complet!A:R,12,FALSE)) | O8: =IF(VLOOKUP($A8,DICO_Complet!A:R,13,FALSE)=0,"",VLOOKUP($A8,DICO_Complet!A:R,13,FALSE)) | P8: =IF(VLOOKUP($A8,DICO_Complet!A:R,14,FALSE)=0,"",VLOOKUP($A8,DICO_Complet!A:R,14,FALSE)) | Q8: =IF(VLOOKUP($A8,DICO_Complet!A:R,15,FALSE)=0,"",VLOOKUP($A8,DICO_Complet!A:R,15,FALSE)) | R8: =IF(VLOOKUP($A8,DICO_Complet!A:R,16,FALSE)=0,"",VLOOKUP($A8,DICO_Complet!A:R,16,FALSE)) | S8: =IF(VLOOKUP($A8,DICO_Complet!A:R,17,FALSE)=0,"",VLOOKUP($A8,DICO_Complet!A:R,17,FALSE)) | T8: =IF(VLOOKUP($A8,DICO_Complet!A:R,18,FALSE)=0,"",VLOOKUP($A8,DICO_Complet!A:R,18,FALSE))
A9: 250528104041 | B9: =IF(ISNA(VLOOKUP(Tableau161920[[#This Row],[Référence]],MON_MSG!A:B,2,FALSE)),"N",IF($I9="Obsolete","N","O")) -> O | C9: =VLOOKUP($A9,DICO_Complet!A:R,3,FALSE) -> AuditTrail | D9: =VLOOKUP($A9,DICO_Complet!A:R,4,FALSE) -> auditTrail | E9: =VLOOKUP($A9,DICO_Complet!A:R,5,FALSE) -> alertDateTime | F9: =VLOOKUP($A9,DICO_Complet!A:R,6,FALSE) -> ISODateTime | G9: =VLOOKUP($A9,DICO_Complet!A:R,7,FALSE) -> DNS | H9: =VLOOKUP($A9,DICO_Complet!A:R,8,FALSE) -> 0 | I9: =IF(VLOOKUP($A9,DICO_Complet!A:R,9,FALSE)<>0,VLOOKUP($A9,DICO_Complet!A:R,9,FALSE),"") | J9: =VLOOKUP($A9,DICO_Complet!A:R,10,FALSE) -> Alert date time | K9: =IF(OR(ISNA(VLOOKUP(Tableau161920[[#This Row],[Référence]],MON_MSG!A:H,7,FALSE)),ISBLANK(VLOOKUP(Tableau161920[[#This Row],[Référence]],MON_MSG!A:H,7,FALSE))),"",VLOOKUP(Tableau161920[[#This Row],[Référence]],MON_MSG!A:H,7,FALSE)) | L9: =IF(OR(ISNA(VLOOKUP(Tableau161920[[#This Row],[Référence]],MON_MSG!A:I,8,FALSE)),ISBLANK(VLOOKUP(Tableau161920[[#This Row],[Référence]],MON_MSG!A:I,8,FALSE))),"",VLOOKUP(Tableau161920[[#This Row],[Référence]],MON_MSG!A:I,8,FALSE)) | M9: =IF(OR(ISNA(VLOOKUP(Tableau161920[[#This Row],[Référence]],MON_MSG!A:J,9,FALSE)),ISBLANK(VLOOKUP(Tableau161920[[#This Row],[Référence]],MON_MSG!A:J,9,FALSE))),"",VLOOKUP(Tableau161920[[#This Row],[Référence]],MON_MSG!A:J,9,FALSE)) | N9: =IF(VLOOKUP($A9,DICO_Complet!A:R,12,FALSE)=0,"",VLOOKUP($A9,DICO_Complet!A:R,12,FALSE)) | O9: =IF(VLOOKUP($A9,DICO_Complet!A:R,13,FALSE)=0,"",VLOOKUP($A9,DICO_Complet!A:R,13,FALSE)) | P9: =IF(VLOOKUP($A9,DICO_Complet!A:R,14,FALSE)=0,"",VLOOKUP($A9,DICO_Complet!A:R,14,FALSE)) | Q9: =IF(VLOOKUP($A9,DICO_Complet!A:R,15,FALSE)=0,"",VLOOKUP($A9,DICO_Complet!A:R,15,FALSE)) | R9: =IF(VLOOKUP($A9,DICO_Complet!A:R,16,FALSE)=0,"",VLOOKUP($A9,DICO_Complet!A:R,16,FALSE)) | S9: =IF(VLOOKUP($A9,DICO_Complet!A:R,17,FALSE)=0,"",VLOOKUP($A9,DICO_Complet!A:R,17,FALSE)) | T9: =IF(VLOOKUP($A9,DICO_Complet!A:R,18,FALSE)=0,"",VLOOKUP($A9,DICO_Complet!A:R,18,FALSE))
A10: 250717102622 | B10: =IF(ISNA(VLOOKUP(Tableau161920[[#This Row],[Référence]],MON_MSG!A:B,2,FALSE)),"N",IF($I10="Obsolete","N","O")) -> O | C10: =VLOOKUP($A10,DICO_Complet!A:R,3,FALSE) -> AuditTrail | D10: =VLOOKUP($A10,DICO_Complet!A:R,4,FALSE) -> auditTrail | E10: =VLOOKUP($A10,DICO_Complet!A:R,5,FALSE) -> alertMessage | F10: =VLOOKUP($A10,DICO_Complet!A:R,6,FALSE) -> Max255Text | G10: =VLOOKUP($A10,DICO_Complet!A:R,7,FALSE) -> DNS | H10: =VLOOKUP($A10,DICO_Complet!A:R,8,FALSE) -> 0 | I10: =IF(VLOOKUP($A10,DICO_Complet!A:R,9,FALSE)<>0,VLOOKUP($A10,DICO_Complet!A:R,9,FALSE),"") | J10: =VLOOKUP($A10,DICO_Complet!A:R,10,FALSE) -> Message content | K10: =IF(OR(ISNA(VLOOKUP(Tableau161920[[#This Row],[Référence]],MON_MSG!A:H,7,FALSE)),ISBLANK(VLOOKUP(Tableau161920[[#This Row],[Référence]],MON_MSG!A:H,7,FALSE))),"",VLOOKUP(Tableau161920[[#This Row],[Référence]],MON_MSG!A:H,7,FALSE)) | L10: =IF(OR(ISNA(VLOOKUP(Tableau161920[[#This Row],[Référence]],MON_MSG!A:I,8,FALSE)),ISBLANK(VLOOKUP(Tableau161920[[#This Row],[Référence]],MON_MSG!A:I,8,FALSE))),"",VLOOKUP(Tableau161920[[#This Row],[Référence]],MON_MSG!A:I,8,FALSE)) | M10: =IF(OR(ISNA(VLOOKUP(Tableau161920[[#This Row],[Référence]],MON_MSG!A:J,9,FALSE)),ISBLANK(VLOOKUP(Tableau161920[[#This Row],[Référence]],MON_MSG!A:J,9,FALSE))),"",VLOOKUP(Tableau161920[[#This Row],[Référence]],MON_MSG!A:J,9,FALSE)) | N10: =IF(VLOOKUP($A10,DICO_Complet!A:R,12,FALSE)=0,"",VLOOKUP($A10,DICO_Complet!A:R,12,FALSE)) | O10: =IF(VLOOKUP($A10,DICO_Complet!A:R,13,FALSE)=0,"",VLOOKUP($A10,DICO_Complet!A:R,13,FALSE)) | P10: =IF(VLOOKUP($A10,DICO_Complet!A:R,14,FALSE)=0,"",VLOOKUP($A10,DICO_Complet!A:R,14,FALSE)) | Q10: =IF(VLOOKUP($A10,DICO_Complet!A:R,15,FALSE)=0,"",VLOOKUP($A10,DICO_Complet!A:R,15,FALSE)) | R10: =IF(VLOOKUP($A10,DICO_Complet!A:R,16,FALSE)=0,"",VLOOKUP($A10,DICO_Complet!A:R,16,FALSE)) | S10: =IF(VLOOKUP($A10,DICO_Complet!A:R,17,FALSE)=0,"",VLOOKUP($A10,DICO_Complet!A:R,17,FALSE)) | T10: =IF(VLOOKUP($A10,DICO_Complet!A:R,18,FALSE)=0,"",VLOOKUP($A10,DICO_Complet!A:R,18,FALSE))
A11: 250717102624 | B11: =IF(ISNA(VLOOKUP(Tableau161920[[#This Row],[Référence]],MON_MSG!A:B,2,FALSE)),"N",IF($I11="Obsolete","N","O")) -> O | C11: =VLOOKUP($A11,DICO_Complet!A:R,3,FALSE) -> AuditTrail | D11: =VLOOKUP($A11,DICO_Complet!A:R,4,FALSE) -> auditTrail | E11: =VLOOKUP($A11,DICO_Complet!A:R,5,FALSE) -> alertRecipientEmailAddress | F11: =VLOOKUP($A11,DICO_Complet!A:R,6,FALSE) -> EmailAddressType | G11: =VLOOKUP($A11,DICO_Complet!A:R,7,FALSE) -> DSP | H11: =VLOOKUP($A11,DICO_Complet!A:R,8,FALSE) -> 0 | I11: =IF(VLOOKUP($A11,DICO_Complet!A:R,9,FALSE)<>0,VLOOKUP($A11,DICO_Complet!A:R,9,FALSE),"") | J11: =VLOOKUP($A11,DICO_Complet!A:R,10,FALSE) -> email that received the message | K11: =IF(OR(ISNA(VLOOKUP(Tableau161920[[#This Row],[Référence]],MON_MSG!A:H,7,FALSE)),ISBLANK(VLOOKUP(Tableau161920[[#This Row],[Référence]],MON_MSG!A:H,7,FALSE))),"",VLOOKUP(Tableau161920[[#This Row],[Référence]],MON_MSG!A:H,7,FALSE)) | L11: =IF(OR(ISNA(VLOOKUP(Tableau161920[[#This Row],[Référence]],MON_MSG!A:I,8,FALSE)),ISBLANK(VLOOKUP(Tableau161920[[#This Row],[Référence]],MON_MSG!A:I,8,FALSE))),"",VLOOKUP(Tableau161920[[#This Row],[Référence]],MON_MSG!A:I,8,FALSE)) | M11: =IF(OR(ISNA(VLOOKUP(Tableau161920[[#This Row],[Référence]],MON_MSG!A:J,9,FALSE)),ISBLANK(VLOOKUP(Tableau161920[[#This Row],[Référence]],MON_MSG!A:J,9,FALSE))),"",VLOOKUP(Tableau161920[[#This Row],[Référence]],MON_MSG!A:J,9,FALSE)) | N11: =IF(VLOOKUP($A11,DICO_Complet!A:R,12,FALSE)=0,"",VLOOKUP($A11,DICO_Complet!A:R,12,FALSE)) | O11: =IF(VLOOKUP($A11,DICO_Complet!A:R,13,FALSE)=0,"",VLOOKUP($A11,DICO_Complet!A:R,13,FALSE)) | P11: =IF(VLOOKUP($A11,DICO_Complet!A:R,14,FALSE)=0,"",VLOOKUP($A11,DICO_Complet!A:R,14,FALSE)) | Q11: =IF(VLOOKUP($A11,DICO_Complet!A:R,15,FALSE)=0,"",VLOOKUP($A11,DICO_Complet!A:R,15,FALSE)) | R11: =IF(VLOOKUP($A11,DICO_Complet!A:R,16,FALSE)=0,"",VLOOKUP($A11,DICO_Complet!A:R,16,FALSE)) | S11: =IF(VLOOKUP($A11,DICO_Complet!A:R,17,FALSE)=0,"",VLOOKUP($A11,DICO_Complet!A:R,17,FALSE)) | T11: =IF(VLOOKUP($A11,DICO_Complet!A:R,18,FALSE)=0,"",VLOOKUP($A11,DICO_Complet!A:R,18,FALSE))
A12: 250717102623 | B12: =IF(ISNA(VLOOKUP(Tableau161920[[#This Row],[Référence]],MON_MSG!A:B,2,FALSE)),"N",IF($I12="Obsolete","N","O")) -> O | C12: =VLOOKUP($A12,DICO_Complet!A:R,3,FALSE) -> AuditTrail | D12: =VLOOKUP($A12,DICO_Complet!A:R,4,FALSE) -> auditTrail | E12: =VLOOKUP($A12,DICO_Complet!A:R,5,FALSE) -> alertRecipientPhoneNumber | F12: =VLOOKUP($A12,DICO_Complet!A:R,6,FALSE) -> PhoneNumberText | G12: =VLOOKUP($A12,DICO_Complet!A:R,7,FALSE) -> DSP | H12: =VLOOKUP($A12,DICO_Complet!A:R,8,FALSE) -> 0 | I12: =IF(VLOOKUP($A12,DICO_Complet!A:R,9,FALSE)<>0,VLOOKUP($A12,DICO_Complet!A:R,9,FALSE),"") | J12: =VLOOKUP($A12,DICO_Complet!A:R,10,FALSE) -> Phone that received the message | K12: =IF(OR(ISNA(VLOOKUP(Tableau161920[[#This Row],[Référence]],MON_MSG!A:H,7,FALSE)),ISBLANK(VLOOKUP(Tableau161920[[#This Row],[Référence]],MON_MSG!A:H,7,FALSE))),"",VLOOKUP(Tableau161920[[#This Row],[Référence]],MON_MSG!A:H,7,FALSE)) | L12: =IF(OR(ISNA(VLOOKUP(Tableau161920[[#This Row],[Référence]],MON_MSG!A:I,8,FALSE)),ISBLANK(VLOOKUP(Tableau161920[[#This Row],[Référence]],MON_MSG!A:I,8,FALSE))),"",VLOOKUP(Tableau161920[[#This Row],[Référence]],MON_MSG!A:I,8,FALSE)) | M12: =IF(OR(ISNA(VLOOKUP(Tableau161920[[#This Row],[Référence]],MON_MSG!A:J,9,FALSE)),ISBLANK(VLOOKUP(Tableau161920[[#This Row],[Référence]],MON_MSG!A:J,9,FALSE))),"",VLOOKUP(Tableau161920[[#This Row],[Référence]],MON_MSG!A:J,9,FALSE)) | N12: =IF(VLOOKUP($A12,DICO_Complet!A:R,12,FALSE)=0,"",VLOOKUP($A12,DICO_Complet!A:R,12,FALSE)) | O12: =IF(VLOOKUP($A12,DICO_Complet!A:R,13,FALSE)=0,"",VLOOKUP($A12,DICO_Complet!A:R,13,FALSE)) | P12: =IF(VLOOKUP($A12,DICO_Complet!A:R,14,FALSE)=0,"",VLOOKUP($A12,DICO_Complet!A:R,14,FALSE)) | Q12: =IF(VLOOKUP($A12,DICO_Complet!A:R,15,FALSE)=0,"",VLOOKUP($A12,DICO_Complet!A:R,15,FALSE)) | R12: =IF(VLOOKUP($A12,DICO_Complet!A:R,16,FALSE)=0,"",VLOOKUP($A12,DICO_Complet!A:R,16,FALSE)) | S12: =IF(VLOOKUP($A12,DICO_Complet!A:R,17,FALSE)=0,"",VLOOKUP($A12,DICO_Complet!A:R,17,FALSE)) | T12: =IF(VLOOKUP($A12,DICO_Complet!A:R,18,FALSE)=0,"",VLOOKUP($A12,DICO_Complet!A:R,18,FALSE))
A13: 250723172700 | B13: =IF(ISNA(VLOOKUP(Tableau161920[[#This Row],[Référence]],MON_MSG!A:B,2,FALSE)),"N",IF($I13="Obsolete","N","O")) -> O | C13: =VLOOKUP($A13,DICO_Complet!A:R,3,FALSE) -> AuditTrail | D13: =VLOOKUP($A13,DICO_Complet!A:R,4,FALSE) -> auditTrail | E13: =VLOOKUP($A13,DICO_Complet!A:R,5,FALSE) -> auditPhoneNumber | F13: =VLOOKUP($A13,DICO_Complet!A:R,6,FALSE) -> PhoneNumberType | G13: =VLOOKUP($A13,DICO_Complet!A:R,7,FALSE) -> DSP | H13: =VLOOKUP($A13,DICO_Complet!A:R,8,FALSE) -> 0 | I13: =IF(VLOOKUP($A13,DICO_Complet!A:R,9,FALSE)<>0,VLOOKUP($A13,DICO_Complet!A:R,9,FALSE),"") | J13: =VLOOKUP($A13,DICO_Complet!A:R,10,FALSE) -> Phone number with usage and security tag | K13: =IF(OR(ISNA(VLOOKUP(Tableau161920[[#This Row],[Référence]],MON_MSG!A:H,7,FALSE)),ISBLANK(VLOOKUP(Tableau161920[[#This Row],[Référence]],MON_MSG!A:H,7,FALSE))),"",VLOOKUP(Tableau161920[[#This Row],[Référence]],MON_MSG!A:H,7,FALSE)) | L13: =IF(OR(ISNA(VLOOKUP(Tableau161920[[#This Row],[Référence]],MON_MSG!A:I,8,FALSE)),ISBLANK(VLOOKUP(Tableau161920[[#This Row],[Référence]],MON_MSG!A:I,8,FALSE))),"",VLOOKUP(Tableau161920[[#This Row],[Référence]],MON_MSG!A:I,8,FALSE)) | M13: =IF(OR(ISNA(VLOOKUP(Tableau161920[[#This Row],[Référence]],MON_MSG!A:J,9,FALSE)),ISBLANK(VLOOKUP(Tableau161920[[#This Row],[Référence]],MON_MSG!A:J,9,FALSE))),"",VLOOKUP(Tableau161920[[#This Row],[Référence]],MON_MSG!A:J,9,FALSE)) | N13: =IF(VLOOKUP($A13,DICO_Complet!A:R,12,FALSE)=0,"",VLOOKUP($A13,DICO_Complet!A:R,12,FALSE)) | O13: =IF(VLOOKUP($A13,DICO_Complet!A:R,13,FALSE)=0,"",VLOOKUP($A13,DICO_Complet!A:R,13,FALSE)) | P13: =IF(VLOOKUP($A13,DICO_Complet!A:R,14,FALSE)=0,"",VLOOKUP($A13,DICO_Complet!A:R,14,FALSE)) | Q13: =IF(VLOOKUP($A13,DICO_Complet!A:R,15,FALSE)=0,"",VLOOKUP($A13,DICO_Complet!A:R,15,FALSE)) | R13: =IF(VLOOKUP($A13,DICO_Complet!A:R,16,FALSE)=0,"",VLOOKUP($A13,DICO_Complet!A:R,16,FALSE)) | S13: =IF(VLOOKUP($A13,DICO_Complet!A:R,17,FALSE)=0,"",VLOOKUP($A13,DICO_Complet!A:R,17,FALSE)) | T13: =IF(VLOOKUP($A13,DICO_Complet!A:R,18,FALSE)=0,"",VLOOKUP($A13,DICO_Complet!A:R,18,FALSE))
A14: 250717102602 | B14: =IF(ISNA(VLOOKUP(Tableau161920[[#This Row],[Référence]],MON_MSG!A:B,2,FALSE)),"N",IF($I14="Obsolete","N","O")) -> O | C14: =VLOOKUP($A14,DICO_Complet!A:R,3,FALSE) -> AuditTrail | D14: =VLOOKUP($A14,DICO_Complet!A:R,4,FALSE) -> auditTrail | E14: =VLOOKUP($A14,DICO_Complet!A:R,5,FALSE) -> auditTrailId | F14: =VLOOKUP($A14,DICO_Complet!A:R,6,FALSE) -> Max255AlphaNumericText | G14: =VLOOKUP($A14,DICO_Complet!A:R,7,FALSE) -> DNS | H14: =VLOOKUP($A14,DICO_Complet!A:R,8,FALSE) -> 0 | I14: =IF(VLOOKUP($A14,DICO_Complet!A:R,9,FALSE)<>0,VLOOKUP($A14,DICO_Complet!A:R,9,FALSE),"") | J14: =VLOOKUP($A14,DICO_Complet!A:R,10,FALSE) -> Audit trail reference | K14: =IF(OR(ISNA(VLOOKUP(Tableau161920[[#This Row],[Référence]],MON_MSG!A:H,7,FALSE)),ISBLANK(VLOOKUP(Tableau161920[[#This Row],[Référence]],MON_MSG!A:H,7,FALSE))),"",VLOOKUP(Tableau161920[[#This Row],[Référence]],MON_MSG!A:H,7,FALSE)) | L14: =IF(OR(ISNA(VLOOKUP(Tableau161920[[#This Row],[Référence]],MON_MSG!A:I,8,FALSE)),ISBLANK(VLOOKUP(Tableau161920[[#This Row],[Référence]],MON_MSG!A:I,8,FALSE))),"",VLOOKUP(Tableau161920[[#This Row],[Référence]],MON_MSG!A:I,8,FALSE)) | M14: =IF(OR(ISNA(VLOOKUP(Tableau161920[[#This Row],[Référence]],MON_MSG!A:J,9,FALSE)),ISBLANK(VLOOKUP(Tableau161920[[#This Row],[Référence]],MON_MSG!A:J,9,FALSE))),"",VLOOKUP(Tableau161920[[#This Row],[Référence]],MON_MSG!A:J,9,FALSE)) | N14: =IF(VLOOKUP($A14,DICO_Complet!A:R,12,FALSE)=0,"",VLOOKUP($A14,DICO_Complet!A:R,12,FALSE)) | O14: =IF(VLOOKUP($A14,DICO_Complet!A:R,13,FALSE)=0,"",VLOOKUP($A14,DICO_Complet!A:R,13,FALSE)) | P14: =IF(VLOOKUP($A14,DICO_Complet!A:R,14,FALSE)=0,"",VLOOKUP($A14,DICO_Complet!A:R,14,FALSE)) | Q14: =IF(VLOOKUP($A14,DICO_Complet!A:R,15,FALSE)=0,"",VLOOKUP($A14,DICO_Complet!A:R,15,FALSE)) | R14: =IF(VLOOKUP($A14,DICO_Complet!A:R,16,FALSE)=0,"",VLOOKUP($A14,DICO_Complet!A:R,16,FALSE)) | S14: =IF(VLOOKUP($A14,DICO_Complet!A:R,17,FALSE)=0,"",VLOOKUP($A14,DICO_Complet!A:R,17,FALSE)) | T14: =IF(VLOOKUP($A14,DICO_Complet!A:R,18,FALSE)=0,"",VLOOKUP($A14,DICO_Complet!A:R,18,FALSE))
... A638: 260422142700 | B638: =IF(ISNA(VLOOKUP(Tableau161920[[#This Row],[Référence]],MON_MSG!A:B,2,FALSE)),"N",IF($I638="Obsolete","N","O")) -> O | C638: =VLOOKUP($A638,DICO_Complet!A:R,3,FALSE) -> Edition | D638: =VLOOKUP($A638,DICO_Complet!A:R,4,FALSE) -> editionParameters | E638: =VLOOKUP($A638,DICO_Complet!A:R,5,FALSE) -> requestDateTime | F638: =VLOOKUP($A638,DICO_Complet!A:R,6,FALSE) -> ISODateTime | G638: =VLOOKUP($A638,DICO_Complet!A:R,7,FALSE) -> DNS | H638: =VLOOKUP($A638,DICO_Complet!A:R,8,FALSE) -> 0 | I638: =IF(VLOOKUP($A638,DICO_Complet!A:R,9,FALSE)<>0,VLOOKUP($A638,DICO_Complet!A:R,9,FALSE),"") | J638: =VLOOKUP($A638,DICO_Complet!A:R,10,FALSE) -> Letter request date time | K638: =IF(OR(ISNA(VLOOKUP(Tableau161920[[#This Row],[Référence]],MON_MSG!A:H,7,FALSE)),ISBLANK(VLOOKUP(Tableau161920[[#This Row],[Référence]],MON_MSG!A:H,7,FALSE))),"",VLOOKUP(Tableau161920[[#This Row],[Référence]],MON_MSG!A:H,7,FALSE)) | L638: =IF(OR(ISNA(VLOOKUP(Tableau161920[[#This Row],[Référence]],MON_MSG!A:I,8,FALSE)),ISBLANK(VLOOKUP(Tableau161920[[#This Row],[Référence]],MON_MSG!A:I,8,FALSE))),"",VLOOKUP(Tableau161920[[#This Row],[Référence]],MON_MSG!A:I,8,FALSE)) | M638: =IF(OR(ISNA(VLOOKUP(Tableau161920[[#This Row],[Référence]],MON_MSG!A:J,9,FALSE)),ISBLANK(VLOOKUP(Tableau161920[[#This Row],[Référence]],MON_MSG!A:J,9,FALSE))),"",VLOOKUP(Tableau161920[[#This Row],[Référence]],MON_MSG!A:J,9,FALSE)) | N638: =IF(VLOOKUP($A638,DICO_Complet!A:R,12,FALSE)=0,"",VLOOKUP($A638,DICO_Complet!A:R,12,FALSE)) | O638: =IF(VLOOKUP($A638,DICO_Complet!A:R,13,FALSE)=0,"",VLOOKUP($A638,DICO_Complet!A:R,13,FALSE)) | P638: =IF(VLOOKUP($A638,DICO_Complet!A:R,14,FALSE)=0,"",VLOOKUP($A638,DICO_Complet!A:R,14,FALSE)) | Q638: =IF(VLOOKUP($A638,DICO_Complet!A:R,15,FALSE)=0,"",VLOOKUP($A638,DICO_Complet!A:R,15,FALSE)) | R638: =IF(VLOOKUP($A638,DICO_Complet!A:R,16,FALSE)=0,"",VLOOKUP($A638,DICO_Complet!A:R,16,FALSE)) | S638: =IF(VLOOKUP($A638,DICO_Complet!A:R,17,FALSE)=0,"",VLOOKUP($A638,DICO_Complet!A:R,17,FALSE)) | T638: =IF(VLOOKUP($A638,DICO_Complet!A:R,18,FALSE)=0,"",VLOOKUP($A638,DICO_Complet!A:R,18,FALSE))
A639: 260526110000 | B639: =IF(ISNA(VLOOKUP(Tableau161920[[#This Row],[Référence]],MON_MSG!A:B,2,FALSE)),"N",IF($I639="Obsolete","N","O")) -> O | C639: =VLOOKUP($A639,DICO_Complet!A:R,3,FALSE) -> Edition | D639: =VLOOKUP($A639,DICO_Complet!A:R,4,FALSE) -> editionParameters | E639: =VLOOKUP($A639,DICO_Complet!A:R,5,FALSE) -> requestDateTime | F639: =VLOOKUP($A639,DICO_Complet!A:R,6,FALSE) -> ISODateTime | G639: =VLOOKUP($A639,DICO_Complet!A:R,7,FALSE) -> DNS | H639: =VLOOKUP($A639,DICO_Complet!A:R,8,FALSE) -> 0 | I639: =IF(VLOOKUP($A639,DICO_Complet!A:R,9,FALSE)<>0,VLOOKUP($A639,DICO_Complet!A:R,9,FALSE),"") | J639: =VLOOKUP($A639,DICO_Complet!A:R,10,FALSE) -> Edition request date time | N639: =IF(VLOOKUP($A639,DICO_Complet!A:R,12,FALSE)=0,"",VLOOKUP($A639,DICO_Complet!A:R,12,FALSE)) | O639: =IF(VLOOKUP($A639,DICO_Complet!A:R,13,FALSE)=0,"",VLOOKUP($A639,DICO_Complet!A:R,13,FALSE)) | P639: =IF(VLOOKUP($A639,DICO_Complet!A:R,14,FALSE)=0,"",VLOOKUP($A639,DICO_Complet!A:R,14,FALSE)) | Q639: =IF(VLOOKUP($A639,DICO_Complet!A:R,15,FALSE)=0,"",VLOOKUP($A639,DICO_Complet!A:R,15,FALSE)) | R639: =IF(VLOOKUP($A639,DICO_Complet!A:R,16,FALSE)=0,"",VLOOKUP($A639,DICO_Complet!A:R,16,FALSE)) | S639: =IF(VLOOKUP($A639,DICO_Complet!A:R,17,FALSE)=0,"",VLOOKUP($A639,DICO_Complet!A:R,17,FALSE)) | T639: =IF(VLOOKUP($A639,DICO_Complet!A:R,18,FALSE)=0,"",VLOOKUP($A639,DICO_Complet!A:R,18,FALSE))
A640: 260422140700 | B640: =IF(ISNA(VLOOKUP(Tableau161920[[#This Row],[Référence]],MON_MSG!A:B,2,FALSE)),"N",IF($I640="Obsolete","N","O")) -> O | C640: =VLOOKUP($A640,DICO_Complet!A:R,3,FALSE) -> Edition | D640: =VLOOKUP($A640,DICO_Complet!A:R,4,FALSE) -> editionParameters | E640: =VLOOKUP($A640,DICO_Complet!A:R,5,FALSE) -> requestedElement | F640: =VLOOKUP($A640,DICO_Complet!A:R,6,FALSE) -> RequestedElementCodeset | G640: =VLOOKUP($A640,DICO_Complet!A:R,7,FALSE) -> DNS | H640: =VLOOKUP($A640,DICO_Complet!A:R,8,FALSE) -> 0 | I640: =IF(VLOOKUP($A640,DICO_Complet!A:R,9,FALSE)<>0,VLOOKUP($A640,DICO_Complet!A:R,9,FALSE),"") | J640: =VLOOKUP($A640,DICO_Complet!A:R,10,FALSE) -> Requested element | K640: =IF(OR(ISNA(VLOOKUP(Tableau161920[[#This Row],[Référence]],MON_MSG!A:H,7,FALSE)),ISBLANK(VLOOKUP(Tableau161920[[#This Row],[Référence]],MON_MSG!A:H,7,FALSE))),"",VLOOKUP(Tableau161920[[#This Row],[Référence]],MON_MSG!A:H,7,FALSE)) | L640: =IF(OR(ISNA(VLOOKUP(Tableau161920[[#This Row],[Référence]],MON_MSG!A:I,8,FALSE)),ISBLANK(VLOOKUP(Tableau161920[[#This Row],[Référence]],MON_MSG!A:I,8,FALSE))),"",VLOOKUP(Tableau161920[[#This Row],[Référence]],MON_MSG!A:I,8,FALSE)) | M640: =IF(OR(ISNA(VLOOKUP(Tableau161920[[#This Row],[Référence]],MON_MSG!A:J,9,FALSE)),ISBLANK(VLOOKUP(Tableau161920[[#This Row],[Référence]],MON_MSG!A:J,9,FALSE))),"",VLOOKUP(Tableau161920[[#This Row],[Référence]],MON_MSG!A:J,9,FALSE)) | N640: =IF(VLOOKUP($A640,DICO_Complet!A:R,12,FALSE)=0,"",VLOOKUP($A640,DICO_Complet!A:R,12,FALSE)) | O640: =IF(VLOOKUP($A640,DICO_Complet!A:R,13,FALSE)=0,"",VLOOKUP($A640,DICO_Complet!A:R,13,FALSE)) | P640: =IF(VLOOKUP($A640,DICO_Complet!A:R,14,FALSE)=0,"",VLOOKUP($A640,DICO_Complet!A:R,14,FALSE)) | Q640: =IF(VLOOKUP($A640,DICO_Complet!A:R,15,FALSE)=0,"",VLOOKUP($A640,DICO_Complet!A:R,15,FALSE)) | R640: =IF(VLOOKUP($A640,DICO_Complet!A:R,16,FALSE)=0,"",VLOOKUP($A640,DICO_Complet!A:R,16,FALSE)) | S640: =IF(VLOOKUP($A640,DICO_Complet!A:R,17,FALSE)=0,"",VLOOKUP($A640,DICO_Complet!A:R,17,FALSE)) | T640: =IF(VLOOKUP($A640,DICO_Complet!A:R,18,FALSE)=0,"",VLOOKUP($A640,DICO_Complet!A:R,18,FALSE))
A641: 250528103700 | B641: =IF(ISNA(VLOOKUP(Tableau161920[[#This Row],[Référence]],MON_MSG!A:B,2,FALSE)),"N",IF($I641="Obsolete","N","O")) -> O | C641: =VLOOKUP($A641,DICO_Complet!A:R,3,FALSE) -> Edition | D641: =VLOOKUP($A641,DICO_Complet!A:R,4,FALSE) -> editionParameters | E641: =VLOOKUP($A641,DICO_Complet!A:R,5,FALSE) -> responseTime | F641: =VLOOKUP($A641,DICO_Complet!A:R,6,FALSE) -> Max250Text | G641: =VLOOKUP($A641,DICO_Complet!A:R,7,FALSE) -> DNS | H641: =VLOOKUP($A641,DICO_Complet!A:R,8,FALSE) -> 0 | I641: =IF(VLOOKUP($A641,DICO_Complet!A:R,9,FALSE)<>0,VLOOKUP($A641,DICO_Complet!A:R,9,FALSE),"") | J641: =VLOOKUP($A641,DICO_Complet!A:R,10,FALSE) -> Response time | K641: =IF(OR(ISNA(VLOOKUP(Tableau161920[[#This Row],[Référence]],MON_MSG!A:H,7,FALSE)),ISBLANK(VLOOKUP(Tableau161920[[#This Row],[Référence]],MON_MSG!A:H,7,FALSE))),"",VLOOKUP(Tableau161920[[#This Row],[Référence]],MON_MSG!A:H,7,FALSE)) | L641: =IF(OR(ISNA(VLOOKUP(Tableau161920[[#This Row],[Référence]],MON_MSG!A:I,8,FALSE)),ISBLANK(VLOOKUP(Tableau161920[[#This Row],[Référence]],MON_MSG!A:I,8,FALSE))),"",VLOOKUP(Tableau161920[[#This Row],[Référence]],MON_MSG!A:I,8,FALSE)) | M641: =IF(OR(ISNA(VLOOKUP(Tableau161920[[#This Row],[Référence]],MON_MSG!A:J,9,FALSE)),ISBLANK(VLOOKUP(Tableau161920[[#This Row],[Référence]],MON_MSG!A:J,9,FALSE))),"",VLOOKUP(Tableau161920[[#This Row],[Référence]],MON_MSG!A:J,9,FALSE)) | N641: =IF(VLOOKUP($A641,DICO_Complet!A:R,12,FALSE)=0,"",VLOOKUP($A641,DICO_Complet!A:R,12,FALSE)) | O641: =IF(VLOOKUP($A641,DICO_Complet!A:R,13,FALSE)=0,"",VLOOKUP($A641,DICO_Complet!A:R,13,FALSE)) | P641: =IF(VLOOKUP($A641,DICO_Complet!A:R,14,FALSE)=0,"",VLOOKUP($A641,DICO_Complet!A:R,14,FALSE)) | Q641: =IF(VLOOKUP($A641,DICO_Complet!A:R,15,FALSE)=0,"",VLOOKUP($A641,DICO_Complet!A:R,15,FALSE)) | R641: =IF(VLOOKUP($A641,DICO_Complet!A:R,16,FALSE)=0,"",VLOOKUP($A641,DICO_Complet!A:R,16,FALSE)) | S641: =IF(VLOOKUP($A641,DICO_Complet!A:R,17,FALSE)=0,"",VLOOKUP($A641,DICO_Complet!A:R,17,FALSE)) | T641: =IF(VLOOKUP($A641,DICO_Complet!A:R,18,FALSE)=0,"",VLOOKUP($A641,DICO_Complet!A:R,18,FALSE))
A642: 250528102450 | B642: =IF(ISNA(VLOOKUP(Tableau161920[[#This Row],[Référence]],MON_MSG!A:B,2,FALSE)),"N",IF($I642="Obsolete","N","O")) -> O | C642: =VLOOKUP($A642,DICO_Complet!A:R,3,FALSE) -> Edition | D642: =VLOOKUP($A642,DICO_Complet!A:R,4,FALSE) -> editionParameters | E642: =VLOOKUP($A642,DICO_Complet!A:R,5,FALSE) -> serviceName | F642: =VLOOKUP($A642,DICO_Complet!A:R,6,FALSE) -> Max255Text | G642: =VLOOKUP($A642,DICO_Complet!A:R,7,FALSE) -> DNS | H642: =VLOOKUP($A642,DICO_Complet!A:R,8,FALSE) -> 0 | I642: =IF(VLOOKUP($A642,DICO_Complet!A:R,9,FALSE)<>0,VLOOKUP($A642,DICO_Complet!A:R,9,FALSE),"") | J642: =VLOOKUP($A642,DICO_Complet!A:R,10,FALSE) -> Service name | K642: =IF(OR(ISNA(VLOOKUP(Tableau161920[[#This Row],[Référence]],MON_MSG!A:H,7,FALSE)),ISBLANK(VLOOKUP(Tableau161920[[#This Row],[Référence]],MON_MSG!A:H,7,FALSE))),"",VLOOKUP(Tableau161920[[#This Row],[Référence]],MON_MSG!A:H,7,FALSE)) | L642: =IF(OR(ISNA(VLOOKUP(Tableau161920[[#This Row],[Référence]],MON_MSG!A:I,8,FALSE)),ISBLANK(VLOOKUP(Tableau161920[[#This Row],[Référence]],MON_MSG!A:I,8,FALSE))),"",VLOOKUP(Tableau161920[[#This Row],[Référence]],MON_MSG!A:I,8,FALSE)) | M642: =IF(OR(ISNA(VLOOKUP(Tableau161920[[#This Row],[Référence]],MON_MSG!A:J,9,FALSE)),ISBLANK(VLOOKUP(Tableau161920[[#This Row],[Référence]],MON_MSG!A:J,9,FALSE))),"",VLOOKUP(Tableau161920[[#This Row],[Référence]],MON_MSG!A:J,9,FALSE)) | N642: =IF(VLOOKUP($A642,DICO_Complet!A:R,12,FALSE)=0,"",VLOOKUP($A642,DICO_Complet!A:R,12,FALSE)) | O642: =IF(VLOOKUP($A642,DICO_Complet!A:R,13,FALSE)=0,"",VLOOKUP($A642,DICO_Complet!A:R,13,FALSE)) | P642: =IF(VLOOKUP($A642,DICO_Complet!A:R,14,FALSE)=0,"",VLOOKUP($A642,DICO_Complet!A:R,14,FALSE)) | Q642: =IF(VLOOKUP($A642,DICO_Complet!A:R,15,FALSE)=0,"",VLOOKUP($A642,DICO_Complet!A:R,15,FALSE)) | R642: =IF(VLOOKUP($A642,DICO_Complet!A:R,16,FALSE)=0,"",VLOOKUP($A642,DICO_Complet!A:R,16,FALSE)) | S642: =IF(VLOOKUP($A642,DICO_Complet!A:R,17,FALSE)=0,"",VLOOKUP($A642,DICO_Complet!A:R,17,FALSE)) | T642: =IF(VLOOKUP($A642,DICO_Complet!A:R,18,FALSE)=0,"",VLOOKUP($A642,DICO_Complet!A:R,18,FALSE))
A643: 260422140300 | B643: =IF(ISNA(VLOOKUP(Tableau161920[[#This Row],[Référence]],MON_MSG!A:B,2,FALSE)),"N",IF($I643="Obsolete","N","O")) -> O | C643: =VLOOKUP($A643,DICO_Complet!A:R,3,FALSE) -> Edition | D643: =VLOOKUP($A643,DICO_Complet!A:R,4,FALSE) -> editionParameters | E643: =VLOOKUP($A643,DICO_Complet!A:R,5,FALSE) -> serviceProviderBankContact | F643: =VLOOKUP($A643,DICO_Complet!A:R,6,FALSE) -> ContactType | G643: =VLOOKUP($A643,DICO_Complet!A:R,7,FALSE) -> DNS | H643: =VLOOKUP($A643,DICO_Complet!A:R,8,FALSE) -> 0 | I643: =IF(VLOOKUP($A643,DICO_Complet!A:R,9,FALSE)<>0,VLOOKUP($A643,DICO_Complet!A:R,9,FALSE),"") | J643: =VLOOKUP($A643,DICO_Complet!A:R,10,FALSE) -> Contact information of the bank service provider | K643: =IF(OR(ISNA(VLOOKUP(Tableau161920[[#This Row],[Référence]],MON_MSG!A:H,7,FALSE)),ISBLANK(VLOOKUP(Tableau161920[[#This Row],[Référence]],MON_MSG!A:H,7,FALSE))),"",VLOOKUP(Tableau161920[[#This Row],[Référence]],MON_MSG!A:H,7,FALSE)) | L643: =IF(OR(ISNA(VLOOKUP(Tableau161920[[#This Row],[Référence]],MON_MSG!A:I,8,FALSE)),ISBLANK(VLOOKUP(Tableau161920[[#This Row],[Référence]],MON_MSG!A:I,8,FALSE))),"",VLOOKUP(Tableau161920[[#This Row],[Référence]],MON_MSG!A:I,8,FALSE)) | M643: =IF(OR(ISNA(VLOOKUP(Tableau161920[[#This Row],[Référence]],MON_MSG!A:J,9,FALSE)),ISBLANK(VLOOKUP(Tableau161920[[#This Row],[Référence]],MON_MSG!A:J,9,FALSE))),"",VLOOKUP(Tableau161920[[#This Row],[Référence]],MON_MSG!A:J,9,FALSE)) | N643: =IF(VLOOKUP($A643,DICO_Complet!A:R,12,FALSE)=0,"",VLOOKUP($A643,DICO_Complet!A:R,12,FALSE)) | O643: =IF(VLOOKUP($A643,DICO_Complet!A:R,13,FALSE)=0,"",VLOOKUP($A643,DICO_Complet!A:R,13,FALSE)) | P643: =IF(VLOOKUP($A643,DICO_Complet!A:R,14,FALSE)=0,"",VLOOKUP($A643,DICO_Complet!A:R,14,FALSE)) | Q643: =IF(VLOOKUP($A643,DICO_Complet!A:R,15,FALSE)=0,"",VLOOKUP($A643,DICO_Complet!A:R,15,FALSE)) | R643: =IF(VLOOKUP($A643,DICO_Complet!A:R,16,FALSE)=0,"",VLOOKUP($A643,DICO_Complet!A:R,16,FALSE)) | S643: =IF(VLOOKUP($A643,DICO_Complet!A:R,17,FALSE)=0,"",VLOOKUP($A643,DICO_Complet!A:R,17,FALSE)) | T643: =IF(VLOOKUP($A643,DICO_Complet!A:R,18,FALSE)=0,"",VLOOKUP($A643,DICO_Complet!A:R,18,FALSE))
A644: 260526131700 | B644: =IF(ISNA(VLOOKUP(Tableau161920[[#This Row],[Référence]],MON_MSG!A:B,2,FALSE)),"N",IF($I644="Obsolete","N","O")) -> O | C644: =VLOOKUP($A644,DICO_Complet!A:R,3,FALSE) -> Edition | D644: =VLOOKUP($A644,DICO_Complet!A:R,4,FALSE) -> editionParameters | E644: =VLOOKUP($A644,DICO_Complet!A:R,5,FALSE) -> variant | F644: =VLOOKUP($A644,DICO_Complet!A:R,6,FALSE) -> Max2Text | G644: =VLOOKUP($A644,DICO_Complet!A:R,7,FALSE) -> DNS | H644: =VLOOKUP($A644,DICO_Complet!A:R,8,FALSE) -> 0 | I644: =IF(VLOOKUP($A644,DICO_Complet!A:R,9,FALSE)<>0,VLOOKUP($A644,DICO_Complet!A:R,9,FALSE),"") | J644: =VLOOKUP($A644,DICO_Complet!A:R,10,FALSE) -> Defines the letter variant to be generated and allows adapting the layout and document subject | K644: =IF(OR(ISNA(VLOOKUP(Tableau161920[[#This Row],[Référence]],MON_MSG!A:H,7,FALSE)),ISBLANK(VLOOKUP(Tableau161920[[#This Row],[Référence]],MON_MSG!A:H,7,FALSE))),"",VLOOKUP(Tableau161920[[#This Row],[Référence]],MON_MSG!A:H,7,FALSE)) | L644: =IF(OR(ISNA(VLOOKUP(Tableau161920[[#This Row],[Référence]],MON_MSG!A:I,8,FALSE)),ISBLANK(VLOOKUP(Tableau161920[[#This Row],[Référence]],MON_MSG!A:I,8,FALSE))),"",VLOOKUP(Tableau161920[[#This Row],[Référence]],MON_MSG!A:I,8,FALSE)) | M644: =IF(OR(ISNA(VLOOKUP(Tableau161920[[#This Row],[Référence]],MON_MSG!A:J,9,FALSE)),ISBLANK(VLOOKUP(Tableau161920[[#This Row],[Référence]],MON_MSG!A:J,9,FALSE))),"",VLOOKUP(Tableau161920[[#This Row],[Référence]],MON_MSG!A:J,9,FALSE)) | N644: =IF(VLOOKUP($A644,DICO_Complet!A:R,12,FALSE)=0,"",VLOOKUP($A644,DICO_Complet!A:R,12,FALSE)) | O644: =IF(VLOOKUP($A644,DICO_Complet!A:R,13,FALSE)=0,"",VLOOKUP($A644,DICO_Complet!A:R,13,FALSE)) | P644: =IF(VLOOKUP($A644,DICO_Complet!A:R,14,FALSE)=0,"",VLOOKUP($A644,DICO_Complet!A:R,14,FALSE)) | Q644: =IF(VLOOKUP($A644,DICO_Complet!A:R,15,FALSE)=0,"",VLOOKUP($A644,DICO_Complet!A:R,15,FALSE)) | R644: =IF(VLOOKUP($A644,DICO_Complet!A:R,16,FALSE)=0,"",VLOOKUP($A644,DICO_Complet!A:R,16,FALSE)) | S644: =IF(VLOOKUP($A644,DICO_Complet!A:R,17,FALSE)=0,"",VLOOKUP($A644,DICO_Complet!A:R,17,FALSE)) | T644: =IF(VLOOKUP($A644,DICO_Complet!A:R,18,FALSE)=0,"",VLOOKUP($A644,DICO_Complet!A:R,18,FALSE))
A645: 260226092800 | B645: =IF(ISNA(VLOOKUP(Tableau161920[[#This Row],[Référence]],MON_MSG!A:B,2,FALSE)),"N",IF($I645="Obsolete","N","O")) -> O | C645: =VLOOKUP($A645,DICO_Complet!A:R,3,FALSE) -> Environment | D645: =VLOOKUP($A645,DICO_Complet!A:R,4,FALSE) -> accountOwner | E645: =VLOOKUP($A645,DICO_Complet!A:R,5,FALSE) -> birthCountryCode | F645: =VLOOKUP($A645,DICO_Complet!A:R,6,FALSE) -> ISO3NumericCountryCode | G645: =VLOOKUP($A645,DICO_Complet!A:R,7,FALSE) -> DNS | H645: =VLOOKUP($A645,DICO_Complet!A:R,8,FALSE) -> 0 | I645: =IF(VLOOKUP($A645,DICO_Complet!A:R,9,FALSE)<>0,VLOOKUP($A645,DICO_Complet!A:R,9,FALSE),"") | J645: =VLOOKUP($A645,DICO_Complet!A:R,10,FALSE) -> Account owner birth country code | K645: =IF(OR(ISNA(VLOOKUP(Tableau161920[[#This Row],[Référence]],MON_MSG!A:H,7,FALSE)),ISBLANK(VLOOKUP(Tableau161920[[#This Row],[Référence]],MON_MSG!A:H,7,FALSE))),"",VLOOKUP(Tableau161920[[#This Row],[Référence]],MON_MSG!A:H,7,FALSE)) | L645: =IF(OR(ISNA(VLOOKUP(Tableau161920[[#This Row],[Référence]],MON_MSG!A:I,8,FALSE)),ISBLANK(VLOOKUP(Tableau161920[[#This Row],[Référence]],MON_MSG!A:I,8,FALSE))),"",VLOOKUP(Tableau161920[[#This Row],[Référence]],MON_MSG!A:I,8,FALSE)) | M645: =IF(OR(ISNA(VLOOKUP(Tableau161920[[#This Row],[Référence]],MON_MSG!A:J,9,FALSE)),ISBLANK(VLOOKUP(Tableau161920[[#This Row],[Référence]],MON_MSG!A:J,9,FALSE))),"",VLOOKUP(Tableau161920[[#This Row],[Référence]],MON_MSG!A:J,9,FALSE)) | N645: =IF(VLOOKUP($A645,DICO_Complet!A:R,12,FALSE)=0,"",VLOOKUP($A645,DICO_Complet!A:R,12,FALSE)) | O645: =IF(VLOOKUP($A645,DICO_Complet!A:R,13,FALSE)=0,"",VLOOKUP($A645,DICO_Complet!A:R,13,FALSE)) -> 118-4013 | P645: =IF(VLOOKUP($A645,DICO_Complet!A:R,14,FALSE)=0,"",VLOOKUP($A645,DICO_Complet!A:R,14,FALSE)) | Q645: =IF(VLOOKUP($A645,DICO_Complet!A:R,15,FALSE)=0,"",VLOOKUP($A645,DICO_Complet!A:R,15,FALSE)) | R645: =IF(VLOOKUP($A645,DICO_Complet!A:R,16,FALSE)=0,"",VLOOKUP($A645,DICO_Complet!A:R,16,FALSE)) -> 56.05.90 | S645: =IF(VLOOKUP($A645,DICO_Complet!A:R,17,FALSE)=0,"",VLOOKUP($A645,DICO_Complet!A:R,17,FALSE)) | T645: =IF(VLOOKUP($A645,DICO_Complet!A:R,18,FALSE)=0,"",VLOOKUP($A645,DICO_Complet!A:R,18,FALSE))
A646: 260226093400 | B646: =IF(ISNA(VLOOKUP(Tableau161920[[#This Row],[Référence]],MON_MSG!A:B,2,FALSE)),"N",IF($I646="Obsolete","N","O")) -> O | C646: =VLOOKUP($A646,DICO_Complet!A:R,3,FALSE) -> Environment | D646: =VLOOKUP($A646,DICO_Complet!A:R,4,FALSE) -> accountOwner | E646: =VLOOKUP($A646,DICO_Complet!A:R,5,FALSE) -> birthDate | F646: =VLOOKUP($A646,DICO_Complet!A:R,6,FALSE) -> ISODate | G646: =VLOOKUP($A646,DICO_Complet!A:R,7,FALSE) -> DSP | H646: =VLOOKUP($A646,DICO_Complet!A:R,8,FALSE) -> 0 | I646: =IF(VLOOKUP($A646,DICO_Complet!A:R,9,FALSE)<>0,VLOOKUP($A646,DICO_Complet!A:R,9,FALSE),"") | J646: =VLOOKUP($A646,DICO_Complet!A:R,10,FALSE) -> Date of birth of account owner | K646: =IF(OR(ISNA(VLOOKUP(Tableau161920[[#This Row],[Référence]],MON_MSG!A:H,7,FALSE)),ISBLANK(VLOOKUP(Tableau161920[[#This Row],[Référence]],MON_MSG!A:H,7,FALSE))),"",VLOOKUP(Tableau161920[[#This Row],[Référence]],MON_MSG!A:H,7,FALSE)) | L646: =IF(OR(ISNA(VLOOKUP(Tableau161920[[#This Row],[Référence]],MON_MSG!A:I,8,FALSE)),ISBLANK(VLOOKUP(Tableau161920[[#This Row],[Référence]],MON_MSG!A:I,8,FALSE))),"",VLOOKUP(Tableau161920[[#This Row],[Référence]],MON_MSG!A:I,8,FALSE)) | M646: =IF(OR(ISNA(VLOOKUP(Tableau161920[[#This Row],[Référence]],MON_MSG!A:J,9,FALSE)),ISBLANK(VLOOKUP(Tableau161920[[#This Row],[Référence]],MON_MSG!A:J,9,FALSE))),"",VLOOKUP(Tableau161920[[#This Row],[Référence]],MON_MSG!A:J,9,FALSE)) | N646: =IF(VLOOKUP($A646,DICO_Complet!A:R,12,FALSE)=0,"",VLOOKUP($A646,DICO_Complet!A:R,12,FALSE)) | O646: =IF(VLOOKUP($A646,DICO_Complet!A:R,13,FALSE)=0,"",VLOOKUP($A646,DICO_Complet!A:R,13,FALSE)) -> 118-4015 | P646: =IF(VLOOKUP($A646,DICO_Complet!A:R,14,FALSE)=0,"",VLOOKUP($A646,DICO_Complet!A:R,14,FALSE)) | Q646: =IF(VLOOKUP($A646,DICO_Complet!A:R,15,FALSE)=0,"",VLOOKUP($A646,DICO_Complet!A:R,15,FALSE)) | R646: =IF(VLOOKUP($A646,DICO_Complet!A:R,16,FALSE)=0,"",VLOOKUP($A646,DICO_Complet!A:R,16,FALSE)) -> 56.05.92 | S646: =IF(VLOOKUP($A646,DICO_Complet!A:R,17,FALSE)=0,"",VLOOKUP($A646,DICO_Complet!A:R,17,FALSE)) | T646: =IF(VLOOKUP($A646,DICO_Complet!A:R,18,FALSE)=0,"",VLOOKUP($A646,DICO_Complet!A:R,18,FALSE))
A647: 250401135100 | B647: =IF(ISNA(VLOOKUP(Tableau161920[[#This Row],[Référence]],MON_MSG!A:B,2,FALSE)),"N",IF($I647="Obsolete","N","O")) -> O | C647: =VLOOKUP($A647,DICO_Complet!A:R,3,FALSE) -> Environment | D647: =VLOOKUP($A647,DICO_Complet!A:R,4,FALSE) -> acquirer | E647: =VLOOKUP($A647,DICO_Complet!A:R,5,FALSE) -> acquirerName | F647: =VLOOKUP($A647,DICO_Complet!A:R,6,FALSE) -> Max40Text | G647: =VLOOKUP($A647,DICO_Complet!A:R,7,FALSE) -> DNS | H647: =VLOOKUP($A647,DICO_Complet!A:R,8,FALSE) -> 0 | I647: =IF(VLOOKUP($A647,DICO_Complet!A:R,9,FALSE)<>0,VLOOKUP($A647,DICO_Complet!A:R,9,FALSE),"") | J647: =VLOOKUP($A647,DICO_Complet!A:R,10,FALSE) -> Acquirer Name | K647: =IF(OR(ISNA(VLOOKUP(Tableau161920[[#This Row],[Référence]],MON_MSG!A:H,7,FALSE)),ISBLANK(VLOOKUP(Tableau161920[[#This Row],[Référence]],MON_MSG!A:H,7,FALSE))),"",VLOOKUP(Tableau161920[[#This Row],[Référence]],MON_MSG!A:H,7,FALSE)) | L647: =IF(OR(ISNA(VLOOKUP(Tableau161920[[#This Row],[Référence]],MON_MSG!A:I,8,FALSE)),ISBLANK(VLOOKUP(Tableau161920[[#This Row],[Référence]],MON_MSG!A:I,8,FALSE))),"",VLOOKUP(Tableau161920[[#This Row],[Référence]],MON_MSG!A:I,8,FALSE)) | M647: =IF(OR(ISNA(VLOOKUP(Tableau161920[[#This Row],[Référence]],MON_MSG!A:J,9,FALSE)),ISBLANK(VLOOKUP(Tableau161920[[#This Row],[Référence]],MON_MSG!A:J,9,FALSE))),"",VLOOKUP(Tableau161920[[#This Row],[Référence]],MON_MSG!A:J,9,FALSE)) | N647: =IF(VLOOKUP($A647,DICO_Complet!A:R,12,FALSE)=0,"",VLOOKUP($A647,DICO_Complet!A:R,12,FALSE)) | O647: =IF(VLOOKUP($A647,DICO_Complet!A:R,13,FALSE)=0,"",VLOOKUP($A647,DICO_Complet!A:R,13,FALSE)) -> 112-0022 | P647: =IF(VLOOKUP($A647,DICO_Complet!A:R,14,FALSE)=0,"",VLOOKUP($A647,DICO_Complet!A:R,14,FALSE)) | Q647: =IF(VLOOKUP($A647,DICO_Complet!A:R,15,FALSE)=0,"",VLOOKUP($A647,DICO_Complet!A:R,15,FALSE)) | R647: =IF(VLOOKUP($A647,DICO_Complet!A:R,16,FALSE)=0,"",VLOOKUP($A647,DICO_Complet!A:R,16,FALSE)) -> field 34 Dataset ID 02 Tag C1 | S647: =IF(VLOOKUP($A647,DICO_Complet!A:R,17,FALSE)=0,"",VLOOKUP($A647,DICO_Complet!A:R,17,FALSE)) -> N/A | T647: =IF(VLOOKUP($A647,DICO_Complet!A:R,18,FALSE)=0,"",VLOOKUP($A647,DICO_Complet!A:R,18,FALSE))
A648: 250617141811 | B648: =IF(ISNA(VLOOKUP(Tableau161920[[#This Row],[Référence]],MON_MSG!A:B,2,FALSE)),"N",IF($I648="Obsolete","N","O")) -> O | C648: =VLOOKUP($A648,DICO_Complet!A:R,3,FALSE) -> Environment | D648: =VLOOKUP($A648,DICO_Complet!A:R,4,FALSE) -> acquirer | E648: =VLOOKUP($A648,DICO_Complet!A:R,5,FALSE) -> acquirerReferenceIdentification | F648: =VLOOKUP($A648,DICO_Complet!A:R,6,FALSE) -> Max6Text | G648: =VLOOKUP($A648,DICO_Complet!A:R,7,FALSE) -> DNS | H648: =VLOOKUP($A648,DICO_Complet!A:R,8,FALSE) -> 0 | I648: =IF(VLOOKUP($A648,DICO_Complet!A:R,9,FALSE)<>0,VLOOKUP($A648,DICO_Complet!A:R,9,FALSE),"") | J648: =VLOOKUP($A648,DICO_Complet!A:R,10,FALSE) -> Acquirer Reference Identification | K648: =IF(OR(ISNA(VLOOKUP(Tableau161920[[#This Row],[Référence]],MON_MSG!A:H,7,FALSE)),ISBLANK(VLOOKUP(Tableau161920[[#This Row],[Référence]],MON_MSG!A:H,7,FALSE))),"",VLOOKUP(Tableau161920[[#This Row],[Référence]],MON_MSG!A:H,7,FALSE)) | L648: =IF(OR(ISNA(VLOOKUP(Tableau161920[[#This Row],[Référence]],MON_MSG!A:I,8,FALSE)),ISBLANK(VLOOKUP(Tableau161920[[#This Row],[Référence]],MON_MSG!A:I,8,FALSE))),"",VLOOKUP(Tableau161920[[#This Row],[Référence]],MON_MSG!A:I,8,FALSE)) | M648: =IF(OR(ISNA(VLOOKUP(Tableau161920[[#This Row],[Référence]],MON_MSG!A:J,9,FALSE)),ISBLANK(VLOOKUP(Tableau161920[[#This Row],[Référence]],MON_MSG!A:J,9,FALSE))),"",VLOOKUP(Tableau161920[[#This Row],[Référence]],MON_MSG!A:J,9,FALSE)) | N648: =IF(VLOOKUP($A648,DICO_Complet!A:R,12,FALSE)=0,"",VLOOKUP($A648,DICO_Complet!A:R,12,FALSE)) -> ISO32_p1 | O648: =IF(VLOOKUP($A648,DICO_Complet!A:R,13,FALSE)=0,"",VLOOKUP($A648,DICO_Complet!A:R,13,FALSE)) -> 032-p1 | P648: =IF(VLOOKUP($A648,DICO_Complet!A:R,14,FALSE)=0,"",VLOOKUP($A648,DICO_Complet!A:R,14,FALSE)) -> 032-p1 | Q648: =IF(VLOOKUP($A648,DICO_Complet!A:R,15,FALSE)=0,"",VLOOKUP($A648,DICO_Complet!A:R,15,FALSE)) -> 032-p1 | R648: =IF(VLOOKUP($A648,DICO_Complet!A:R,16,FALSE)=0,"",VLOOKUP($A648,DICO_Complet!A:R,16,FALSE)) | S648: =IF(VLOOKUP($A648,DICO_Complet!A:R,17,FALSE)=0,"",VLOOKUP($A648,DICO_Complet!A:R,17,FALSE)) | T648: =IF(VLOOKUP($A648,DICO_Complet!A:R,18,FALSE)=0,"",VLOOKUP($A648,DICO_Complet!A:R,18,FALSE))
A649: 250418220108 | B649: =IF(ISNA(VLOOKUP(Tableau161920[[#This Row],[Référence]],MON_MSG!A:B,2,FALSE)),"N",IF($I649="Obsolete","N","O")) -> O | C649: =VLOOKUP($A649,DICO_Complet!A:R,3,FALSE) -> Environment | D649: =VLOOKUP($A649,DICO_Complet!A:R,4,FALSE) -> acquirer | E649: =VLOOKUP($A649,DICO_Complet!A:R,5,FALSE) -> acquirerSettlementCurrency | F649: =VLOOKUP($A649,DICO_Complet!A:R,6,FALSE) -> ISO3NumericCurrencyCode | G649: =VLOOKUP($A649,DICO_Complet!A:R,7,FALSE) -> DNS | H649: =VLOOKUP($A649,DICO_Complet!A:R,8,FALSE) -> 0 | I649: =IF(VLOOKUP($A649,DICO_Complet!A:R,9,FALSE)<>0,VLOOKUP($A649,DICO_Complet!A:R,9,FALSE),"") | J649: =VLOOKUP($A649,DICO_Complet!A:R,10,FALSE) -> Currency Code | K649: =IF(OR(ISNA(VLOOKUP(Tableau161920[[#This Row],[Référence]],MON_MSG!A:H,7,FALSE)),ISBLANK(VLOOKUP(Tableau161920[[#This Row],[Référence]],MON_MSG!A:H,7,FALSE))),"",VLOOKUP(Tableau161920[[#This Row],[Référence]],MON_MSG!A:H,7,FALSE)) | L649: =IF(OR(ISNA(VLOOKUP(Tableau161920[[#This Row],[Référence]],MON_MSG!A:I,8,FALSE)),ISBLANK(VLOOKUP(Tableau161920[[#This Row],[Référence]],MON_MSG!A:I,8,FALSE))),"",VLOOKUP(Tableau161920[[#This Row],[Référence]],MON_MSG!A:I,8,FALSE)) | M649: =IF(OR(ISNA(VLOOKUP(Tableau161920[[#This Row],[Référence]],MON_MSG!A:J,9,FALSE)),ISBLANK(VLOOKUP(Tableau161920[[#This Row],[Référence]],MON_MSG!A:J,9,FALSE))),"",VLOOKUP(Tableau161920[[#This Row],[Référence]],MON_MSG!A:J,9,FALSE)) | N649: =IF(VLOOKUP($A649,DICO_Complet!A:R,12,FALSE)=0,"",VLOOKUP($A649,DICO_Complet!A:R,12,FALSE)) | O649: =IF(VLOOKUP($A649,DICO_Complet!A:R,13,FALSE)=0,"",VLOOKUP($A649,DICO_Complet!A:R,13,FALSE)) | P649: =IF(VLOOKUP($A649,DICO_Complet!A:R,14,FALSE)=0,"",VLOOKUP($A649,DICO_Complet!A:R,14,FALSE)) | Q649: =IF(VLOOKUP($A649,DICO_Complet!A:R,15,FALSE)=0,"",VLOOKUP($A649,DICO_Complet!A:R,15,FALSE)) | R649: =IF(VLOOKUP($A649,DICO_Complet!A:R,16,FALSE)=0,"",VLOOKUP($A649,DICO_Complet!A:R,16,FALSE)) | S649: =IF(VLOOKUP($A649,DICO_Complet!A:R,17,FALSE)=0,"",VLOOKUP($A649,DICO_Complet!A:R,17,FALSE)) | T649: =IF(VLOOKUP($A649,DICO_Complet!A:R,18,FALSE)=0,"",VLOOKUP($A649,DICO_Complet!A:R,18,FALSE)) -> XXXX
A650: 250708150900 | B650: =IF(ISNA(VLOOKUP(Tableau161920[[#This Row],[Référence]],MON_MSG!A:B,2,FALSE)),"N",IF($I650="Obsolete","N","O")) -> O | C650: =VLOOKUP($A650,DICO_Complet!A:R,3,FALSE) -> Environment | D650: =VLOOKUP($A650,DICO_Complet!A:R,4,FALSE) -> acquirer | E650: =VLOOKUP($A650,DICO_Complet!A:R,5,FALSE) -> backOfficeEmailAddress | F650: =VLOOKUP($A650,DICO_Complet!A:R,6,FALSE) -> EmailAddressType | G650: =VLOOKUP($A650,DICO_Complet!A:R,7,FALSE) -> DNS | H650: =VLOOKUP($A650,DICO_Complet!A:R,8,FALSE) -> 0 | I650: =IF(VLOOKUP($A650,DICO_Complet!A:R,9,FALSE)<>0,VLOOKUP($A650,DICO_Complet!A:R,9,FALSE),"") | J650: =VLOOKUP($A650,DICO_Complet!A:R,10,FALSE) -> Email address for merchant to contact back office | K650: =IF(OR(ISNA(VLOOKUP(Tableau161920[[#This Row],[Référence]],MON_MSG!A:H,7,FALSE)),ISBLANK(VLOOKUP(Tableau161920[[#This Row],[Référence]],MON_MSG!A:H,7,FALSE))),"",VLOOKUP(Tableau161920[[#This Row],[Référence]],MON_MSG!A:H,7,FALSE)) | L650: =IF(OR(ISNA(VLOOKUP(Tableau161920[[#This Row],[Référence]],MON_MSG!A:I,8,FALSE)),ISBLANK(VLOOKUP(Tableau161920[[#This Row],[Référence]],MON_MSG!A:I,8,FALSE))),"",VLOOKUP(Tableau161920[[#This Row],[Référence]],MON_MSG!A:I,8,FALSE)) | M650: =IF(OR(ISNA(VLOOKUP(Tableau161920[[#This Row],[Référence]],MON_MSG!A:J,9,FALSE)),ISBLANK(VLOOKUP(Tableau161920[[#This Row],[Référence]],MON_MSG!A:J,9,FALSE))),"",VLOOKUP(Tableau161920[[#This Row],[Référence]],MON_MSG!A:J,9,FALSE)) | N650: =IF(VLOOKUP($A650,DICO_Complet!A:R,12,FALSE)=0,"",VLOOKUP($A650,DICO_Complet!A:R,12,FALSE)) | O650: =IF(VLOOKUP($A650,DICO_Complet!A:R,13,FALSE)=0,"",VLOOKUP($A650,DICO_Complet!A:R,13,FALSE)) | P650: =IF(VLOOKUP($A650,DICO_Complet!A:R,14,FALSE)=0,"",VLOOKUP($A650,DICO_Complet!A:R,14,FALSE)) | Q650: =IF(VLOOKUP($A650,DICO_Complet!A:R,15,FALSE)=0,"",VLOOKUP($A650,DICO_Complet!A:R,15,FALSE)) | R650: =IF(VLOOKUP($A650,DICO_Complet!A:R,16,FALSE)=0,"",VLOOKUP($A650,DICO_Complet!A:R,16,FALSE)) | S650: =IF(VLOOKUP($A650,DICO_Complet!A:R,17,FALSE)=0,"",VLOOKUP($A650,DICO_Complet!A:R,17,FALSE)) | T650: =IF(VLOOKUP($A650,DICO_Complet!A:R,18,FALSE)=0,"",VLOOKUP($A650,DICO_Complet!A:R,18,FALSE)) -> COTLP4
A651: 250418220110 | B651: =IF(ISNA(VLOOKUP(Tableau161920[[#This Row],[Référence]],MON_MSG!A:B,2,FALSE)),"N",IF($I651="Obsolete","N","O")) -> O | C651: =VLOOKUP($A651,DICO_Complet!A:R,3,FALSE) -> Environment | D651: =VLOOKUP($A651,DICO_Complet!A:R,4,FALSE) -> acquirer | E651: =VLOOKUP($A651,DICO_Complet!A:R,5,FALSE) -> backOfficeFax | F651: =VLOOKUP($A651,DICO_Complet!A:R,6,FALSE) -> PhoneNumberText | G651: =VLOOKUP($A651,DICO_Complet!A:R,7,FALSE) -> DNS | H651: =VLOOKUP($A651,DICO_Complet!A:R,8,FALSE) -> 0 | I651: =IF(VLOOKUP($A651,DICO_Complet!A:R,9,FALSE)<>0,VLOOKUP($A651,DICO_Complet!A:R,9,FALSE),"") | J651: =VLOOKUP($A651,DICO_Complet!A:R,10,FALSE) -> Fax machine number for merchant to contact back office | K651: =IF(OR(ISNA(VLOOKUP(Tableau161920[[#This Row],[Référence]],MON_MSG!A:H,7,FALSE)),ISBLANK(VLOOKUP(Tableau161920[[#This Row],[Référence]],MON_MSG!A:H,7,FALSE))),"",VLOOKUP(Tableau161920[[#This Row],[Référence]],MON_MSG!A:H,7,FALSE)) | L651: =IF(OR(ISNA(VLOOKUP(Tableau161920[[#This Row],[Référence]],MON_MSG!A:I,8,FALSE)),ISBLANK(VLOOKUP(Tableau161920[[#This Row],[Référence]],MON_MSG!A:I,8,FALSE))),"",VLOOKUP(Tableau161920[[#This Row],[Référence]],MON_MSG!A:I,8,FALSE)) | M651: =IF(OR(ISNA(VLOOKUP(Tableau161920[[#This Row],[Référence]],MON_MSG!A:J,9,FALSE)),ISBLANK(VLOOKUP(Tableau161920[[#This Row],[Référence]],MON_MSG!A:J,9,FALSE))),"",VLOOKUP(Tableau161920[[#This Row],[Référence]],MON_MSG!A:J,9,FALSE)) | N651: =IF(VLOOKUP($A651,DICO_Complet!A:R,12,FALSE)=0,"",VLOOKUP($A651,DICO_Complet!A:R,12,FALSE)) | O651: =IF(VLOOKUP($A651,DICO_Complet!A:R,13,FALSE)=0,"",VLOOKUP($A651,DICO_Complet!A:R,13,FALSE)) | P651: =IF(VLOOKUP($A651,DICO_Complet!A:R,14,FALSE)=0,"",VLOOKUP($A651,DICO_Complet!A:R,14,FALSE)) | Q651: =IF(VLOOKUP($A651,DICO_Complet!A:R,15,FALSE)=0,"",VLOOKUP($A651,DICO_Complet!A:R,15,FALSE)) | R651: =IF(VLOOKUP($A651,DICO_Complet!A:R,16,FALSE)=0,"",VLOOKUP($A651,DICO_Complet!A:R,16,FALSE)) | S651: =IF(VLOOKUP($A651,DICO_Complet!A:R,17,FALSE)=0,"",VLOOKUP($A651,DICO_Complet!A:R,17,FALSE)) | T651: =IF(VLOOKUP($A651,DICO_Complet!A:R,18,FALSE)=0,"",VLOOKUP($A651,DICO_Complet!A:R,18,FALSE)) -> COFAXS
... A868: 241112000119 | B868: =IF(ISNA(VLOOKUP(Tableau161920[[#This Row],[Référence]],MON_MSG!A:B,2,FALSE)),"N",IF($I868="Obsolete","N","O")) -> O | C868: =VLOOKUP($A868,DICO_Complet!A:R,3,FALSE) -> Environment | D868: =VLOOKUP($A868,DICO_Complet!A:R,4,FALSE) -> executionContract | E868: =VLOOKUP($A868,DICO_Complet!A:R,5,FALSE) -> executionContractCategory | F868: =VLOOKUP($A868,DICO_Complet!A:R,6,FALSE) -> ExecutionContractCategoryCodeset | G868: =VLOOKUP($A868,DICO_Complet!A:R,7,FALSE) -> DNS | H868: =VLOOKUP($A868,DICO_Complet!A:R,8,FALSE) -> 0 | I868: =IF(VLOOKUP($A868,DICO_Complet!A:R,9,FALSE)<>0,VLOOKUP($A868,DICO_Complet!A:R,9,FALSE),"") | J868: =VLOOKUP($A868,DICO_Complet!A:R,10,FALSE) -> Merchant type. Used to apply controls and enrichments based on merchant nature | K868: =IF(OR(ISNA(VLOOKUP(Tableau161920[[#This Row],[Référence]],MON_MSG!A:H,7,FALSE)),ISBLANK(VLOOKUP(Tableau161920[[#This Row],[Référence]],MON_MSG!A:H,7,FALSE))),"",VLOOKUP(Tableau161920[[#This Row],[Référence]],MON_MSG!A:H,7,FALSE)) | L868: =IF(OR(ISNA(VLOOKUP(Tableau161920[[#This Row],[Référence]],MON_MSG!A:I,8,FALSE)),ISBLANK(VLOOKUP(Tableau161920[[#This Row],[Référence]],MON_MSG!A:I,8,FALSE))),"",VLOOKUP(Tableau161920[[#This Row],[Référence]],MON_MSG!A:I,8,FALSE)) | M868: =IF(OR(ISNA(VLOOKUP(Tableau161920[[#This Row],[Référence]],MON_MSG!A:J,9,FALSE)),ISBLANK(VLOOKUP(Tableau161920[[#This Row],[Référence]],MON_MSG!A:J,9,FALSE))),"",VLOOKUP(Tableau161920[[#This Row],[Référence]],MON_MSG!A:J,9,FALSE)) | N868: =IF(VLOOKUP($A868,DICO_Complet!A:R,12,FALSE)=0,"",VLOOKUP($A868,DICO_Complet!A:R,12,FALSE)) -> AUT367 | O868: =IF(VLOOKUP($A868,DICO_Complet!A:R,13,FALSE)=0,"",VLOOKUP($A868,DICO_Complet!A:R,13,FALSE)) | P868: =IF(VLOOKUP($A868,DICO_Complet!A:R,14,FALSE)=0,"",VLOOKUP($A868,DICO_Complet!A:R,14,FALSE)) | Q868: =IF(VLOOKUP($A868,DICO_Complet!A:R,15,FALSE)=0,"",VLOOKUP($A868,DICO_Complet!A:R,15,FALSE)) | R868: =IF(VLOOKUP($A868,DICO_Complet!A:R,16,FALSE)=0,"",VLOOKUP($A868,DICO_Complet!A:R,16,FALSE)) | S868: =IF(VLOOKUP($A868,DICO_Complet!A:R,17,FALSE)=0,"",VLOOKUP($A868,DICO_Complet!A:R,17,FALSE)) | T868: =IF(VLOOKUP($A868,DICO_Complet!A:R,18,FALSE)=0,"",VLOOKUP($A868,DICO_Complet!A:R,18,FALSE))
A869: 251212150500 | B869: =IF(ISNA(VLOOKUP(Tableau161920[[#This Row],[Référence]],MON_MSG!A:B,2,FALSE)),"N",IF($I869="Obsolete","N","O")) -> O | C869: =VLOOKUP($A869,DICO_Complet!A:R,3,FALSE) -> Environment | D869: =VLOOKUP($A869,DICO_Complet!A:R,4,FALSE) -> executionContract | E869: =VLOOKUP($A869,DICO_Complet!A:R,5,FALSE) -> executionContractId | F869: =VLOOKUP($A869,DICO_Complet!A:R,6,FALSE) -> Max21Text | G869: =VLOOKUP($A869,DICO_Complet!A:R,7,FALSE) -> DNS | H869: =VLOOKUP($A869,DICO_Complet!A:R,8,FALSE) -> 0 | I869: =IF(VLOOKUP($A869,DICO_Complet!A:R,9,FALSE)<>0,VLOOKUP($A869,DICO_Complet!A:R,9,FALSE),"") | J869: =VLOOKUP($A869,DICO_Complet!A:R,10,FALSE) -> Execution Contract Unique Identifier | N869: =IF(VLOOKUP($A869,DICO_Complet!A:R,12,FALSE)=0,"",VLOOKUP($A869,DICO_Complet!A:R,12,FALSE)) | O869: =IF(VLOOKUP($A869,DICO_Complet!A:R,13,FALSE)=0,"",VLOOKUP($A869,DICO_Complet!A:R,13,FALSE)) | P869: =IF(VLOOKUP($A869,DICO_Complet!A:R,14,FALSE)=0,"",VLOOKUP($A869,DICO_Complet!A:R,14,FALSE)) | Q869: =IF(VLOOKUP($A869,DICO_Complet!A:R,15,FALSE)=0,"",VLOOKUP($A869,DICO_Complet!A:R,15,FALSE)) | R869: =IF(VLOOKUP($A869,DICO_Complet!A:R,16,FALSE)=0,"",VLOOKUP($A869,DICO_Complet!A:R,16,FALSE)) | S869: =IF(VLOOKUP($A869,DICO_Complet!A:R,17,FALSE)=0,"",VLOOKUP($A869,DICO_Complet!A:R,17,FALSE)) | T869: =IF(VLOOKUP($A869,DICO_Complet!A:R,18,FALSE)=0,"",VLOOKUP($A869,DICO_Complet!A:R,18,FALSE))
A870: 250613153500 | B870: =IF(ISNA(VLOOKUP(Tableau161920[[#This Row],[Référence]],MON_MSG!A:B,2,FALSE)),"N",IF($I870="Obsolete","N","O")) -> O | C870: =VLOOKUP($A870,DICO_Complet!A:R,3,FALSE) -> Environment | D870: =VLOOKUP($A870,DICO_Complet!A:R,4,FALSE) -> executionContract | E870: =VLOOKUP($A870,DICO_Complet!A:R,5,FALSE) -> executionContractNumber | F870: =VLOOKUP($A870,DICO_Complet!A:R,6,FALSE) -> Max15Text | G870: =VLOOKUP($A870,DICO_Complet!A:R,7,FALSE) -> DNS | H870: =VLOOKUP($A870,DICO_Complet!A:R,8,FALSE) -> 0 | I870: =IF(VLOOKUP($A870,DICO_Complet!A:R,9,FALSE)<>0,VLOOKUP($A870,DICO_Complet!A:R,9,FALSE),"") | J870: =VLOOKUP($A870,DICO_Complet!A:R,10,FALSE) -> Execution Contract Number | K870: =IF(OR(ISNA(VLOOKUP(Tableau161920[[#This Row],[Référence]],MON_MSG!A:H,7,FALSE)),ISBLANK(VLOOKUP(Tableau161920[[#This Row],[Référence]],MON_MSG!A:H,7,FALSE))),"",VLOOKUP(Tableau161920[[#This Row],[Référence]],MON_MSG!A:H,7,FALSE)) | L870: =IF(OR(ISNA(VLOOKUP(Tableau161920[[#This Row],[Référence]],MON_MSG!A:I,8,FALSE)),ISBLANK(VLOOKUP(Tableau161920[[#This Row],[Référence]],MON_MSG!A:I,8,FALSE))),"",VLOOKUP(Tableau161920[[#This Row],[Référence]],MON_MSG!A:I,8,FALSE)) | M870: =IF(OR(ISNA(VLOOKUP(Tableau161920[[#This Row],[Référence]],MON_MSG!A:J,9,FALSE)),ISBLANK(VLOOKUP(Tableau161920[[#This Row],[Référence]],MON_MSG!A:J,9,FALSE))),"",VLOOKUP(Tableau161920[[#This Row],[Référence]],MON_MSG!A:J,9,FALSE)) | N870: =IF(VLOOKUP($A870,DICO_Complet!A:R,12,FALSE)=0,"",VLOOKUP($A870,DICO_Complet!A:R,12,FALSE)) -> RSB59_202 | O870: =IF(VLOOKUP($A870,DICO_Complet!A:R,13,FALSE)=0,"",VLOOKUP($A870,DICO_Complet!A:R,13,FALSE)) -> 059-202 | P870: =IF(VLOOKUP($A870,DICO_Complet!A:R,14,FALSE)=0,"",VLOOKUP($A870,DICO_Complet!A:R,14,FALSE)) -> 046-DF5F | Q870: =IF(VLOOKUP($A870,DICO_Complet!A:R,15,FALSE)=0,"",VLOOKUP($A870,DICO_Complet!A:R,15,FALSE)) -> 059-202 | R870: =IF(VLOOKUP($A870,DICO_Complet!A:R,16,FALSE)=0,"",VLOOKUP($A870,DICO_Complet!A:R,16,FALSE)) | S870: =IF(VLOOKUP($A870,DICO_Complet!A:R,17,FALSE)=0,"",VLOOKUP($A870,DICO_Complet!A:R,17,FALSE)) | T870: =IF(VLOOKUP($A870,DICO_Complet!A:R,18,FALSE)=0,"",VLOOKUP($A870,DICO_Complet!A:R,18,FALSE))
A871: 250919150400 | B871: =IF(ISNA(VLOOKUP(Tableau161920[[#This Row],[Référence]],MON_MSG!A:B,2,FALSE)),"N",IF($I871="Obsolete","N","O")) -> O | C871: =VLOOKUP($A871,DICO_Complet!A:R,3,FALSE) -> Environment | D871: =VLOOKUP($A871,DICO_Complet!A:R,4,FALSE) -> executionContract | E871: =VLOOKUP($A871,DICO_Complet!A:R,5,FALSE) -> newExecutionContractIndicator | F871: =VLOOKUP($A871,DICO_Complet!A:R,6,FALSE) -> TrueFalseIndicator | G871: =VLOOKUP($A871,DICO_Complet!A:R,7,FALSE) -> DNS | H871: =VLOOKUP($A871,DICO_Complet!A:R,8,FALSE) -> 0 | I871: =IF(VLOOKUP($A871,DICO_Complet!A:R,9,FALSE)<>0,VLOOKUP($A871,DICO_Complet!A:R,9,FALSE),"") | J871: =VLOOKUP($A871,DICO_Complet!A:R,10,FALSE) -> Bank flag for new execution contract on POS creation or update with new channels. | K871: =IF(OR(ISNA(VLOOKUP(Tableau161920[[#This Row],[Référence]],MON_MSG!A:H,7,FALSE)),ISBLANK(VLOOKUP(Tableau161920[[#This Row],[Référence]],MON_MSG!A:H,7,FALSE))),"",VLOOKUP(Tableau161920[[#This Row],[Référence]],MON_MSG!A:H,7,FALSE)) | L871: =IF(OR(ISNA(VLOOKUP(Tableau161920[[#This Row],[Référence]],MON_MSG!A:I,8,FALSE)),ISBLANK(VLOOKUP(Tableau161920[[#This Row],[Référence]],MON_MSG!A:I,8,FALSE))),"",VLOOKUP(Tableau161920[[#This Row],[Référence]],MON_MSG!A:I,8,FALSE)) | M871: =IF(OR(ISNA(VLOOKUP(Tableau161920[[#This Row],[Référence]],MON_MSG!A:J,9,FALSE)),ISBLANK(VLOOKUP(Tableau161920[[#This Row],[Référence]],MON_MSG!A:J,9,FALSE))),"",VLOOKUP(Tableau161920[[#This Row],[Référence]],MON_MSG!A:J,9,FALSE)) | N871: =IF(VLOOKUP($A871,DICO_Complet!A:R,12,FALSE)=0,"",VLOOKUP($A871,DICO_Complet!A:R,12,FALSE)) | O871: =IF(VLOOKUP($A871,DICO_Complet!A:R,13,FALSE)=0,"",VLOOKUP($A871,DICO_Complet!A:R,13,FALSE)) | P871: =IF(VLOOKUP($A871,DICO_Complet!A:R,14,FALSE)=0,"",VLOOKUP($A871,DICO_Complet!A:R,14,FALSE)) | Q871: =IF(VLOOKUP($A871,DICO_Complet!A:R,15,FALSE)=0,"",VLOOKUP($A871,DICO_Complet!A:R,15,FALSE)) | R871: =IF(VLOOKUP($A871,DICO_Complet!A:R,16,FALSE)=0,"",VLOOKUP($A871,DICO_Complet!A:R,16,FALSE)) | S871: =IF(VLOOKUP($A871,DICO_Complet!A:R,17,FALSE)=0,"",VLOOKUP($A871,DICO_Complet!A:R,17,FALSE)) | T871: =IF(VLOOKUP($A871,DICO_Complet!A:R,18,FALSE)=0,"",VLOOKUP($A871,DICO_Complet!A:R,18,FALSE))
A872: 250324112200 | B872: =IF(ISNA(VLOOKUP(Tableau161920[[#This Row],[Référence]],MON_MSG!A:B,2,FALSE)),"N",IF($I872="Obsolete","N","O")) -> O | C872: =VLOOKUP($A872,DICO_Complet!A:R,3,FALSE) -> Environment | D872: =VLOOKUP($A872,DICO_Complet!A:R,4,FALSE) -> executionContract | E872: =VLOOKUP($A872,DICO_Complet!A:R,5,FALSE) -> processingCountry | F872: =VLOOKUP($A872,DICO_Complet!A:R,6,FALSE) -> ISO3NumericCountryCode | G872: =VLOOKUP($A872,DICO_Complet!A:R,7,FALSE) -> DNS | H872: =VLOOKUP($A872,DICO_Complet!A:R,8,FALSE) -> 0 | I872: =IF(VLOOKUP($A872,DICO_Complet!A:R,9,FALSE)<>0,VLOOKUP($A872,DICO_Complet!A:R,9,FALSE),"") | J872: =VLOOKUP($A872,DICO_Complet!A:R,10,FALSE) -> Execution contract country code. Used by terminal configuration service to identify scheme parameters to be sent to the merchant's equipment. | K872: =IF(OR(ISNA(VLOOKUP(Tableau161920[[#This Row],[Référence]],MON_MSG!A:H,7,FALSE)),ISBLANK(VLOOKUP(Tableau161920[[#This Row],[Référence]],MON_MSG!A:H,7,FALSE))),"",VLOOKUP(Tableau161920[[#This Row],[Référence]],MON_MSG!A:H,7,FALSE)) | L872: =IF(OR(ISNA(VLOOKUP(Tableau161920[[#This Row],[Référence]],MON_MSG!A:I,8,FALSE)),ISBLANK(VLOOKUP(Tableau161920[[#This Row],[Référence]],MON_MSG!A:I,8,FALSE))),"",VLOOKUP(Tableau161920[[#This Row],[Référence]],MON_MSG!A:I,8,FALSE)) | M872: =IF(OR(ISNA(VLOOKUP(Tableau161920[[#This Row],[Référence]],MON_MSG!A:J,9,FALSE)),ISBLANK(VLOOKUP(Tableau161920[[#This Row],[Référence]],MON_MSG!A:J,9,FALSE))),"",VLOOKUP(Tableau161920[[#This Row],[Référence]],MON_MSG!A:J,9,FALSE)) | N872: =IF(VLOOKUP($A872,DICO_Complet!A:R,12,FALSE)=0,"",VLOOKUP($A872,DICO_Complet!A:R,12,FALSE)) | O872: =IF(VLOOKUP($A872,DICO_Complet!A:R,13,FALSE)=0,"",VLOOKUP($A872,DICO_Complet!A:R,13,FALSE)) | P872: =IF(VLOOKUP($A872,DICO_Complet!A:R,14,FALSE)=0,"",VLOOKUP($A872,DICO_Complet!A:R,14,FALSE)) | Q872: =IF(VLOOKUP($A872,DICO_Complet!A:R,15,FALSE)=0,"",VLOOKUP($A872,DICO_Complet!A:R,15,FALSE)) | R872: =IF(VLOOKUP($A872,DICO_Complet!A:R,16,FALSE)=0,"",VLOOKUP($A872,DICO_Complet!A:R,16,FALSE)) | S872: =IF(VLOOKUP($A872,DICO_Complet!A:R,17,FALSE)=0,"",VLOOKUP($A872,DICO_Complet!A:R,17,FALSE)) | T872: =IF(VLOOKUP($A872,DICO_Complet!A:R,18,FALSE)=0,"",VLOOKUP($A872,DICO_Complet!A:R,18,FALSE))
A873: 250324114800 | B873: =IF(ISNA(VLOOKUP(Tableau161920[[#This Row],[Référence]],MON_MSG!A:B,2,FALSE)),"N",IF($I873="Obsolete","N","O")) -> O | C873: =VLOOKUP($A873,DICO_Complet!A:R,3,FALSE) -> Environment | D873: =VLOOKUP($A873,DICO_Complet!A:R,4,FALSE) -> executionContract | E873: =VLOOKUP($A873,DICO_Complet!A:R,5,FALSE) -> processingEndDate | F873: =VLOOKUP($A873,DICO_Complet!A:R,6,FALSE) -> ISODateTime | G873: =VLOOKUP($A873,DICO_Complet!A:R,7,FALSE) -> DNS | H873: =VLOOKUP($A873,DICO_Complet!A:R,8,FALSE) -> 0 | I873: =IF(VLOOKUP($A873,DICO_Complet!A:R,9,FALSE)<>0,VLOOKUP($A873,DICO_Complet!A:R,9,FALSE),"") | J873: =VLOOKUP($A873,DICO_Complet!A:R,10,FALSE) -> Merchant Processing End Date | K873: =IF(OR(ISNA(VLOOKUP(Tableau161920[[#This Row],[Référence]],MON_MSG!A:H,7,FALSE)),ISBLANK(VLOOKUP(Tableau161920[[#This Row],[Référence]],MON_MSG!A:H,7,FALSE))),"",VLOOKUP(Tableau161920[[#This Row],[Référence]],MON_MSG!A:H,7,FALSE)) | L873: =IF(OR(ISNA(VLOOKUP(Tableau161920[[#This Row],[Référence]],MON_MSG!A:I,8,FALSE)),ISBLANK(VLOOKUP(Tableau161920[[#This Row],[Référence]],MON_MSG!A:I,8,FALSE))),"",VLOOKUP(Tableau161920[[#This Row],[Référence]],MON_MSG!A:I,8,FALSE)) | M873: =IF(OR(ISNA(VLOOKUP(Tableau161920[[#This Row],[Référence]],MON_MSG!A:J,9,FALSE)),ISBLANK(VLOOKUP(Tableau161920[[#This Row],[Référence]],MON_MSG!A:J,9,FALSE))),"",VLOOKUP(Tableau161920[[#This Row],[Référence]],MON_MSG!A:J,9,FALSE)) | N873: =IF(VLOOKUP($A873,DICO_Complet!A:R,12,FALSE)=0,"",VLOOKUP($A873,DICO_Complet!A:R,12,FALSE)) | O873: =IF(VLOOKUP($A873,DICO_Complet!A:R,13,FALSE)=0,"",VLOOKUP($A873,DICO_Complet!A:R,13,FALSE)) | P873: =IF(VLOOKUP($A873,DICO_Complet!A:R,14,FALSE)=0,"",VLOOKUP($A873,DICO_Complet!A:R,14,FALSE)) | Q873: =IF(VLOOKUP($A873,DICO_Complet!A:R,15,FALSE)=0,"",VLOOKUP($A873,DICO_Complet!A:R,15,FALSE)) | R873: =IF(VLOOKUP($A873,DICO_Complet!A:R,16,FALSE)=0,"",VLOOKUP($A873,DICO_Complet!A:R,16,FALSE)) | S873: =IF(VLOOKUP($A873,DICO_Complet!A:R,17,FALSE)=0,"",VLOOKUP($A873,DICO_Complet!A:R,17,FALSE)) | T873: =IF(VLOOKUP($A873,DICO_Complet!A:R,18,FALSE)=0,"",VLOOKUP($A873,DICO_Complet!A:R,18,FALSE))
A874: 250617141800 | B874: =IF(ISNA(VLOOKUP(Tableau161920[[#This Row],[Référence]],MON_MSG!A:B,2,FALSE)),"N",IF($I874="Obsolete","N","O")) -> O | C874: =VLOOKUP($A874,DICO_Complet!A:R,3,FALSE) -> Environment | D874: =VLOOKUP($A874,DICO_Complet!A:R,4,FALSE) -> executionContract | E874: =VLOOKUP($A874,DICO_Complet!A:R,5,FALSE) -> processingName | F874: =VLOOKUP($A874,DICO_Complet!A:R,6,FALSE) -> Max70Text | G874: =VLOOKUP($A874,DICO_Complet!A:R,7,FALSE) -> DNS | H874: =VLOOKUP($A874,DICO_Complet!A:R,8,FALSE) -> 0 | I874: =IF(VLOOKUP($A874,DICO_Complet!A:R,9,FALSE)<>0,VLOOKUP($A874,DICO_Complet!A:R,9,FALSE),"") | J874: =VLOOKUP($A874,DICO_Complet!A:R,10,FALSE) -> Merchant Name used by all acquisition services. | K874: =IF(OR(ISNA(VLOOKUP(Tableau161920[[#This Row],[Référence]],MON_MSG!A:H,7,FALSE)),ISBLANK(VLOOKUP(Tableau161920[[#This Row],[Référence]],MON_MSG!A:H,7,FALSE))),"",VLOOKUP(Tableau161920[[#This Row],[Référence]],MON_MSG!A:H,7,FALSE)) | L874: =IF(OR(ISNA(VLOOKUP(Tableau161920[[#This Row],[Référence]],MON_MSG!A:I,8,FALSE)),ISBLANK(VLOOKUP(Tableau161920[[#This Row],[Référence]],MON_MSG!A:I,8,FALSE))),"",VLOOKUP(Tableau161920[[#This Row],[Référence]],MON_MSG!A:I,8,FALSE)) | M874: =IF(OR(ISNA(VLOOKUP(Tableau161920[[#This Row],[Référence]],MON_MSG!A:J,9,FALSE)),ISBLANK(VLOOKUP(Tableau161920[[#This Row],[Référence]],MON_MSG!A:J,9,FALSE))),"",VLOOKUP(Tableau161920[[#This Row],[Référence]],MON_MSG!A:J,9,FALSE)) | N874: =IF(VLOOKUP($A874,DICO_Complet!A:R,12,FALSE)=0,"",VLOOKUP($A874,DICO_Complet!A:R,12,FALSE)) | O874: =IF(VLOOKUP($A874,DICO_Complet!A:R,13,FALSE)=0,"",VLOOKUP($A874,DICO_Complet!A:R,13,FALSE)) -> 043-p1-1 | P874: =IF(VLOOKUP($A874,DICO_Complet!A:R,14,FALSE)=0,"",VLOOKUP($A874,DICO_Complet!A:R,14,FALSE)) -> 043-p1-1 | Q874: =IF(VLOOKUP($A874,DICO_Complet!A:R,15,FALSE)=0,"",VLOOKUP($A874,DICO_Complet!A:R,15,FALSE)) -> 043-p1-1 | R874: =IF(VLOOKUP($A874,DICO_Complet!A:R,16,FALSE)=0,"",VLOOKUP($A874,DICO_Complet!A:R,16,FALSE)) | S874: =IF(VLOOKUP($A874,DICO_Complet!A:R,17,FALSE)=0,"",VLOOKUP($A874,DICO_Complet!A:R,17,FALSE)) | T874: =IF(VLOOKUP($A874,DICO_Complet!A:R,18,FALSE)=0,"",VLOOKUP($A874,DICO_Complet!A:R,18,FALSE))
A875: 250324114700 | B875: =IF(ISNA(VLOOKUP(Tableau161920[[#This Row],[Référence]],MON_MSG!A:B,2,FALSE)),"N",IF($I875="Obsolete","N","O")) -> O | C875: =VLOOKUP($A875,DICO_Complet!A:R,3,FALSE) -> Environment | D875: =VLOOKUP($A875,DICO_Complet!A:R,4,FALSE) -> executionContract | E875: =VLOOKUP($A875,DICO_Complet!A:R,5,FALSE) -> processingStartDate | F875: =VLOOKUP($A875,DICO_Complet!A:R,6,FALSE) -> ISODateTime | G875: =VLOOKUP($A875,DICO_Complet!A:R,7,FALSE) -> DNS | H875: =VLOOKUP($A875,DICO_Complet!A:R,8,FALSE) -> 0 | I875: =IF(VLOOKUP($A875,DICO_Complet!A:R,9,FALSE)<>0,VLOOKUP($A875,DICO_Complet!A:R,9,FALSE),"") | J875: =VLOOKUP($A875,DICO_Complet!A:R,10,FALSE) -> Merchant Processing Start Date | K875: =IF(OR(ISNA(VLOOKUP(Tableau161920[[#This Row],[Référence]],MON_MSG!A:H,7,FALSE)),ISBLANK(VLOOKUP(Tableau161920[[#This Row],[Référence]],MON_MSG!A:H,7,FALSE))),"",VLOOKUP(Tableau161920[[#This Row],[Référence]],MON_MSG!A:H,7,FALSE)) | L875: =IF(OR(ISNA(VLOOKUP(Tableau161920[[#This Row],[Référence]],MON_MSG!A:I,8,FALSE)),ISBLANK(VLOOKUP(Tableau161920[[#This Row],[Référence]],MON_MSG!A:I,8,FALSE))),"",VLOOKUP(Tableau161920[[#This Row],[Référence]],MON_MSG!A:I,8,FALSE)) | M875: =IF(OR(ISNA(VLOOKUP(Tableau161920[[#This Row],[Référence]],MON_MSG!A:J,9,FALSE)),ISBLANK(VLOOKUP(Tableau161920[[#This Row],[Référence]],MON_MSG!A:J,9,FALSE))),"",VLOOKUP(Tableau161920[[#This Row],[Référence]],MON_MSG!A:J,9,FALSE)) | N875: =IF(VLOOKUP($A875,DICO_Complet!A:R,12,FALSE)=0,"",VLOOKUP($A875,DICO_Complet!A:R,12,FALSE)) | O875: =IF(VLOOKUP($A875,DICO_Complet!A:R,13,FALSE)=0,"",VLOOKUP($A875,DICO_Complet!A:R,13,FALSE)) | P875: =IF(VLOOKUP($A875,DICO_Complet!A:R,14,FALSE)=0,"",VLOOKUP($A875,DICO_Complet!A:R,14,FALSE)) | Q875: =IF(VLOOKUP($A875,DICO_Complet!A:R,15,FALSE)=0,"",VLOOKUP($A875,DICO_Complet!A:R,15,FALSE)) | R875: =IF(VLOOKUP($A875,DICO_Complet!A:R,16,FALSE)=0,"",VLOOKUP($A875,DICO_Complet!A:R,16,FALSE)) | S875: =IF(VLOOKUP($A875,DICO_Complet!A:R,17,FALSE)=0,"",VLOOKUP($A875,DICO_Complet!A:R,17,FALSE)) | T875: =IF(VLOOKUP($A875,DICO_Complet!A:R,18,FALSE)=0,"",VLOOKUP($A875,DICO_Complet!A:R,18,FALSE))
A876: 251120143000 | B876: =IF(ISNA(VLOOKUP(Tableau161920[[#This Row],[Référence]],MON_MSG!A:B,2,FALSE)),"N",IF($I876="Obsolete","N","O")) -> O | C876: =VLOOKUP($A876,DICO_Complet!A:R,3,FALSE) -> Environment | D876: =VLOOKUP($A876,DICO_Complet!A:R,4,FALSE) -> insurance | E876: =VLOOKUP($A876,DICO_Complet!A:R,5,FALSE) -> cardPackageCode | F876: =VLOOKUP($A876,DICO_Complet!A:R,6,FALSE) -> Max255Text | G876: =VLOOKUP($A876,DICO_Complet!A:R,7,FALSE) -> DNS | H876: =VLOOKUP($A876,DICO_Complet!A:R,8,FALSE) -> 0 | I876: =IF(VLOOKUP($A876,DICO_Complet!A:R,9,FALSE)<>0,VLOOKUP($A876,DICO_Complet!A:R,9,FALSE),"") | J876: =VLOOKUP($A876,DICO_Complet!A:R,10,FALSE) -> Card Package Code | K876: =IF(OR(ISNA(VLOOKUP(Tableau161920[[#This Row],[Référence]],MON_MSG!A:H,7,FALSE)),ISBLANK(VLOOKUP(Tableau161920[[#This Row],[Référence]],MON_MSG!A:H,7,FALSE))),"",VLOOKUP(Tableau161920[[#This Row],[Référence]],MON_MSG!A:H,7,FALSE)) | L876: =IF(OR(ISNA(VLOOKUP(Tableau161920[[#This Row],[Référence]],MON_MSG!A:I,8,FALSE)),ISBLANK(VLOOKUP(Tableau161920[[#This Row],[Référence]],MON_MSG!A:I,8,FALSE))),"",VLOOKUP(Tableau161920[[#This Row],[Référence]],MON_MSG!A:I,8,FALSE)) | M876: =IF(OR(ISNA(VLOOKUP(Tableau161920[[#This Row],[Référence]],MON_MSG!A:J,9,FALSE)),ISBLANK(VLOOKUP(Tableau161920[[#This Row],[Référence]],MON_MSG!A:J,9,FALSE))),"",VLOOKUP(Tableau161920[[#This Row],[Référence]],MON_MSG!A:J,9,FALSE)) | N876: =IF(VLOOKUP($A876,DICO_Complet!A:R,12,FALSE)=0,"",VLOOKUP($A876,DICO_Complet!A:R,12,FALSE)) | O876: =IF(VLOOKUP($A876,DICO_Complet!A:R,13,FALSE)=0,"",VLOOKUP($A876,DICO_Complet!A:R,13,FALSE)) | P876: =IF(VLOOKUP($A876,DICO_Complet!A:R,14,FALSE)=0,"",VLOOKUP($A876,DICO_Complet!A:R,14,FALSE)) | Q876: =IF(VLOOKUP($A876,DICO_Complet!A:R,15,FALSE)=0,"",VLOOKUP($A876,DICO_Complet!A:R,15,FALSE)) | R876: =IF(VLOOKUP($A876,DICO_Complet!A:R,16,FALSE)=0,"",VLOOKUP($A876,DICO_Complet!A:R,16,FALSE)) | S876: =IF(VLOOKUP($A876,DICO_Complet!A:R,17,FALSE)=0,"",VLOOKUP($A876,DICO_Complet!A:R,17,FALSE)) | T876: =IF(VLOOKUP($A876,DICO_Complet!A:R,18,FALSE)=0,"",VLOOKUP($A876,DICO_Complet!A:R,18,FALSE))
A877: 251027112310 | B877: =IF(ISNA(VLOOKUP(Tableau161920[[#This Row],[Référence]],MON_MSG!A:B,2,FALSE)),"N",IF($I877="Obsolete","N","O")) -> O | C877: =VLOOKUP($A877,DICO_Complet!A:R,3,FALSE) -> Environment | D877: =VLOOKUP($A877,DICO_Complet!A:R,4,FALSE) -> insurance | E877: =VLOOKUP($A877,DICO_Complet!A:R,5,FALSE) -> excessAmount | F877: =VLOOKUP($A877,DICO_Complet!A:R,6,FALSE) -> AmountType | G877: =VLOOKUP($A877,DICO_Complet!A:R,7,FALSE) -> DNS | H877: =VLOOKUP($A877,DICO_Complet!A:R,8,FALSE) -> 0 | I877: =IF(VLOOKUP($A877,DICO_Complet!A:R,9,FALSE)<>0,VLOOKUP($A877,DICO_Complet!A:R,9,FALSE),"") | J877: =VLOOKUP($A877,DICO_Complet!A:R,10,FALSE) -> Excess amount | K877: =IF(OR(ISNA(VLOOKUP(Tableau161920[[#This Row],[Référence]],MON_MSG!A:H,7,FALSE)),ISBLANK(VLOOKUP(Tableau161920[[#This Row],[Référence]],MON_MSG!A:H,7,FALSE))),"",VLOOKUP(Tableau161920[[#This Row],[Référence]],MON_MSG!A:H,7,FALSE)) | L877: =IF(OR(ISNA(VLOOKUP(Tableau161920[[#This Row],[Référence]],MON_MSG!A:I,8,FALSE)),ISBLANK(VLOOKUP(Tableau161920[[#This Row],[Référence]],MON_MSG!A:I,8,FALSE))),"",VLOOKUP(Tableau161920[[#This Row],[Référence]],MON_MSG!A:I,8,FALSE)) | M877: =IF(OR(ISNA(VLOOKUP(Tableau161920[[#This Row],[Référence]],MON_MSG!A:J,9,FALSE)),ISBLANK(VLOOKUP(Tableau161920[[#This Row],[Référence]],MON_MSG!A:J,9,FALSE))),"",VLOOKUP(Tableau161920[[#This Row],[Référence]],MON_MSG!A:J,9,FALSE)) | N877: =IF(VLOOKUP($A877,DICO_Complet!A:R,12,FALSE)=0,"",VLOOKUP($A877,DICO_Complet!A:R,12,FALSE)) | O877: =IF(VLOOKUP($A877,DICO_Complet!A:R,13,FALSE)=0,"",VLOOKUP($A877,DICO_Complet!A:R,13,FALSE)) | P877: =IF(VLOOKUP($A877,DICO_Complet!A:R,14,FALSE)=0,"",VLOOKUP($A877,DICO_Complet!A:R,14,FALSE)) | Q877: =IF(VLOOKUP($A877,DICO_Complet!A:R,15,FALSE)=0,"",VLOOKUP($A877,DICO_Complet!A:R,15,FALSE)) | R877: =IF(VLOOKUP($A877,DICO_Complet!A:R,16,FALSE)=0,"",VLOOKUP($A877,DICO_Complet!A:R,16,FALSE)) | S877: =IF(VLOOKUP($A877,DICO_Complet!A:R,17,FALSE)=0,"",VLOOKUP($A877,DICO_Complet!A:R,17,FALSE)) | T877: =IF(VLOOKUP($A877,DICO_Complet!A:R,18,FALSE)=0,"",VLOOKUP($A877,DICO_Complet!A:R,18,FALSE))
A878: 251027112306 | B878: =IF(ISNA(VLOOKUP(Tableau161920[[#This Row],[Référence]],MON_MSG!A:B,2,FALSE)),"N",IF($I878="Obsolete","N","O")) -> O | C878: =VLOOKUP($A878,DICO_Complet!A:R,3,FALSE) -> Environment | D878: =VLOOKUP($A878,DICO_Complet!A:R,4,FALSE) -> insurance | E878: =VLOOKUP($A878,DICO_Complet!A:R,5,FALSE) -> insuranceContractLabel | F878: =VLOOKUP($A878,DICO_Complet!A:R,6,FALSE) -> Max255Text | G878: =VLOOKUP($A878,DICO_Complet!A:R,7,FALSE) -> DNS | H878: =VLOOKUP($A878,DICO_Complet!A:R,8,FALSE) -> 0 | I878: =IF(VLOOKUP($A878,DICO_Complet!A:R,9,FALSE)<>0,VLOOKUP($A878,DICO_Complet!A:R,9,FALSE),"") | J878: =VLOOKUP($A878,DICO_Complet!A:R,10,FALSE) -> Insurance contract label | K878: =IF(OR(ISNA(VLOOKUP(Tableau161920[[#This Row],[Référence]],MON_MSG!A:H,7,FALSE)),ISBLANK(VLOOKUP(Tableau161920[[#This Row],[Référence]],MON_MSG!A:H,7,FALSE))),"",VLOOKUP(Tableau161920[[#This Row],[Référence]],MON_MSG!A:H,7,FALSE)) | L878: =IF(OR(ISNA(VLOOKUP(Tableau161920[[#This Row],[Référence]],MON_MSG!A:I,8,FALSE)),ISBLANK(VLOOKUP(Tableau161920[[#This Row],[Référence]],MON_MSG!A:I,8,FALSE))),"",VLOOKUP(Tableau161920[[#This Row],[Référence]],MON_MSG!A:I,8,FALSE)) | M878: =IF(OR(ISNA(VLOOKUP(Tableau161920[[#This Row],[Référence]],MON_MSG!A:J,9,FALSE)),ISBLANK(VLOOKUP(Tableau161920[[#This Row],[Référence]],MON_MSG!A:J,9,FALSE))),"",VLOOKUP(Tableau161920[[#This Row],[Référence]],MON_MSG!A:J,9,FALSE)) | N878: =IF(VLOOKUP($A878,DICO_Complet!A:R,12,FALSE)=0,"",VLOOKUP($A878,DICO_Complet!A:R,12,FALSE)) | O878: =IF(VLOOKUP($A878,DICO_Complet!A:R,13,FALSE)=0,"",VLOOKUP($A878,DICO_Complet!A:R,13,FALSE)) | P878: =IF(VLOOKUP($A878,DICO_Complet!A:R,14,FALSE)=0,"",VLOOKUP($A878,DICO_Complet!A:R,14,FALSE)) | Q878: =IF(VLOOKUP($A878,DICO_Complet!A:R,15,FALSE)=0,"",VLOOKUP($A878,DICO_Complet!A:R,15,FALSE)) | R878: =IF(VLOOKUP($A878,DICO_Complet!A:R,16,FALSE)=0,"",VLOOKUP($A878,DICO_Complet!A:R,16,FALSE)) | S878: =IF(VLOOKUP($A878,DICO_Complet!A:R,17,FALSE)=0,"",VLOOKUP($A878,DICO_Complet!A:R,17,FALSE)) | T878: =IF(VLOOKUP($A878,DICO_Complet!A:R,18,FALSE)=0,"",VLOOKUP($A878,DICO_Complet!A:R,18,FALSE))
A879: 251120143001 | B879: =IF(ISNA(VLOOKUP(Tableau161920[[#This Row],[Référence]],MON_MSG!A:B,2,FALSE)),"N",IF($I879="Obsolete","N","O")) -> O | C879: =VLOOKUP($A879,DICO_Complet!A:R,3,FALSE) -> Environment | D879: =VLOOKUP($A879,DICO_Complet!A:R,4,FALSE) -> insurance | E879: =VLOOKUP($A879,DICO_Complet!A:R,5,FALSE) -> insuranceContractNumber | F879: =VLOOKUP($A879,DICO_Complet!A:R,6,FALSE) -> Max255Text | G879: =VLOOKUP($A879,DICO_Complet!A:R,7,FALSE) -> DNS | H879: =VLOOKUP($A879,DICO_Complet!A:R,8,FALSE) -> 0 | I879: =IF(VLOOKUP($A879,DICO_Complet!A:R,9,FALSE)<>0,VLOOKUP($A879,DICO_Complet!A:R,9,FALSE),"") | J879: =VLOOKUP($A879,DICO_Complet!A:R,10,FALSE) -> Insurance Contract Number | K879: =IF(OR(ISNA(VLOOKUP(Tableau161920[[#This Row],[Référence]],MON_MSG!A:H,7,FALSE)),ISBLANK(VLOOKUP(Tableau161920[[#This Row],[Référence]],MON_MSG!A:H,7,FALSE))),"",VLOOKUP(Tableau161920[[#This Row],[Référence]],MON_MSG!A:H,7,FALSE)) | L879: =IF(OR(ISNA(VLOOKUP(Tableau161920[[#This Row],[Référence]],MON_MSG!A:I,8,FALSE)),ISBLANK(VLOOKUP(Tableau161920[[#This Row],[Référence]],MON_MSG!A:I,8,FALSE))),"",VLOOKUP(Tableau161920[[#This Row],[Référence]],MON_MSG!A:I,8,FALSE)) | M879: =IF(OR(ISNA(VLOOKUP(Tableau161920[[#This Row],[Référence]],MON_MSG!A:J,9,FALSE)),ISBLANK(VLOOKUP(Tableau161920[[#This Row],[Référence]],MON_MSG!A:J,9,FALSE))),"",VLOOKUP(Tableau161920[[#This Row],[Référence]],MON_MSG!A:J,9,FALSE)) | N879: =IF(VLOOKUP($A879,DICO_Complet!A:R,12,FALSE)=0,"",VLOOKUP($A879,DICO_Complet!A:R,12,FALSE)) | O879: =IF(VLOOKUP($A879,DICO_Complet!A:R,13,FALSE)=0,"",VLOOKUP($A879,DICO_Complet!A:R,13,FALSE)) | P879: =IF(VLOOKUP($A879,DICO_Complet!A:R,14,FALSE)=0,"",VLOOKUP($A879,DICO_Complet!A:R,14,FALSE)) | Q879: =IF(VLOOKUP($A879,DICO_Complet!A:R,15,FALSE)=0,"",VLOOKUP($A879,DICO_Complet!A:R,15,FALSE)) | R879: =IF(VLOOKUP($A879,DICO_Complet!A:R,16,FALSE)=0,"",VLOOKUP($A879,DICO_Complet!A:R,16,FALSE)) | S879: =IF(VLOOKUP($A879,DICO_Complet!A:R,17,FALSE)=0,"",VLOOKUP($A879,DICO_Complet!A:R,17,FALSE)) | T879: =IF(VLOOKUP($A879,DICO_Complet!A:R,18,FALSE)=0,"",VLOOKUP($A879,DICO_Complet!A:R,18,FALSE))
A880: 251120143003 | B880: =IF(ISNA(VLOOKUP(Tableau161920[[#This Row],[Référence]],MON_MSG!A:B,2,FALSE)),"N",IF($I880="Obsolete","N","O")) -> O | C880: =VLOOKUP($A880,DICO_Complet!A:R,3,FALSE) -> Environment | D880: =VLOOKUP($A880,DICO_Complet!A:R,4,FALSE) -> insurance | E880: =VLOOKUP($A880,DICO_Complet!A:R,5,FALSE) -> insuranceCoverageLimit | F880: =VLOOKUP($A880,DICO_Complet!A:R,6,FALSE) -> AmountType | G880: =VLOOKUP($A880,DICO_Complet!A:R,7,FALSE) -> DNS | H880: =VLOOKUP($A880,DICO_Complet!A:R,8,FALSE) -> 0 | I880: =IF(VLOOKUP($A880,DICO_Complet!A:R,9,FALSE)<>0,VLOOKUP($A880,DICO_Complet!A:R,9,FALSE),"") | J880: =VLOOKUP($A880,DICO_Complet!A:R,10,FALSE) -> Limit of the assurance coverage (amount and currency) | K880: =IF(OR(ISNA(VLOOKUP(Tableau161920[[#This Row],[Référence]],MON_MSG!A:H,7,FALSE)),ISBLANK(VLOOKUP(Tableau161920[[#This Row],[Référence]],MON_MSG!A:H,7,FALSE))),"",VLOOKUP(Tableau161920[[#This Row],[Référence]],MON_MSG!A:H,7,FALSE)) | L880: =IF(OR(ISNA(VLOOKUP(Tableau161920[[#This Row],[Référence]],MON_MSG!A:I,8,FALSE)),ISBLANK(VLOOKUP(Tableau161920[[#This Row],[Référence]],MON_MSG!A:I,8,FALSE))),"",VLOOKUP(Tableau161920[[#This Row],[Référence]],MON_MSG!A:I,8,FALSE)) | M880: =IF(OR(ISNA(VLOOKUP(Tableau161920[[#This Row],[Référence]],MON_MSG!A:J,9,FALSE)),ISBLANK(VLOOKUP(Tableau161920[[#This Row],[Référence]],MON_MSG!A:J,9,FALSE))),"",VLOOKUP(Tableau161920[[#This Row],[Référence]],MON_MSG!A:J,9,FALSE)) | N880: =IF(VLOOKUP($A880,DICO_Complet!A:R,12,FALSE)=0,"",VLOOKUP($A880,DICO_Complet!A:R,12,FALSE)) | O880: =IF(VLOOKUP($A880,DICO_Complet!A:R,13,FALSE)=0,"",VLOOKUP($A880,DICO_Complet!A:R,13,FALSE)) | P880: =IF(VLOOKUP($A880,DICO_Complet!A:R,14,FALSE)=0,"",VLOOKUP($A880,DICO_Complet!A:R,14,FALSE)) | Q880: =IF(VLOOKUP($A880,DICO_Complet!A:R,15,FALSE)=0,"",VLOOKUP($A880,DICO_Complet!A:R,15,FALSE)) | R880: =IF(VLOOKUP($A880,DICO_Complet!A:R,16,FALSE)=0,"",VLOOKUP($A880,DICO_Complet!A:R,16,FALSE)) | S880: =IF(VLOOKUP($A880,DICO_Complet!A:R,17,FALSE)=0,"",VLOOKUP($A880,DICO_Complet!A:R,17,FALSE)) | T880: =IF(VLOOKUP($A880,DICO_Complet!A:R,18,FALSE)=0,"",VLOOKUP($A880,DICO_Complet!A:R,18,FALSE))
A881: 251120143002 | B881: =IF(ISNA(VLOOKUP(Tableau161920[[#This Row],[Référence]],MON_MSG!A:B,2,FALSE)),"N",IF($I881="Obsolete","N","O")) -> O | C881: =VLOOKUP($A881,DICO_Complet!A:R,3,FALSE) -> Environment | D881: =VLOOKUP($A881,DICO_Complet!A:R,4,FALSE) -> insurance | E881: =VLOOKUP($A881,DICO_Complet!A:R,5,FALSE) -> insuranceSubscriptionDateTime | F881: =VLOOKUP($A881,DICO_Complet!A:R,6,FALSE) -> ISODateTime | G881: =VLOOKUP($A881,DICO_Complet!A:R,7,FALSE) -> DNS | H881: =VLOOKUP($A881,DICO_Complet!A:R,8,FALSE) -> 0 | I881: =IF(VLOOKUP($A881,DICO_Complet!A:R,9,FALSE)<>0,VLOOKUP($A881,DICO_Complet!A:R,9,FALSE),"") | J881: =VLOOKUP($A881,DICO_Complet!A:R,10,FALSE) -> Insurance subscriptiuon date (YYYY-MM-DDThh:mm:ss) | K881: =IF(OR(ISNA(VLOOKUP(Tableau161920[[#This Row],[Référence]],MON_MSG!A:H,7,FALSE)),ISBLANK(VLOOKUP(Tableau161920[[#This Row],[Référence]],MON_MSG!A:H,7,FALSE))),"",VLOOKUP(Tableau161920[[#This Row],[Référence]],MON_MSG!A:H,7,FALSE)) | L881: =IF(OR(ISNA(VLOOKUP(Tableau161920[[#This Row],[Référence]],MON_MSG!A:I,8,FALSE)),ISBLANK(VLOOKUP(Tableau161920[[#This Row],[Référence]],MON_MSG!A:I,8,FALSE))),"",VLOOKUP(Tableau161920[[#This Row],[Référence]],MON_MSG!A:I,8,FALSE)) | M881: =IF(OR(ISNA(VLOOKUP(Tableau161920[[#This Row],[Référence]],MON_MSG!A:J,9,FALSE)),ISBLANK(VLOOKUP(Tableau161920[[#This Row],[Référence]],MON_MSG!A:J,9,FALSE))),"",VLOOKUP(Tableau161920[[#This Row],[Référence]],MON_MSG!A:J,9,FALSE)) | N881: =IF(VLOOKUP($A881,DICO_Complet!A:R,12,FALSE)=0,"",VLOOKUP($A881,DICO_Complet!A:R,12,FALSE)) | O881: =IF(VLOOKUP($A881,DICO_Complet!A:R,13,FALSE)=0,"",VLOOKUP($A881,DICO_Complet!A:R,13,FALSE)) | P881: =IF(VLOOKUP($A881,DICO_Complet!A:R,14,FALSE)=0,"",VLOOKUP($A881,DICO_Complet!A:R,14,FALSE)) | Q881: =IF(VLOOKUP($A881,DICO_Complet!A:R,15,FALSE)=0,"",VLOOKUP($A881,DICO_Complet!A:R,15,FALSE)) | R881: =IF(VLOOKUP($A881,DICO_Complet!A:R,16,FALSE)=0,"",VLOOKUP($A881,DICO_Complet!A:R,16,FALSE)) | S881: =IF(VLOOKUP($A881,DICO_Complet!A:R,17,FALSE)=0,"",VLOOKUP($A881,DICO_Complet!A:R,17,FALSE)) | T881: =IF(VLOOKUP($A881,DICO_Complet!A:R,18,FALSE)=0,"",VLOOKUP($A881,DICO_Complet!A:R,18,FALSE))
... A1833: 260422171100 | B1833: =IF(ISNA(VLOOKUP(Tableau161920[[#This Row],[Référence]],MON_MSG!A:B,2,FALSE)),"N",IF($I1833="Obsolete","N","O")) -> O | C1833: =VLOOKUP($A1833,DICO_Complet!A:R,3,FALSE) -> Transaction | D1833: =VLOOKUP($A1833,DICO_Complet!A:R,4,FALSE) -> originalTransactionData | E1833: =VLOOKUP($A1833,DICO_Complet!A:R,5,FALSE) -> initialThreeDsProtocolVersion | F1833: =VLOOKUP($A1833,DICO_Complet!A:R,6,FALSE) -> Max2NumericText | G1833: =VLOOKUP($A1833,DICO_Complet!A:R,7,FALSE) -> DNS | H1833: =VLOOKUP($A1833,DICO_Complet!A:R,8,FALSE) -> 0 | I1833: =IF(VLOOKUP($A1833,DICO_Complet!A:R,9,FALSE)<>0,VLOOKUP($A1833,DICO_Complet!A:R,9,FALSE),"") | J1833: =VLOOKUP($A1833,DICO_Complet!A:R,10,FALSE) -> 3DS protocol major version | K1833: =IF(OR(ISNA(VLOOKUP(Tableau161920[[#This Row],[Référence]],MON_MSG!A:H,7,FALSE)),ISBLANK(VLOOKUP(Tableau161920[[#This Row],[Référence]],MON_MSG!A:H,7,FALSE))),"",VLOOKUP(Tableau161920[[#This Row],[Référence]],MON_MSG!A:H,7,FALSE)) | L1833: =IF(OR(ISNA(VLOOKUP(Tableau161920[[#This Row],[Référence]],MON_MSG!A:I,8,FALSE)),ISBLANK(VLOOKUP(Tableau161920[[#This Row],[Référence]],MON_MSG!A:I,8,FALSE))),"",VLOOKUP(Tableau161920[[#This Row],[Référence]],MON_MSG!A:I,8,FALSE)) | M1833: =IF(OR(ISNA(VLOOKUP(Tableau161920[[#This Row],[Référence]],MON_MSG!A:J,9,FALSE)),ISBLANK(VLOOKUP(Tableau161920[[#This Row],[Référence]],MON_MSG!A:J,9,FALSE))),"",VLOOKUP(Tableau161920[[#This Row],[Référence]],MON_MSG!A:J,9,FALSE)) | N1833: =IF(VLOOKUP($A1833,DICO_Complet!A:R,12,FALSE)=0,"",VLOOKUP($A1833,DICO_Complet!A:R,12,FALSE)) -> RSB119_0046_ p1 | O1833: =IF(VLOOKUP($A1833,DICO_Complet!A:R,13,FALSE)=0,"",VLOOKUP($A1833,DICO_Complet!A:R,13,FALSE)) -> 119-0046-p1 | P1833: =IF(VLOOKUP($A1833,DICO_Complet!A:R,14,FALSE)=0,"",VLOOKUP($A1833,DICO_Complet!A:R,14,FALSE)) -> 059-0046-p1 | Q1833: =IF(VLOOKUP($A1833,DICO_Complet!A:R,15,FALSE)=0,"",VLOOKUP($A1833,DICO_Complet!A:R,15,FALSE)) -> 056-0046-p1 | R1833: =IF(VLOOKUP($A1833,DICO_Complet!A:R,16,FALSE)=0,"",VLOOKUP($A1833,DICO_Complet!A:R,16,FALSE)) | S1833: =IF(VLOOKUP($A1833,DICO_Complet!A:R,17,FALSE)=0,"",VLOOKUP($A1833,DICO_Complet!A:R,17,FALSE)) | T1833: =IF(VLOOKUP($A1833,DICO_Complet!A:R,18,FALSE)=0,"",VLOOKUP($A1833,DICO_Complet!A:R,18,FALSE))

Sheet DICO_Complet
A1: Reference | B1: N/A | C1: Segment Message | D1: Object | E1: Attribute | F1: Type | G1: Sensitivity | H1: Colonne2 | I1: Obsolete | J1: Libellé | K1: Commentaire | L1: CIFO | M1: CBAE | N1: CB2AF | O1: CB2A | P1: VISA | Q1: MCD | R1: Mainframe
A2: 241112000000 | B2: XXX | C2: ApiResponse | D2: error | E2: code | F2: Max20Text | G2: DNS | J2: Error code
A3: 241112000001 | B3: XXX | C3: ApiResponse | D3: error | E3: developerText | F3: Max70Text | G3: DNS | J3: Explains possible reason(s) of the error, and possible corrections
A4: 241112000003 | B4: XXX | C4: ApiResponse | D4: error | E4: moreInfo | F4: Max256Text | G4: DNS | J4: URI to documents
A5: 241112000004 | B5: XXX | C5: ApiResponse | D5: error | E5: text | F5: Max40Text | G5: DNS | J5: short text that explains the error in a language that is useful for the end-user of the service
A6: 241112000002 | B6: XXX | C6: ApiResponse | D6: httpStatus | E6: httpCode | F6: Exact3NumericText | G6: DNS | J6: Status code http
A7: 250331114316 | B7: XXX | C7: ApiResponse | D7: httpStatus | E7: requestId | F7: Max36NumericText | G7: DNS | J7: Unique ID of API response
A8: 250528104041 | C8: AuditTrail | D8: auditTrail | E8: alertDateTime | F8: ISODateTime | G8: DNS | J8: Alert date time
A9: 250717102622 | C9: AuditTrail | D9: auditTrail | E9: alertMessage | F9: Max255Text | G9: DNS | J9: Message content
A10: 250717102624 | C10: AuditTrail | D10: auditTrail | E10: alertRecipientEmailAddress | F10: EmailAddressType | G10: DSP | J10: email that received the message
A11: 250717102623 | C11: AuditTrail | D11: auditTrail | E11: alertRecipientPhoneNumber | F11: PhoneNumberText | G11: DSP | J11: Phone that received the message
A12: 250723172700 | C12: AuditTrail | D12: auditTrail | E12: auditPhoneNumber | F12: PhoneNumberType | G12: DSP | J12: Phone number with usage and security tag
A13: 250717102602 | C13: AuditTrail | D13: auditTrail | E13: auditTrailId | F13: Max255AlphaNumericText | G13: DNS | J13: Audit trail reference
A14: 250717102604 | C14: AuditTrail | D14: auditTrail | E14: auditTrailRejectReason | F14: Max255Text | G14: DNS | J14: Reason of audit trail reject
A15: 250717102603 | C15: AuditTrail | D15: auditTrail | E15: auditTrailStatus | F15: AuditTrailStatusCodeset | G15: DNS | J15: Status code of the audit trail received
A16: 250717102615 | C16: AuditTrail | D16: auditTrail | E16: awarenessDuration | F16: ISODuration | G16: DNS | J16: Period of fraud indicator evaluation
A17: 250528104035 | C17: AuditTrail | D17: auditTrail | E17: awarenessScore | F17: Max1AlphaNumericText | G17: DNS | J17: Fraud indicator
A18: 250717102636 | C18: AuditTrail | D18: auditTrail | E18: clientSubscriptionId | F18: Max255AlphaNumericText | G18: DNS | J18: Client subscription identifier
A19: 260107110015 | C19: AuditTrail | D19: auditTrail | E19: consistencyScore | F19: ConsistencyScoreCodeset | G19: DNS | J19: Authentication method usage consistency score.
... A36: 250717102637 | C36: AuditTrail | D36: auditTrail | E36: notificationStatus | F36: Max20AlphaNumericText | G36: DNS | J36: Status
A37: 250717102635 | C37: AuditTrail | D37: auditTrail | E37: notificationSubject | F37: Max255Text | G37: DNS | J37: Triggering event of the notification | K37: (temporary password, forgotten password, etc.)
A38: 250717102613 | C38: AuditTrail | D38: auditTrail | E38: numberOfAdvisorCalls | F38: Max2NumericText | G38: DNS | J38: Number of phone calls with an advisor in the 2 months preceding disputed payment
A39: 250717102614 | C39: AuditTrail | D39: auditTrail | E39: numberOfCallCenterCalls | F39: Max2NumericText | G39: DNS | J39: Number of CRC phone calls in the 2 months preceding the disputed payment
A40: 250717102616 | C40: AuditTrail | D40: auditTrail | E40: numberOfConnectedPeriods | F40: Max3NumericText | G40: DNS | J40: Number of 15-day periods in which the user has logged in at least once.
A41: 250528104048 | C41: AuditTrail | D41: auditTrail | E41: numberOfMobileConnections | F41: Max2NumericText | G41: DNS | J41: Count of in-app connexion
A42: 250528104043 | C42: AuditTrail | D42: auditTrail | E42: numberOfSecurePayments | F42: Max5NumericText | G42: DNS | J42: Number of autorised operation
A43: 250528104044 | C43: AuditTrail | D43: auditTrail | E43: numberOfSecurePaymentsDuration | F43: ISODuration | G43: DNS | J43: Duration used to count the number of autorised operation
A44: 250528104045 | C44: AuditTrail | D44: auditTrail | E44: numberOfUndisputedSecurePayments | F44: Max5NumericText | G44: DNS | J44: Count of undisputed operation
A45: 250528104046 | C45: AuditTrail | D45: auditTrail | E45: numberOfUndisputedSecurePaymentsDuration | F45: ISODuration | G45: DNS | J45: Duration used to count the number of undisputed operation
A46: 250528104049 | C46: AuditTrail | D46: auditTrail | E46: numberOfWebConnections | F46: Max2NumericText | G46: DNS | J46: Count of browser-based conexion
A47: 250717102627 | C47: AuditTrail | D47: auditTrail | E47: oldness | F47: Max1AlphaNumericText | G47: DNS | J47: Score defining time since last enrollment prior to disputed payment
A48: 260107110013 | C48: AuditTrail | D48: auditTrail | E48: onlineBankingConnectionAuthenticationMethod | F48: AuthenticationMethodCodeset | G48: DNS | J48: Method used for the strong authentication
A49: 260107110011 | C49: AuditTrail | D49: auditTrail | E49: onlineBankingConnectionDateTime | F49: ISODateTime | G49: DNS | J49: Banking connection date time
... A69: 251212151300 | C69: Context | D69: acceptanceChannel | E69: acceptanceChannelId | F69: Exact8Text | G69: DNS | J69: Acceptance Channel Unique Identifier
A70: 250401134500 | B70: XXX | C70: Context | D70: acceptanceChannel | E70: acceptanceMode | F70: AcceptanceModeCodeset | G70: DNS | J70: Payment Acceptance Channel Mode | O70: N/A
A71: 250922172100 | C71: Context | D71: acceptanceChannel | E71: acceptorUrlAddress | F71: EmailAddressType | G71: DNS | J71: Email address of the eCommerce site. Used to verify the email address
A72: 250428083000 | C72: Context | D72: acceptanceChannel | E72: additionalInvoiceIndicator | F72: TrueFalseIndicator | G72: DNS | J72: Additional Invoice Indicator
A73: 250721161907 | C73: Context | D73: acceptanceChannel | E73: allowedAllCurrency | F73: TrueFalseIndicator | G73: DNS | J73: Allowed all currency
A74: 250324111900 | B74: XXX | C74: Context | D74: acceptanceChannel | E74: allowedCurrency | F74: ISO3NumericCurrencyCode | G74: DNS | J74: Merchant Processing Allowed Currencies | O74: N/A
A75: 250324114000 | B75: XXX | C75: Context | D75: acceptanceChannel | E75: allowedScheme | F75: AllowedSchemeCodeset | G75: DNS | J75: Merchant allowed schemes
A76: 250428083400 | C76: Context | D76: acceptanceChannel | E76: authorisationFloorLimit | F76: AmountType | G76: DNS | J76: Autorisation Floor Limit
A77: 250428082600 | C77: Context | D77: acceptanceChannel | E77: authorisationForcingIndicator | F77: TrueFalseIndicator | G77: DNS | J77: Autorisation Forcing Indicator
A78: 250721161914 | C78: Context | D78: acceptanceChannel | E78: authorisedOrEstimatedAmount | F78: AmountType | G78: DNS | J78: Authorised Or Estimated Amount
A79: 250604110100 | B79: XXX | C79: Context | D79: acceptanceChannel | E79: cardBlockingListDistribution | F79: CardBlockingListDistributionCodeset | G79: DNS | I79: Obsolete | J79: List of blocked zones
A80: 251118173700 | C80: Context | D80: acceptanceChannel | E80: cardholderTicketFooterMessage | F80: Max40Text | G80: DNS | J80: Cardholder Ticket Footer Message
A81: 251118173500 | C81: Context | D81: acceptanceChannel | E81: cardholderTicketHeaderMessage | F81: Max40Text | G81: DNS | J81: Cardholder Ticket Header Message
A82: 251118173000 | C82: Context | D82: acceptanceChannel | E82: cardholderTicketPrintIndicator | F82: TrueFalseIndicator | G82: DNS | J82: Cardholder Ticket Print Indicator
A83: 250919145800 | C83: Context | D83: acceptanceChannel | E83: cardValidityCheck | F83: TrueFalseIndicator | G83: DNS | J83: Data used by the remote configuration service to enable card expiry date verification on the merchant's device.
A84: 250428083250 | C84: Context | D84: acceptanceChannel | E84: contactlessCreditIndicator | F84: TrueFalseIndicator | G84: DNS | J84: Contactless Credit Indicator
A85: 250415115300 | B85: XXX | C85: Context | D85: acceptanceChannel | E85: creditIndicator | F85: TrueFalseIndicator | G85: DNS | J85: Credit Indicator
A86: 241112000113 | B86: XXX | C86: Context | D86: acceptanceChannel | E86: cryptoCurrencyIndicator | F86: TrueFalseIndicator | G86: DNS | J86: Crypto Currency Indicator | K86: detail du champ merchantAdditionalData | L86: AUT368
A87: 250415115400 | B87: XXX | C87: Context | D87: acceptanceChannel | E87: forbiddenCardProduct | F87: ForbiddenCardProductCodeset | G87: DNS | J87: Forbidden Card Product
A88: 250721161913 | C88: Context | D88: acceptanceChannel | E88: maxCumulAmount | F88: AmountType | G88: DNS | J88: Max Cumul Amount
A89: 250428083500 | C89: Context | D89: acceptanceChannel | E89: maximumAuthorisedAmount | F89: AmountType | G89: DNS | J89: Maximum Authorised Amount
A90: 250401140000 | B90: XXX | C90: Context | D90: acceptanceChannel | E90: maximumAuthorisedCredit | F90: AmountType | G90: DNS | J90: Credit maximum authorised amount and currency | K90: Terminal Parameter use
A91: 250401135900 | B91: XXX | C91: Context | D91: acceptanceChannel | E91: maximumAuthorisedDebit | F91: AmountType | G91: DNS | J91: Debit maximum authorised amount and currency | K91: Terminal Parameter use
A92: 250721161917 | C92: Context | D92: acceptanceChannel | E92: maxOfferAmount | F92: AmountType | G92: DNS | J92: Max Offer Amount
A93: 250721161916 | C93: Context | D93: acceptanceChannel | E93: maxOfflineDays | F93: Max3NumericText | G93: DNS | J93: Max Offline Days
A94: 241112000120 | B94: XXX | C94: Context | D94: acceptanceChannel | E94: merchantCategoryCode | F94: ISO18245MerchantCategoryCode | G94: DNS | J94: Merchant Category Code | L94: ISO18 | M94: 018 | N94: 018 | O94: 018 | Q94: DE 018
A95: 251027112325 | C95: Context | D95: acceptanceChannel | E95: merchantCategoryCodeLabel | F95: Max255Text | G95: DNS | J95: Merchant Category Code Label
A96: 250415115700 | B96: XXX | C96: Context | D96: acceptanceChannel | E96: merchantSchemeChoice | F96: BrandCodeset | G96: DNS | J96: Merchant Scheme Choice
A97: 251118173400 | C97: Context | D97: acceptanceChannel | E97: merchantTicketFooterMessage | F97: Max40Text | G97: DNS | J97: Merchant Ticket Footer Message
A98: 250428083550 | C98: Context | D98: acceptanceChannel | E98: merchantTicketHeaderMessage | F98: Max40Text | G98: DNS | J98: Merchant Ticket Header Message
A99: 250721161910 | C99: Context | D99: acceptanceChannel | E99: merchantTicketLocalisationPlate | F99: Max20AlphaNumericText | G99: DSP | J99: Merchant Ticket Localisation Plate
A100: 250721161909 | C100: Context | D100: acceptanceChannel | E100: merchantTicketNamePlate | F100: Max20AlphaNumericText | G100: DSP | J100: Merchant Ticket Name Plate
A101: 250415115600 | B101: XXX | C101: Context | D101: acceptanceChannel | E101: merchantTicketPrintIndicator | F101: TrueFalseIndicator | G101: DNS | J101: Merchant Ticket Print Indicator
A102: 250401135500 | B102: XXX | C102: Context | D102: acceptanceChannel | E102: noShowIndicator | F102: TrueFalseIndicator | G102: DNS | J102: No Show Indicator
A103: 250428082800 | C103: Context | D103: acceptanceChannel | E103: panTruncationIndicator | F103: TrueFalseIndicator | G103: DNS | J103: Pan Truncated Indicator
A104: 250428082900 | C104: Context | D104: acceptanceChannel | E104: partialAuthorisationIndicator | F104: TrueFalseIndicator | G104: DNS | J104: Partial Autorisation Indicator
A105: 250415115500 | B105: XXX | C105: Context | D105: acceptanceChannel | E105: paymentRiskProfile | F105: Exact3Text | G105: DNS | J105: Payment Risk Profile
A106: 250721161918 | C106: Context | D106: acceptanceChannel | E106: paymentUse | F106: PaymentUseCodeset | G106: DNS | J106: Payment Use
A107: 250721161912 | C107: Context | D107: acceptanceChannel | E107: preauthorisationTimeLimit | F107: Max2NumericText | G107: DNS | J107: Preauthorisation Time Limit
A108: 250401134800 | B108: XXX | C108: Context | D108: acceptanceChannel | E108: readingMode | F108: ReadingModeCodeset | G108: DNS | J108: Payment Reading Mode
A109: 250721161915 | C109: Context | D109: acceptanceChannel | E109: reversalFloorLimit | F109: AmountType | G109: DNS | J109: Reversal Floor Limit
A110: 250428083300 | C110: Context | D110: acceptanceChannel | E110: singleTapIndicator | F110: TrueFalseIndicator | G110: DNS | J110: Single Tap Indicator
A111: 250415114700 | B111: XXX | C111: Context | D111: acceptanceChannel | E111: telecomIndicator | F111: Exact2Text | G111: DNS | J111: Telecom Indicator
A112: 250721161911 | C112: Context | D112: acceptanceChannel | E112: transactionCaptureTime | F112: ISOTime | G112: DNS | J112: Transaction Capture Time
A113: 250428083200 | C113: Context | D113: acceptanceChannel | E113: whiteListeDistributionIndicator | F113: TrueFalseIndicator | G113: DNS | J113: White List Distribution Indicator
A114: 251024124501 | C114: Context | D114: callingData | E114: callDateTime | F114: ISODateTime | G114: DNS | J114: Date Time in local region
A115: 251024124507 | C115: Context | D115: callingData | E115: callerCategory | F115: CallerCategoryCodeset | G115: DNS | J115: Interlocutor type
A116: 251029113900 | C116: Context | D116: callingData | E116: callNumber | F116: Max5NumericText | G116: DNS | J116: Call count number
A117: 251024124505 | C117: Context | D117: callingData | E117: callReason | F117: CallCaseReasonCodeset | G117: DNS | J117: Reason of the call
A118: 251024124510 | C118: Context | D118: callingData | E118: callResult | F118: CallResultCodeset | G118: DNS | J118: Result of the call
A119: 251024124506 | C119: Context | D119: callingData | E119: callSubReason | F119: CallCaseSubReasonCodeset | G119: DNS | J119: Subreason of the call
A120: 251024124509 | C120: Context | D120: callingData | E120: fraudAlertDateTime | F120: ISODateTime | G120: DNS | J120: Date Time of the associated fraud
A121: 251024124508 | C121: Context | D121: callingData | E121: fraudAlertReference | F121: Max255AlphaNumericText | G121: DNS | J121: Reference of the alert CRC
A122: 251024124502 | C122: Context | D122: callingData | E122: incomingCallIndicator | F122: TrueFalseIndicator | G122: DNS | J122: Is an incoming call
A123: 251024124504 | C123: Context | D123: callingData | E123: internalEntityName | F123: Max100Text | G123: DNS | J123: Branch name
... A165: 250617090013 | C165: Context | D165: cardAgreementParameters | E165: usageRestrictionStartDateTime | F165: ISODateTime | G165: DNS | J165: startDateTime
A166: 250331114321 | B166: XXX | C166: Context | D166: cardContext | E166: acquiringChannel | F166: AcquiringChannelCodeset | G166: DNS | J166: Indicates through which channel the action is triggered
A167: 241112000005 | B167: XXX | C167: Context | D167: cardContext | E167: actionOnCard | F167: ActivationCardCodeset | G167: DNS | J167: Action on card during transaction (activated, desactivated) | K167: Activated, Desactivated or Nothing | L167: AUT358/ AUT359
A168: 250331162616 | B168: XXX | C168: Context | D168: cardContext | E168: activationCodeForNoShowInvoice | F168: Exact1AlphaNumericText | G168: DNS | J168: Activation code for no-show invoice | N168: 053-0033 en 1.3 mais plus en 1.6
A169: 250331162615 | B169: XXX | C169: Context | D169: cardContext | E169: activCodePLBSInvoiceRemoteModeOrPreAuthProlongTransaction | F169: Exact1AlphaNumericText | G169: DNS | J169: Activation code for invoice for the reservation and rental of goods or services in remote mode
A170: 250331162617 | B170: XXX | C170: Context | D170: cardContext | E170: additionalInvoiceActivationCode | F170: Exact1AlphaNumericText | G170: DNS | J170: Additional invoice activation code | N170: 072-DF07-p13
A171: 260211115200 | C171: Context | D171: cardContext | E171: blockingDateTime | F171: ISODateTime | G171: DNS | J171: Blocking date and time
A172: 250410114322 | B172: XXX | C172: Context | D172: cardContext | E172: blockingReasonCode | F172: BlockingReasonCodeset | G172: DNS | J172: Blocking reason code
A173: 251110110003 | C173: Context | D173: cardContext | E173: blockingReference | F173: Max36IdentifierText | G173: DNS | J173: Blocking reference
A174: 250410114323 | B174: XXX | C174: Context | D174: cardContext | E174: blockingRegulatoryReasonCode | F174: BlockingRegulatoryReasonCodeset | G174: DNS | J174: BlockingRegulatoryReasonCodeset
A175: 251125100015 | C175: Context | D175: cardContext | E175: cardRiskLevel | F175: Max10AlphaNumericText | G175: DNS | J175: Represents the level of risk linked to the card
A176: 250617090116 | C176: Context | D176: cardContext | E176: cardSelectionCode | F176: CardSelectionCodeset | G176: DNS | J176: Card filter selection code
...

Sheet TypesSimples
A1: Libellés | B1: Définiton | C1: Type | D1: Pattern | E1: FractionD | F1: TotalD | G1: minLength /mininclusive | H1: maxLength | I1: Commentaire
A2: 4Or6NumericText | B2: Number of objects represented as a positive integer. | C2: string | D2: ([0-9]{4}|[0-9]{6})
A3: Base25OneRate | B3: Rate expressed as a decimal | C3: string | D3: [0-9]{1,25}(\.?[0-9]{0,13})? | I3: 25 max avant la virgule et 13 max après la virgule
A4: DecimalRate | B4: decimal Amount | C4: string | D4: [0-9]{1,8}(\.?[0-9]{0,7})? | I4: 8 max avant la virgule et 7 max après la virgule
A5: EmailAddressType | B5: Email address | C5: email | I5: Max 99+'@'+39+'.'+20 = Max 160
A6: Exact107AlphaNumericText | B6: 107 alphanumeric and special characters | C6: string | D6: [0-9A-Za-z]{107}
A7: Exact10AlphaNumericText | B7: 10 alphanumeric characters | C7: string | D7: [0-9A-Za-z]{10}
A8: Exact10HexBinaryText | B8: Specifies a character string with an exact length of 10 binary bytes (20 hexadecimal text characters) | C8: string | D8: ([0-9A-F][0-9A-F]){10}
A9: Exact10NumericText | B9: Specifies a numeric string with an exact length of 10 digits. | C9: string | D9: [0-9]{10}
A10: Exact10Text | B10: 10 alphanumeric and special characters | C10: string | G10: 10 | H10: 10
A11: Exact11NumericText | B11: Specifies a numeric string with an exact length of 11 digits. | C11: string | D11: [0-9]{11}
A12: Exact11Text | B12: 11 alphanumeric and special characters | C12: string | G12: 11 | H12: 11
A13: Exact12AlphaNumericText | B13: 12 alphanumeric characters | C13: string | D13: [0-9A-Za-z]{12}
A14: Exact12NumericText | B14: Specifies a numeric string with an exact length of 12 digits. | C14: string | D14: [0-9]{12}
A15: Exact12Text | B15: 12 alphanumeric and special characters | C15: string | G15: 12 | H15: 12
A16: Exact15AlphaNumericText | B16: 15 alphanumeric characters | C16: string | D16: [0-9A-Za-z]{15}
A17: Exact15HexBinaryText | B17: Specifies a character string with an exact length of 15 binary bytes (30 hexadecimal text characters) | C17: string | D17: ([0-9A-F][0-9A-F]){15}
A18: Exact15Text | B18: 15 alphanumeric and special characters | C18: string | G18: 15 | H18: 15
A19: Exact16AlphaNumericText | B19: 16 alphanumeric characters | C19: string | D19: [0-9A-Za-z]{16}
A20: Exact16HexBinaryText | B20: Specifies a character string with an exact length of 16 binary bytes (32 hexadecimal text characters) | C20: string | D20: ([0-9A-F][0-9A-F]){16}
A21: Exact16NumericText | B21: Specifies a numeric string with an exact length of 16 digits. | C21: string | D21: [0-9]{16}
A22: Exact16Text | B22: 16 alphanumeric and special characters | C22: string | G22: 16 | H22: 16
A23: Exact19AlphaNumericText | B23: 19 alphanumeric characters | C23: string | D23: [0-9A-Za-z]{19}
A24: Exact19HexBinaryText | B24: Specifies a character string with an exact length of 19 binary bytes (38 hexadecimal text characters) | C24: string | D24: ([0-9A-F][0-9A-F]){19}
A25: Exact1AlphaNumericText | B25: 1 alphanumeric character | C25: string | D25: [0-9A-Za-z]{1}
A26: Exact1HexBinaryText | B26: Specifies a character string with an exact length of 1 binary bytes (2 hexadecimal text characters) | C26: string | D26: ([0-9A-F][0-9A-F]){1}
A27: Exact1NumericText | B27: Specifies a numeric string with an exact length of 1 digits. | C27: string | D27: [0-9]{1}
A28: Exact1Text | B28: Specifies a string with an exact length of 1 character | C28: string | G28: 1 | H28: 1
A29: Exact20HexBinaryText | B29: Specifies a character string with an exact length of 20 binary bytes (40 hexadecimal text characters) | C29: string | D29: ([0-9A-F][0-9A-F]){20}
A30: Exact20Text | B30: 20 alphanumeric and special characters | C30: string | G30: 20 | H30: 20
A31: Exact24Text | B31: 24 alphanumeric and special characters | C31: string | G31: 24 | H31: 24
A32: Exact252HexBinaryText | B32: Specifies a character string with an exact length of 252 binary bytes (504 hexadecimal text characters) | C32: string | D32: ([0-9A-F][0-9A-F]){252}
A33: Exact2AlphaNumericText | B33: 2 alphanumeric characters | C33: string | D33: [0-9A-Za-z]{2}
A34: Exact2HexBinaryText | B34: Specifies a character string with an exact length of 2 binary bytes (4 hexadecimal text characters) | C34: string | D34: ([0-9A-F][0-9A-F]){2}
A35: Exact2NumericText | B35: Specifies a numeric string with an exact length of 2 digits. | C35: string | D35: [0-9]{2}
A36: Exact2Text | B36: 2 alphanumeric and special characters | C36: string | G36: 2 | H36: 2
A37: Exact30AlphaNumericText | B37: 30 alphanumeric and special characters | C37: string | D37: [0-9A-Za-z]{30}
A38: Exact32Text | B38: 32 alphanumeric and special characters | C38: string | G38: 32 | H38: 32
A39: Exact36Text | B39: 36 alphanumeric and special characters | C39: string | G39: 36 | H39: 36
A40: Exact3AlphaNumericText | B40: 3 alphanumeric characters | C40: string | D40: [0-9A-Za-z]{3}
A41: Exact3HexBinaryText | B41: Specifies a character string with an exact length of 3 binary bytes (6 hexadecimal text characters) | C41: string | D41: ([0-9A-F][0-9A-F]){3}
A42: Exact3NumericText | B42: Specifies a numeric string with an exact length of 3 digits. | C42: string | D42: [0-9]{3}
A43: Exact3Text | B43: 3 alphanumeric and special characters | C43: string | G43: 3 | H43: 3
A44: Exact40Text | B44: Month within a particular calendar year represented by YYYY-MM (ISO 8601). | C44: string | G44: 40 | H44: 40
A45: Exact4AlphaNumericText | B45: 4 alphanumeric characters | C45: string | D45: [0-9A-Za-z]{4}
A46: Exact4HexBinaryText | B46: Specifies a character string with an exact length of 4 binary bytes (8 hexadecimal text characters) | C46: string | D46: ([0-9A-F][0-9A-F]){4}
A47: Exact4NumericText | B47: Specifies a numeric string with an exact length of 4 digits. | C47: string | D47: [0-9]{4}
A48: Exact4Text | B48: 4 alphanumeric and special characters | C48: string | G48: 4 | H48: 4
A49: Exact5HexBinaryText | B49: Specifies a character string with an exact length of 5 binary bytes (10 hexadecimal text characters) | C49: string | D49: ([0-9A-F][0-9A-F]){5}
A50: Exact5NumericText | B50: Specifies a numeric string with an exact length of 5 digits. | C50: string | D50: [0-9]{5}
A51: Exact5Text | B51: 5 alphanumeric and special characters | C51: string | G51: 5 | H51: 5
A52: Exact6NumericText | B52: Specifies a numeric string with an exact length of 6 digits. | C52: string | D52: [0-9]{6}
A53: Exact6Text | B53: 6 alphanumeric and special characters | C53: string | G53: 6 | H53: 6
A54: Exact7AlphaNumericText | B54: Specifies a alphanumeric string with a minlength of 1 and maxlength of 7 digits | C54: string | D54: [0-9A-Za-z]{7}
A55: Exact7HexBinaryText | B55: Specifies a character string with an exact length of 7 binary bytes (14 hexadecimal text characters) | C55: string | D55: ([0-9A-F][0-9A-F]){7}
A56: Exact8AlphaNumericText | B56: 8 alphanumeric characters | C56: string | D56: [0-9A-Za-z]{8}
A57: Exact8HexBinaryText | B57: Specifies a character string with an exact length of 8 binary bytes (16 hexadecimal text characters) | C57: string | D57: ([0-9A-F][0-9A-F]){8}
A58: Exact8NumericText | B58: Specifies a numeric string with an exact length of 8 digits. | C58: string | D58: [0-9]{8}
A59: Exact8Text | B59: 8 alphanumeric and special characters | C59: string | G59: 8 | H59: 8
A60: Exact9AlphaNumericText | B60: 9 alphanumeric and special characters | C60: string | D60: [0-9A-Za-z]{9}
A61: IBANIdentifier | B61: The International Bank Account Number is a code used internationally by financial institutions to uniquely identify the account of a customer at a financial institution as described in the 2007 edition of the ISO 13616 standard Banking and related financial services International Bank Account Number (IBAN) and replaced by the more recent edition of the standard. | C61: string | D61: [A-Z]{2}[0-9]{2}[a-zA-Z0-9]{1,30}
A62: ImpliedCurrencyAndAmount | B62: Number of monetary units specified in a currency where the unit of currency is implied by the context and compliant with ISO 4217. The decimal separator is a dot. | C62: string | D62: \-?[0-9]{1,18}(\.?[0-9]{0,5})? | I62: Examples : 12.3 / -5.01 / 15.12345 / -123456.12345 Definition : CAPE et ATICA Number of monetary units specified in a currency where the unit of currency is implied by the context and compliant with ISO 4217. The decimal separator is a dot. Note: a zero amount is considered a positive amount. Format : minInclusive 0 / totalDigits 18 / fractionDigits 5
A63: ImpliedFeeCurrencyAndAmount | B63: Number of monetary units FOR FEE specified in a currency where the unit of currency is implied by the context and compliant with ISO 4217. The decimal separator is a dot.Less interger number of digit and until 10 digit for decimal number. | C63: string | D63: \-?[0-9]{1,5}(\.?[0-9]{0,10})? | I63: Examples : 1.1234567891 0.0987654321 or 0.12345 etc …
A64: ISO18245MerchantCategoryCode | B64: Code used to enable the classification of merchants into specific categories. (ISO 18245). | C64: string | D64: [0-9]{4} | I64: Code used to enable the classification of merchants into specific categories based on the type of business, trade or services supplied. Values are specified only for those merchant categories that are generally expected to originate retail financial transactions (ISO 18245). The code is checked against the list of merchant categories coded with four digit characters, defined in the standar
A65: ISO2AlphaNumericCountryCode | B65: Code to identify a country, a dependency, or another area of particular geopolitical interest (ISO 3166, Text -2 code) | C65: string | D65: [A-Z]{2}
A66: ISO3AlphabeticCurrencyCode | B66: Code to identify the Currency | C66: string | D66: [A-Z]{3}
A67: ISO3AlphaNumericCountryCode | B67: Code to identify a country, a dependency, or another area of particular geopolitical interest (ISO 3166, Text -3 code) | C67: string | D67: [A-Z]{3} | G67: 3 | H67: 3
A68: ISO3AlphaNumericCurrencyCode | B68: Code to identify the Currency (ISO 4217) | C68: string | D68: [A-Z]{3}
A69: ISO3NumericCountryCode | B69: Code to identify a country, a dependency, or another area of particular geopolitical interest (ISO 3166, Numeric-3 code) | C69: string | D69: [0-9]{3} | I69: Code to identify a country, a dependency, or another area of particular geopolitical interest, on the basis of country names obtained from the United Nations (ISO 3166, Numeric-3 code). The code is checked against the list of country names coded with three digit characters, defined in the standard.
A70: ISO3NumericCurrencyCode | B70: Code to identify the Currency (ISO 4217) | C70: string | D70: [0-9]{3}
A71: ISOCountrySubdivisionCode | B71: Code to identify an area of geopolitical interest, based on names obtained from the United Nations ISO 3166-2 or the local authority | C71: string | D71: [A-Z]{2,3} | I71: ISO 3166-2
A72: ISODate | B72: Date within a particular calendar year represented by YYYY-MM-DD (ISO 8601). Ex : 2018-11-13 | C72: date | I72: Format : YYYY-MM-DD ; Example 2024-12-31
A73: ISODateTime | B73: The dateTime is specified in the following form <YYYY-MM-DDThh:mm:ss[Timezone]> Ex : 2018-11-13T20:20:39+01:00 - 2018-11-13T20:20:39-04:00 - 2018-11-13T20:20:39+00:00 = 2018-11-13T20:20:39Z | C73: date-time | I73: Definition: A particular point in the progression of time defined by a mandatory date and a mandatory time component - Voir onglet ISODateTime
A74: ISODuration | B74: Represents a duration in the format P(n)Y(n)M(n)DT(n)H(n)M(n)S | C74: duration | I74: Extract Json-Schema : A duration as defined by the ISO 8601 ABNF for "duration". For example P3D express a duration of three days.
A75: ISOMax3ALanguageCode | B75: Identification of the language name in accordance with ISO 639-1 and ISO 639-2. | C75: string | D75: [a-z]{2,3} | I75: Identification of the language name in accordance with ISO 639-1 and ISO 639-2. The type is validated by the list of values coded with two or three alphabetic characters, defined in the standard.
A76: ISOTime | B76: Time is specified in the following form <hh:mm:ssz> Ex : 20:20:39+00:00 | C76: time | I76: Format hh:mm::ssz
A77: ISOYearMonth | B77: Month within a particular calendar year represented by YYYY-MM (ISO 8601). | C77: string | D77: ([0-9]{4})-(1[0-2]|0[1-9]) | I77: Format : YYYY-MM ; Example 2024-12
A78: JWECompact | B78: JWE compact serialization | C78: string | D78: [A-Za-z0-9_-]+\.[A-Za-z0-9_-]+\.[A-Za-z0-9_-]*\.[A-Za-z0-9_-]*\.[A-Za-z0-9_-]+
A79: Max1000AlphaNumericText | B79: Specifies an alphanumeric string with a minlength of 1 and maxlength of 1000 digits | C79: string | D79: [0-9A-Za-z]{1,1000}
A80: Max1000Text | B80: Specifies a character string with a minlength of 1 and maxlength of 1000 characters | C80: string | G80: 1 | H80: 1000
A81: Max100Text | B81: Specifies a character string with a minlength of 1 and maxlength of 100 characters. | C81: string | G81: 1 | H81: 100
A82: Max10AlphaNumericText | B82: Specifies an alphanumeric string with a minlength of 1 and maxlength of 10 digits | C82: string | D82: [0-9A-Za-z]{1,10}
A83: Max10HexBinaryText | B83: Specifies a character string with a maximum length of 10 binary bytes (20 hexadecimal text characters) | C83: string | D83: ([0-9A-F][0-9A-F]){1,10}
A84: Max10NumericText | B84: Specifies a numeric string with a minlength of 1 and maxlength of 10 digits. | C84: string | D84: [0-9]{1,10}
A85: Max10Text | B85: Specifies a character string with a minlength of 1 and maxlength of 10 characters. | C85: string | G85: 1 | H85: 10
A86: Max115HexbinaryText | B86: Specifies a character string with a maximum length of 115 binary bytes (330 hexadecimal text characters) | C86: string | D86: ([0-9A-F][0-9A-F]){1,115}
A87: Max11AlphaNumericText | B87: Specifies an alphanumeric string with a minlength of 1 and maxlength of 11 digits | C87: string | D87: [0-9A-Za-z]{1,11}
A88: Max11NumericText | B88: Specifies a numeric string with a minlength of 1 and maxlength of 11 digits. | C88: string | D88: [0-9]{1,11}
A89: Max11Text | B89: Specifies a character string with a minlength of 1 and maxlength of 10 characters. | C89: string | G89: 1 | H89: 11
A90: Max128HexBinaryText | B90: Specifies a character string with a maximum length of 128 binary bytes (256 hexadecimal text characters) | C90: string | D90: ([0-9A-F][0-9A-F]){1,128}
A91: Max12AlphaNumericText | B91: Specifies a alphanumeric string with a minlength of 1 and maxlength of 12 digits | C91: string | D91: [0-9A-Za-z]{1,12}
A92: Max12NumericText | B92: Specifies a alphanumeric string with a minlength of 1 and maxlength of 12 digits | C92: string | D92: [0-9]{1,12}
A93: Max12Text | B93: Specifies a character string with a minlength of 1 and maxlength of 12 characters | C93: string | G93: 1 | H93: 12
A94: Max13AlphaNumericText | B94: Specifies a alphanumeric string with a minlength of 1 and maxlength of 13 digits | C94: string | D94: [0-9A-Za-z]{1,13}
A95: Max14AlphaNumericText | B95: Specifies a alphanumeric string with a minlength of 1 and maxlength of 14 digits | C95: string | D95: [0-9A-Za-z]{1,14}
A96: Max14NumericText | B96: Specifies a numeric string with a minlength of 1 and maxlength of 14 digits | C96: string | D96: [0-9]{1,14}
A97: Max14Text | B97: Specifies a character string with a minlength of 1 and maxlength of 14 characters. | C97: string | G97: 1 | H97: 14
A98: Max1500Text | B98: Specifies a character string with a minlength of 1 and maxlength of 1500 characters. | C98: string | G98: 1 | H98: 1500
A99: Max150HexBinaryText | B99: Specifies a character string with a maximum length of 150 binary bytes (300 hexadecimal text characters) | C99: string | D99: ([0-9A-F][0-9A-F]){1,150}
A100: Max150Text | B100: Specifies a character string with a minlength of 1 and maxlength of 150 characters | C100: string | G100: 1 | H100: 150
...

Sheet TypesStructures
A1: Structure | B1: Attributes | C1: Typologie | D1: Explication | E1: Commentaires
A2: AdditionalDataType | B2: complement | C2: Max255Text
A3: AdditionalDataType | B3: typeData | C3: Max50Text
A4: AdditionalDataType | B4: value | C4: Max3000Text
A5: AmountType | B5: accountUsage | C5: AccountUsageCodeset
A6: AmountType | B6: amount | C6: ImpliedCurrencyAndAmount
A7: AmountType | B7: amountDescription | C7: Max35Text | D7: Short description of amount
A8: AmountType | B8: conversionDateTime | C8: ISODateTime
A9: AmountType | B9: currency | C9: ISO3NumericCurrencyCode
A10: AmountType | B10: exchangeRate | C10: Base25OneRate
A11: AmountType | B11: originalAmount | C11: ImpliedCurrencyAndAmount | E11: Montant dans la devise du porteur et incluant les "charges" de la transaction
A12: AmountType | B12: originalCurrency | C12: ISO3NumericCurrencyCode | E12: Devise du porteur,
A13: AuthenticationMethodType | B13: additionalInformation | C13: Max256Text | D13: Authentication method additional informations.
A14: AuthenticationMethodType | B14: category | C14: Max20Text | D14: Authentication method type.
A15: AuthenticationMethodType | B15: enrolmentChoiceIndicator | C15: TrueFalseIndicator | D15: Authentication method used for enrolment indicator
A16: AuthenticationMethodType | B16: value | C16: Max256Text | D16: Authentication method value, linked to the authentication method type.
A17: ContactType | B17: civility | C17: Max16Text | D17: Civility
A18: ContactType | B18: email | C18: EmailAddressType
A19: ContactType | B19: fax | C19: PhoneNumberText
A20: ContactType | B20: firstName | C20: Max70Text | D20: firstName
A21: ContactType | B21: language | C21: ISOMax3ALanguageCode
A22: ContactType | B22: lastName | C22: Max70Text | D22: lastName
A23: ContactType | B23: name | C23: Max70Text
A24: ContactType | B24: phone | C24: PhoneNumberText
A25: ContactType | B25: postalAddress | C25: PostalAddressType | D25: Postal Address
A26: CountryReferenceType | B26: countryCodeAN2 | C26: ISO2AlphaNumericCountryCode
A27: CountryReferenceType | B27: countryCodeAN3 | C27: ISO3AlphaNumericCountryCode
A28: CountryReferenceType | B28: countryCodeN3 | C28: ISO3NumericCountryCode
A29: CountryReferenceType | B29: countryName | C29: Max20Text
A30: CurrencyReferenceType | B30: currencyCodeAN3 | C30: ISO3AlphaNumericCurrencyCode
A31: CurrencyReferenceType | B31: currencyCodeN3 | C31: ISO3NumericCurrencyCode
A32: CurrencyReferenceType | B32: currencyName | C32: Max20Text
A33: CurrencyReferenceType | B33: decimalNumber | C33: Exact1NumericText
A34: DownloadingParameterTableType | B34: identifier | C34: TableIdentifierCodeset | D34: Table identifier
A35: DownloadingParameterTableType | B35: validityAfter | C35: TrueFalseIndicator | D35: status table
A36: DownloadingParameterTableType | B36: validityBefore | C36: TrueFalseIndicator | D36: status table
A37: DownloadingParameterTableType | B37: versionAfter | C37: Exact4NumericText | D37: Table version number
A38: DownloadingParameterTableType | B38: versionBefore | C38: Exact4Text | D38: Table version number
A39: EmailHeaderType | B39: cc | C39: Max3000Text | D39: cc field
A40: EmailHeaderType | B40: cci | C40: Max3000Text | D40: cci field
A41: EmailHeaderType | B41: date | C41: ISODateTime | D41: date
A42: EmailHeaderType | B42: from | C42: Max30Text | D42: Sender email address
A43: EmailHeaderType | B43: object | C43: Max30Text | D43: Email subject
A44: EmailHeaderType | B44: to | C44: Max30Text | D44: Destination email address
A45: ExchangeRateInformationType | B45: exchangeRate | C45: Base25OneRate
A46: ExchangeRateInformationType | B46: exchangeRateOrigin | C46: ExchangeRateOriginCodeset
A47: ExchangeRateInformationType | B47: exchangeRateProvider | C47: Max70Text
A48: ExchangeRateInformationType | B48: network | C48: NetworkCodeset
A49: ExchangeRateInformationType | B49: persistentFxEligibleIndicator | C49: TrueFalseIndicator
A50: ExchangeRateInformationType | B50: rateDiffPercent | C50: Exact6NumericText
A51: ExchangeRateInformationType | B51: rateDiffSign | C51: DebitCreditCodeset
A52: ExchangeRateInformationType | B52: rateTableId | C52: Max5AlphaNumericText
A53: FeeAmountType | B53: amountDescription | C53: Max35Text | D53: Short description of amount
A54: FeeAmountType | B54: conversionDateTime | C54: ISODateTime
A55: FeeAmountType | B55: currency | C55: ISO3NumericCurrencyCode
A56: FeeAmountType | B56: exchangeRate | C56: Base25OneRate
A57: FeeAmountType | B57: feeAmount | C57: ImpliedFeeCurrencyAndAmount
A58: FeeAmountType | B58: originalCurrency | C58: ISO3NumericCurrencyCode | E58: Devise du porteur,
A59: FeeAmountType | B59: originalFeeAmount | C59: ImpliedFeeCurrencyAndAmount | E59: Montant dans la devise du porteur et incluant les "charges" de la transaction
A60: FeesType | B60: conversionDateTime | C60: ISODateTime
A61: FeesType | B61: currency | C61: ISO3NumericCurrencyCode
A62: FeesType | B62: debitCredit | C62: DebitCreditCodeset
A63: FeesType | B63: exchangeRate | C63: Base25OneRate
A64: FeesType | B64: feesAmount | C64: ImpliedFeeCurrencyAndAmount
A65: FeesType | B65: feesDescription | C65: Max35Text | D65: Short description of the Fee amount
A66: FeesType | B66: feesDescriptor | C66: Max35Text | D66: Identification of specific fee
A67: FeesType | B67: feesNature | C67: FeesNatureCodeset
A68: FeesType | B68: feesOtherNature | C68: Max35Text | D68: Additional information for specify the type of fee
A69: FeesType | B69: feesProgram | C69: Max35Text | D69: Identification of fee program
A70: FeesType | B70: originalCurrency | C70: ISO3NumericCurrencyCode
A71: KeyValueType | B71: key | C71: Max70Text | D71: Universal usage with string
A72: KeyValueType | B72: value | C72: Max70Text | D72: Universal usage with string
A73: LimitType | B73: limitAmount | C73: ImpliedCurrencyAndAmount | D73: montant de la limite
A74: LimitType | B74: limitDescription | C74: Max35Text | D74: description de la limite
A75: LimitType | B75: limitId | C75: LimitTypeIDCodeset | D75: Identifiant de la limite
A76: OnlinePinKeysType | B76: identifier | C76: Max15HexBinaryText | D76: The Identifier data element is formated as indicated in field 72 type DFAB description
A77: OnlinePinKeysType | B77: identifierLength | C77: Exact2NumericText | D77: LIST OF ONLINE PIN KEYS is a TLV structure
A78: OnlinePinKeysType | B78: version | C78: ISODateTime | D78: Version (YYYYMMDDhh (GMT))
A79: OptionalServicesSupportedType | B79: partialApprovalIndicator | C79: Exact1NumericText | D79: 59.805 subElement (bit 1) - OBSOLETE
A80: OptionalServicesSupportedType | B80: purchaseApprovalIndicator | C80: Exact1NumericText | D80: 59.805 subElement (bit 2) - OBSOLETE
A81: OptionalServicesSupportedType | B81: reversalIndicator | C81: Exact1NumericText | D81: 59.805 subElement (bit 3) - OBSOLETE
A82: OptionalServicesSupportedType | B82: singleTapIndicator | C82: Exact1NumericText | D82: 59.805 subElement (bit 4) - OBSOLETE
... A107: PostalAddressType | B107: townNameLocation | C107: Max70Text | D107: Additionnal Address 3 - for city
A108: ProcessorCardDataType | B108: cardLevel | C108: CardLevelCodeset
A109: ProcessorCardDataType | B109: cardUsage | C109: CardUsageCodeset
A110: ProcessorIssuerDataType | B110: issuerPlace | C110: IssuerPlaceCodeset
A111: ProcessorIssuerDataType | B111: issuerZone | C111: IssuerZoneCodeset
A112: ReferenceAttachmentType | B112: attachmentId | C112: Exact16AlphaNumericText | D112: Folder reference
A113: ReferenceAttachmentType | B113: process | C113: Max5AlphaNumericText | D113: Process type
A114: ReservedUseDataType | B114: complement | C114: Max255Text | D114: Information on the reserve use data
A115: ReservedUseDataType | B115: typeData | C115: Max50Text | D115: Name of the reserve use data
A116: ReservedUseDataType | B116: value | C116: Max3000Text | D116: Value of the reserve use data
A117: SchemeFeesType | B117: bilateralAgreementID | C117: Max75Text | D117: ID of the bilateral agreement
A118: SchemeFeesType | B118: billingId | C118: Max20Text | D118: The billing identifier for the ICS (as appering on the invoice) | E118: Estimation, max 20
A119: SchemeFeesType | B119: fixedOrCalculatedAmountInfo | C119: FeeAmountType | D119: Fixed amount or calculated amount proportional to the operation (rate)
A120: SchemeFeesType | B120: rechargeable | C120: TrueFalseIndicator | D120: Yes the billing fee is directly chargeable to the merchant
A121: SchemeFeesType | B121: regionApplied | C121: MastercardRegionCodeset | D121: World region, Mastercard specific | E121: "ASPA", "CNDA", …...
A122: SchemeFeesType | B122: schemeFeesAmountInfo | C122: FeeAmountType | D122: Amount when scheme fee is expressed as amount (in settlement currency)
A123: SchemeFeesType | B123: schemeFeesAmountNature | C123: SchemeFeesAmountNatureCodeset | D123: For fee expressed as amount, specify whether it corresponds to floor, a cap, or by default fixed (an amount without particular meaning) | E123: FIXD=fixed (default), MINI=minimum, MAXI=maximum
A124: SchemeFeesType | B124: schemeFeesCategory | C124: SchemeFeesCategoryCodeset | D124: Quantity-based (amount or number) or Amount-based (% rate or bps (e.g 0,01% = 0,0001 $ Base Point)) | E124: Operation, Licence, Processing, Subscription, Penalties
...

Sheet Codeset
A1: Codeset | B1: Format | C1: Data | D1: Data Comment | E1: Ctrl Nbcar
A2: AcceptanceLevelCodeCodeset | B2: Exact4Text | C2: DENI | D2: 2 = Denied | E2: =LEN(C2) -> 4
A3: AcceptanceLevelCodeCodeset | B3: Exact4Text | C3: FORB | D3: 3 = Forbidden | E3: =LEN(C3) -> 4
A4: AcceptanceLevelCodeCodeset | B4: Exact4Text | C4: MONT | D4: 1 = Monitored | E4: =LEN(C4) -> 4
A5: AcceptanceLevelCodeCodeset | B5: Exact4Text | C5: NORM | D5: 0 = Normal | E5: =LEN(C5) -> 4
A6: AcceptanceLevelCodeCodeset | B6: Exact4Text | C6: PRIV | D6: 4 = Private | E6: =LEN(C6) -> 4
A7: AcceptanceLevelCodeCodeset | B7: Exact4Text | C7: TEST | D7: 8 =Test | E7: =LEN(C7) -> 4
A8: AcceptanceModeCodeset | B8: Exact4Text | C8: FFPM | D8: Face to face payment | E8: =LEN(C8) -> 4
A9: AcceptanceModeCodeset | B9: Exact4Text | C9: RMPM | D9: Remote payment | E9: =LEN(C9) -> 4
A10: AcceptanceModeCodeset | B10: Exact4Text | C10: UTPM | D10: Unattended payment | E10: =LEN(C10) -> 4
A11: AcceptanceSystemCurrentConnectingModeCodeset | B11: Exact4Text | C11: DELI | D11: X25 dedicated line | E11: =LEN(C11) -> 4
A12: AcceptanceSystemCurrentConnectingModeCodeset | B12: Exact4Text | C12: GPRI | D12: GPRS IP | E12: =LEN(C12) -> 4
A13: AcceptanceSystemCurrentConnectingModeCodeset | B13: Exact4Text | C13: GSMI | D13: GSM IP | E13: =LEN(C13) -> 4
... A1729: IcsSettlementServiceCodeset | B1729: Exact4Text | C1729: WSAL | D1729: Mastercard Wholesale Settlement Service | E1729: =LEN(C1729) -> 4

Sheet ANNEXES

Sheet Statistiques
A1: Type | B1: NB Dico Complet | C1: NB Types Structurés
A2: AdditionalDataType | B2: =COUNTIF(DICO_Complet!$F$1:$F$1725,$A2) -> 15 | C2: =COUNTIF(TypesStructures!$C$2:$C$502,$A2) -> 0 | F2: TrueFalseIndicator
A3: AmountType | B3: =COUNTIF(DICO_Complet!$F$1:$F$1725,$A3) -> 81 | C3: =COUNTIF(TypesStructures!$C$2:$C$502,$A3) -> 0 | F3: String Text | G3: =SUMIF($A$2:$A$500,RIGHT($A2,4)="Text") -> 0
A4: AuthenticationMethodType | B4: =COUNTIF(DICO_Complet!$F$1:$F$1725,$A4) -> 1 | C4: =COUNTIF(TypesStructures!$C$2:$C$502,$A4) -> 0
A5: Base25OneRate | B5: =COUNTIF(DICO_Complet!$F$1:$F$1725,$A5) -> 2 | C5: =COUNTIF(TypesStructures!$C$2:$C$502,$A5) -> 5
A6: ContactType | B6: =COUNTIF(DICO_Complet!$F$1:$F$1725,$A6) -> 7 | C6: =COUNTIF(TypesStructures!$C$2:$C$502,$A6) -> 0
A7: CountryReferenceType | B7: =COUNTIF(DICO_Complet!$F$1:$F$1725,$A7) -> 3 | C7: =COUNTIF(TypesStructures!$C$2:$C$502,$A7) -> 0
A8: CurrencyReferenceType | B8: =COUNTIF(DICO_Complet!$F$1:$F$1725,$A8) -> 1 | C8: =COUNTIF(TypesStructures!$C$2:$C$502,$A8) -> 0
A9: DecimalRate | B9: =COUNTIF(DICO_Complet!$F$1:$F$1725,$A9) -> 1 | C9: =COUNTIF(TypesStructures!$C$2:$C$502,$A9) -> 0
A10: DownloadingParameterTableType | B10: =COUNTIF(DICO_Complet!$F$1:$F$1725,$A10) -> 1 | C10: =COUNTIF(TypesStructures!$C$2:$C$502,$A10) -> 0
A11: EmailAddressType | B11: =COUNTIF(DICO_Complet!$F$1:$F$1725,$A11) -> 13 | C11: =COUNTIF(TypesStructures!$C$2:$C$502,$A11) -> 1
A12: EmailHeaderType | B12: =COUNTIF(DICO_Complet!$F$1:$F$1725,$A12) -> 1 | C12: =COUNTIF(TypesStructures!$C$2:$C$502,$A12) -> 0
A13: Exact10HexBinaryText | B13: =COUNTIF(DICO_Complet!$F$1:$F$1725,$A13) -> 3 | C13: =COUNTIF(TypesStructures!$C$2:$C$502,$A13) -> 0
A14: Exact10NumericText | B14: =COUNTIF(DICO_Complet!$F$1:$F$1725,$A14) -> 1 | C14: =COUNTIF(TypesStructures!$C$2:$C$502,$A14) -> 0
A15: Exact11NumericText | B15: =COUNTIF(DICO_Complet!$F$1:$F$1725,$A15) -> 3 | C15: =COUNTIF(TypesStructures!$C$2:$C$502,$A15) -> 0
... A213: UUIDType | B213: =COUNTIF(DICO_Complet!$F$1:$F$1725,$A213) -> 18 | C213: =COUNTIF(TypesStructures!$C$2:$C$502,$A213) -> 0
B214: =SUM(B2:B213) -> 1415 | C214: =SUM(C2:C213) -> 108

Sheet Obsoletes-Retirés
A1: Référence | B1: N/A | C1: Segment Message | D1: Object | E1: Attribute | F1: Type | G1: Sensitivity | H1: Colonne2 | I1: Obsolète | J1: Libellé | K1: Commentaire | L1: CIFO | M1: CBAE | N1: CB2AF | O1: CB2A | P1: VISA | Q1: MCD | R1: Mainframe | S1: temp_ Data | T1: Demander Par | U1: New Element Checking | V1: Type Checking | W1: Type Case Checking
A2: 241112000060 | B2: XXX | C2: Context | D2: transactionContext | E2: uuidContainerCategory | F2: UUIDContainerCategoryCodeset | G2: DNS | I2: Obsolete | J2: Type of UUID Container | L2: RSB57_23_p1 | M2: 057-0023-p1 | N2: 059-0023-p1 | O2: 056-0023-p1 | Q2: DE 48 SE 66 SF2 | V2: UUIDContainerCategoryCodeset | W2: TRUE
A3: 241112000061 | B3: XXX | C3: Context | D3: transactionContext | E3: uuidContainerValue | F3: Exact36Text | G3: DNS | I3: Obsolete | J3: Value of UUID Container | L3: RSB57_23_p2 | M3: 057-0023-p2 | N3: 059-0023 p2 | O3: 056-0023-p2 | Q3: DE 48 SE 66 SF2 | V3: Exact36Text | W3: TRUE
A4: 241112000131 | B4: XXX | C4: Environment | D4: merchant | E4: postalAddress | F4: PostalAddressType | G4: DNS | I4: Obsolete | J4: Postal Address | L4: ISO43_p2 | M4: 043 -p2 | N4: 043 -p2 | O4: 043-p2 | Q4: DE 43 | V4: PostalAddressType | W4: TRUE
A5: 241112000190 | B5: XXX | C5: Transaction | D5: transactionDetails | E5: accountUsage | F5: AccountUsageCodeset | G5: DNS | I5: Obsolete | J5: Account - Usage | K5: à creuser avec expert metier | L5: ISO54 | M5: [054] | V5: AccountUsageCodeset | W5: TRUE
A6: 241112000197 | B6: XXX | C6: Transaction | D6: transactionDetails | E6: cardBrandApplied | F6: BrandCodeset | G6: DNS | I6: Obsolete | J6: Brand selected | L6: RSB57_3 | M6: 057-0003 | N6: 059-0003 | O6: 056-0003 | P6: field 104 Dataset ID 57 Tag 84 | Q6: DE 112 SE 098 | V6: BrandCodeset | W6: TRUE
A7: 241112000212 | B7: XXX | C7: Transaction | D7: originalTransactionData | E7: originalUniqueIdentifier | F7: Max50Text | G7: DNS | I7: Obsolete | J7: Debit unique reference identifier | K7: Comme RSB47_99 | L7: RSB119_0047 | M7: 119-0047 | N7: 059-0047 | O7: 119-0047 | Q7: DE 48 SE63 | V7: Max50Text | W7: TRUE
A8: 241112000213 | B8: XXX | C8: Transaction | D8: transactionDetails | E8: originalUniqueIdentifier | F8: Max50Text | G8: DNS | I8: Obsolete | J8: Original unique transaction identifier | L8: RSB47_99 | M8: 047-99 | N8: 047-99 | O8: 047-99 | P8: field 125, Usage 2, Dataset ID 03, tag 03 | Q8: DE 48 SE63, DE 105 SE 001 | V8: Max50Text | W8: TRUE
A9: 241112000215 | B9: XXX | C9: Environment | D9: card | E9: primaryAccountNumberL4D | F9: Exact4NumericText | G9: DNS | I9: Obsolete | J9: Last four digits of PAN | L9: RSB105_10 | M9: 105-10 | V9: Exact4NumericText | W9: TRUE
A10: 250317120001 | B10: XXX | C10: Context | D10: transactionContext | E10: tracabilityEventID | F10: UUIDType | G10: DNS | I10: Obsolete | J10: Traceability event (PC80) unique and non ambiguous identifier. | K10: Remplacé par 3 valeurs distinctes | V10: UUIDType | W10: TRUE
A11: 250324131102 | B11: XXX | C11: Transaction | D11: disputeData | E11: statusLabel | F11: Max255Text | G11: DNS | I11: Obsolete | J11: Label of the status | V11: Max255Text | W11: TRUE
A12: 250401135200 | B12: XXX | C12: Context | D12: merchantParameters | E12: paymentProtocolCategory | F12: PaymentProtocolCategoryCodeset | G12: DNS | I12: Obsolete | J12: Payment Protocol Category | V12: ERREUR | W12: FALSE
A13: 250401135400 | B13: XXX | C13: Context | D13: merchantParameters | E13: paymentProtocolVersion | F13: PaymentProtocolVersionCodeset | G13: DNS | I13: Obsolete | J13: Payment Protocol version | V13: ERREUR | W13: FALSE
A14: 250401140100 | B14: XXX | C14: Context | D14: merchantParameters | E14: creditGroupingIndicator | F14: TrueFalseIndicator | G14: DNS | I14: Obsolete | J14: Credit grouping indicator | V14: TrueFalseIndicator | W14: TRUE
A15: 250401140400 | B15: XXX | C15: Context | D15: merchantParameters | E15: transactionPaperStatementIndicator | F15: TrueFalseIndicator | G15: DNS | I15: Obsolete | J15: Transaction Paper Statement Indicator | V15: TrueFalseIndicator | W15: TRUE
A16: 250401140500 | B16: XXX | C16: Context | D16: merchantParameters | E16: transactionNumericStatementIndicator | F16: TrueFalseIndicator | G16: DNS | I16: Obsolete | J16: Transaction Numeric Statement Indicator | V16: TrueFalseIndicator | W16: TRUE
A17: 250401140800 | B17: XXX | C17: Context | D17: merchantParameters | E17: fraudReportingIndicator | F17: TrueFalseIndicator | G17: DNS | I17: Obsolete | J17: Fraud reporting indicator | V17: TrueFalseIndicator | W17: TRUE
A18: 250408114000 | B18: XXX | C18: Environment | D18: merchant | E18: internationalBankAccountNumber | F18: IBANIdentifier | G18: DSS | I18: Obsolete | J18: International Bank Account Number | V18: IBANIdentifier | W18: TRUE
A19: 250408114600 | B19: XXX | C19: Context | D19: merchantParameters | E19: mainGroupingIdentifier | F19: MainGroupingIdentifierCodeset | G19: DNS | I19: Obsolete | J19: Main Grouping Identifier | V19: MainGroupingIdentifierCodeset | W19: TRUE
A20: 250408114700 | B20: XXX | C20: Context | D20: merchantParameters | E20: secundaryGroupingIdentifier | F20: SecundaryGroupingIdentifierCodeset | G20: DNS | I20: Obsolete | J20: Secondary Grouping Identifier | V20: SecundaryGroupingIdentifierCodeset | W20: TRUE
